// converted by version  [v3.1.0]
// on Tue Jul 06 15:18:05 PDT 2021

.package javacard/framework {
	.aid 0xA0:0x0:0x0:0x0:0x62:0x1:0x1;
	.version 1.8;

	.imports {
		0xA0:0x0:0x0:0x0:0x62:0x0:0x1 1.0;		//java/lang
		0xA0:0x0:0x0:0x0:0x62:0x3:0x1 1.0;		//com/sun/javacard/impl
		0xA0:0x0:0x0:0x0:0x62:0x0:0x2 1.0;		//java/io
		0xA0:0x0:0x0:0x0:0x62:0x2:0x8:0x7 1.0;		//javacardx/framework/time
		0xA0:0x0:0x0:0x0:0x62:0x2:0x8:0x1 1.1;		//javacardx/framework/util
		0xA0:0x0:0x0:0x0:0x62:0x2:0x8:0x4 1.0;		//javacardx/framework/string
		0xA0:0x0:0x0:0x0:0x62:0x2:0x9 1.0;		//javacardx/apdu
		0xA0:0x0:0x0:0x0:0x62:0x1:0x2 1.7;		//javacard/security
	}

	.constantPool {
		// 0
		instanceFieldRef byte[] AID/theAID;
		// 1
		instanceFieldRef byte[] CardRuntimeException/theSw;
		// 2
		instanceFieldRef boolean[] OwnerPIN/flags;
		// 3
		instanceFieldRef byte[] OwnerPIN/triesLeft;
		// 4
		instanceFieldRef byte OwnerPIN/tryLimit;
		// 5
		instanceFieldRef byte[] OwnerPIN/pinValue;
		// 6
		instanceFieldRef byte OwnerPIN/pinSize;
		// 7
		instanceFieldRef byte OwnerPIN/maxPINSize;
		// 8
		instanceFieldRef 1.13 Applet/thePrivAccess;
		// 9
		instanceFieldRef byte[] CardException/theSw;
		// 10
		instanceFieldRef 1.15[] Resources/staticResources;
		// 11
		instanceFieldRef 1.12 T0APDUImpl/thePackedBoolean;
		// 12
		instanceFieldRef byte T0APDUImpl/incomingFlag;
		// 13
		instanceFieldRef byte T0APDUImpl/determinedLE;
		// 14
		instanceFieldRef byte T0APDUImpl/sendInProgressFlag;
		// 15
		instanceFieldRef byte T0APDUImpl/outgoingFlag;
		// 16
		instanceFieldRef byte T0APDUImpl/outgoingLenSetFlag;
		// 17
		instanceFieldRef byte T0APDUImpl/noChainingFlag;
		// 18
		instanceFieldRef byte T0APDUImpl/noGetResponseFlag;
		// 19
		instanceFieldRef byte T0APDUImpl/extendedAPDUFlag;
		// 20
		instanceFieldRef byte T0APDUImpl/envelopeFlag;
		// 21
		instanceFieldRef byte T0APDUImpl/extendedSupportFlag;
		// 22
		instanceFieldRef byte[] T0APDUImpl/scratchBuffer;
		// 23
		instanceFieldRef byte[] T0APDUImpl/buffer;
		// 24
		instanceFieldRef 1.12 T1APDUImpl/thePackedBoolean;
		// 25
		instanceFieldRef byte T1APDUImpl/incomingFlag;
		// 26
		instanceFieldRef byte T1APDUImpl/determinedLE;
		// 27
		instanceFieldRef byte T1APDUImpl/sendInProgressFlag;
		// 28
		instanceFieldRef byte T1APDUImpl/outgoingFlag;
		// 29
		instanceFieldRef byte T1APDUImpl/outgoingLenSetFlag;
		// 30
		instanceFieldRef byte T1APDUImpl/extendedAPDUFlag;
		// 31
		instanceFieldRef byte T1APDUImpl/type16Flag;
		// 32
		instanceFieldRef byte T1APDUImpl/extendedSupportFlag;
		// 33
		instanceFieldRef byte[] T1APDUImpl/buffer;
		// 34
		instanceFieldRef byte T1APDUImpl/noChainingFlag;
		// 35
		staticMethodRef 1.6.49()S;		// com/sun/javacard/impl/NativeMethods.E2P_Available()S
		// 36
		staticMethodRef 1.6.51()S;		// com/sun/javacard/impl/NativeMethods.rtr_Available()S
		// 37
		staticMethodRef 1.6.50()S;		// com/sun/javacard/impl/NativeMethods.dtr_Available()S
		// 38
		staticMethodRef 1.6.52([SS)V;		// com/sun/javacard/impl/NativeMethods.availableEEPROM([SS)V
		// 39
		staticMethodRef 1.6.54([SS)V;		// com/sun/javacard/impl/NativeMethods.availableRTR([SS)V
		// 40
		staticMethodRef 1.6.53([SS)V;		// com/sun/javacard/impl/NativeMethods.availableDTR([SS)V
		// 41
		virtualMethodRef 1.13.6(Ljavacard/framework/AID;B)Ljavacard/framework/Shareable;;		// getSharedObject(Ljavacard/framework/AID;B)Ljavacard/framework/Shareable;
		// 42
		virtualMethodRef 1.13.14(Z)V;		// setGCRequestedFlag(Z)V
		// 43
		staticMethodRef 1.6.41()B;		// com/sun/javacard/impl/NativeMethods.getCurrentlySelectedChannel()B
		// 44
		staticMethodRef 1.6.38()B;		// com/sun/javacard/impl/NativeMethods.getMaxChannels()B
		// 45
		staticMethodRef 1.6.15()B;		// com/sun/javacard/impl/NativeMethods.getCardInterfaceCount()B
		// 46
		virtualMethodRef AID/equals(Ljava/lang/Object;)Z;
			.descriptor	Ljava/lang/Object;	0.0;

		// 47
		staticMethodRef 1.6.29(BB)B;		// com/sun/javacard/impl/NativeMethods.getChannelContext(BB)B
		// 48
		staticMethodRef CardRuntimeException/<init>(S)V;
		// 49
		staticFieldRef APDUException APDUException/systemInstance;
		// 50
		virtualMethodRef CardRuntimeException/setReason(S)V;
		// 51
		staticMethodRef 1.6.32(Ljava/lang/Object;)V;		// com/sun/javacard/impl/NativeMethods.checkPreviousContextAccess(Ljava/lang/Object;)V
			.descriptor	Ljava/lang/Object;	0.0;

		// 52
		staticMethodRef Util/arrayCopy([BS[BSS)S;
		// 53
		staticMethodRef 1.6.113()V;		// com/sun/javacard/impl/NativeMethods.sensitiveResultSetTagValUnassigned()V
		// 54
		staticMethodRef PINException/throwIt(S)V;
		// 55
		staticMethodRef 1.6.110()V;		// com/sun/javacard/impl/NativeMethods.sensitiveResultSetBooleanFalse()V
		// 56
		staticFieldRef byte[] AID/bArray;
		// 57
		staticMethodRef JCSystem/makeTransientByteArray(SB)[B;
		// 58
		staticMethodRef OwnerPIN/resetTriesRemaining()V;
		// 59
		staticMethodRef JCSystem/makeTransientBooleanArray(SB)[Z;
		// 60
		virtualMethodRef OwnerPIN/setValidatedFlag(Z)V;
		// 61
		staticMethodRef 1.6.111(S)V;		// com/sun/javacard/impl/NativeMethods.sensitiveResultSet(S)V
		// 62
		virtualMethodRef OwnerPIN/getTriesRemaining()B;
		// 63
		staticMethodRef OwnerPIN/decrementTriesRemaining()V;
		// 64
		virtualMethodRef OwnerPIN/getValidatedFlag()Z;
		// 65
		virtualMethodRef OwnerPIN/isValidated()Z;
		// 66
		virtualMethodRef OwnerPIN/resetAndUnblock()V;
		// 67
		.classRef OwnerPIN;
		// 68
		staticMethodRef OwnerPIN/<init>(BB)V;
		// 69
		.classRef 1.8;		// com/sun/javacard/impl/OwnerPINxImpl
		// 70
		staticMethodRef 1.8.0(BB)V;		// com/sun/javacard/impl/OwnerPINxImpl.<init>(BB)V
		// 71
		.classRef 1.9;		// com/sun/javacard/impl/OwnerPINxWithPredecrementImpl
		// 72
		staticMethodRef 1.9.0(BB)V;		// com/sun/javacard/impl/OwnerPINxWithPredecrementImpl.<init>(BB)V
		// 73
		staticMethodRef 1.6.33(Ljava/lang/Object;Z)V;		// com/sun/javacard/impl/NativeMethods.setJCREentry(Ljava/lang/Object;Z)V
			.descriptor	Ljava/lang/Object;	0.0;

		// 74
		virtualMethodRef 1.13.1(Ljavacard/framework/Applet;)V;		// register(Ljavacard/framework/Applet;)V
		// 75
		virtualMethodRef 1.13.2(Ljavacard/framework/Applet;[BSB)V;		// register(Ljavacard/framework/Applet;[BSB)V
		// 76
		virtualMethodRef 1.13.3()Z;		// selectingApplet()Z
		// 77
		staticMethodRef 1.13.2()Lcom/sun/javacard/impl/PrivAccess;;		// com/sun/javacard/impl/PrivAccess.getPrivAccess()Lcom/sun/javacard/impl/PrivAccess;
			.descriptor	Lcom/sun/javacard/impl/PrivAccess;	1.13;

		// 78
		staticMethodRef ISOException/throwIt(S)V;
		// 79
		virtualMethodRef 1.13.4()Z;		// amIBeingReselected()Z
		// 80
		staticFieldRef APDUComm APDU/apduProtocol;
		// 81
		.classRef APDUComm;
		// 82
		staticMethodRef 1.6.14()B;		// com/sun/javacard/impl/NativeMethods.getActiveInterface()B
		// 83
		staticMethodRef 1.6.13(B)B;		// com/sun/javacard/impl/NativeMethods.getCommProtocol(B)B
		// 84
		.classRef T0APDUImpl;
		// 85
		staticMethodRef T0APDUImpl/<init>()V;
		// 86
		.classRef T1APDUImpl;
		// 87
		staticMethodRef T1APDUImpl/<init>()V;
		// 88
		staticFieldRef APDU APDU/theAPDU;
		// 89
		staticMethodRef APDU/checkErrorState()V;
		// 90
		virtualMethodRef APDU/getCurrentState()B;
		// 91
		staticMethodRef APDUException/throwIt(S)V;
		// 92
		staticMethodRef 1.13.7(BB)B;		// com/sun/javacard/impl/PrivAccess.getSelectedAppID(BB)B
		// 93
		virtualMethodRef 1.13.5()Z;		// inProcessMethod()Z
		// 94
		staticFieldRef 0.10 Dispatcher/securityException;
		// 95
		staticMethodRef APDU/checkAPDUObjectAccess()V;
		// 96
		staticMethodRef 0.2.0()V;		// java/lang/Exception.<init>()V
		// 97
		staticFieldRef CardException CardException/systemInstance;
		// 98
		.classRef AID;
		// 99
		virtualMethodRef CardException/setReason(S)V;
		// 100
		staticFieldRef PINException PINException/systemInstance;
		// 101
		virtualMethodRef CardRuntimeException/setReason(S)V;
		// 102
		virtualMethodRef AID/getBytes([BS)B;
		// 103
		staticMethodRef 1.6.128()B;		// com/sun/javacard/impl/NativeMethods.getLibraryPackageID()B
		// 104
		virtualMethodRef 1.13.9(B)Ljavacard/framework/Resources;;		// getResourceObject(B)Ljavacard/framework/Resources;
		// 105
		.classRef Resources;
		// 106
		staticMethodRef Resources/<init>()V;
		// 107
		virtualMethodRef 1.13.8(B)[Lcom/sun/javacard/impl/StaticResourceEntry;;		// getStaticResources(B)[Lcom/sun/javacard/impl/StaticResourceEntry;
			.descriptor	Lcom/sun/javacard/impl/StaticResourceEntry;	1.15;

		// 108
		staticMethodRef 1.6.34(Ljava/lang/Object;B)V;		// com/sun/javacard/impl/NativeMethods.setObjectContext(Ljava/lang/Object;B)V
			.descriptor	Ljava/lang/Object;	0.0;

		// 109
		virtualMethodRef 1.13.10(BLjavacard/framework/Resources;)V;		// setResourceObject(BLjavacard/framework/Resources;)V
		// 110
		staticMethodRef Resources/checkNullEntries()V;
		// 111
		virtualMethodRef 1.15.2()S;		// getId()S
		// 112
		virtualMethodRef 1.15.4()S;		// getSize()S
		// 113
		staticFieldRef 2.0 Dispatcher/ioException;
		// 114
		virtualMethodRef 1.15.1()[S;		// getData()[S
		// 115
		staticMethodRef JCSystem/makeArrayView(Ljava/lang/Object;SSSLjavacard/framework/Shareable;)Ljava/lang/Object;;
			.descriptor	Ljava/lang/Object;	0.0;
			.descriptor	Ljava/lang/Object;	0.0;

		// 116
		staticMethodRef 1.6.129([S)[B;		// com/sun/javacard/impl/NativeMethods.changeArrayViewType([S)[B
		// 117
		staticMethodRef 1.6.130([SS)V;		// com/sun/javacard/impl/NativeMethods.changeArrayViewLength([SS)V
		// 118
		virtualMethodRef 1.15.3()Z;		// getHalfWord()Z
		// 119
		staticMethodRef 1.6.127(SZSS)Z;		// com/sun/javacard/impl/NativeMethods.validateResourceSize(SZSS)Z
		// 120
		staticMethodRef 1.6.132([SSS)V;		// com/sun/javacard/impl/NativeMethods.checkArrayBounds([SSS)V
		// 121
		staticMethodRef 1.6.131([SS)V;		// com/sun/javacard/impl/NativeMethods.changeArrayViewDataStart([SS)V
		// 122
		staticFieldRef ISOException ISOException/systemInstance;
		// 123
		virtualMethodRef CardRuntimeException/setReason(S)V;
		// 124
		.classRef ISOException;
		// 125
		.classRef 0.1;		// java/lang/Throwable
		// 126
		staticMethodRef 1.6.66()Z;		// com/sun/javacard/impl/NativeMethods.isCardInitialized()Z
		// 127
		staticMethodRef Dispatcher/cardInit()V;
		// 128
		staticMethodRef Dispatcher/cardReset()V;
		// 129
		staticMethodRef 1.13.4()V;		// com/sun/javacard/impl/PrivAccess.resetSelectingAppletFlag()V
		// 130
		staticMethodRef 1.13.6()V;		// com/sun/javacard/impl/PrivAccess.resetProcessMethodFlag()V
		// 131
		staticFieldRef APDU Dispatcher/theAPDU;
		// 132
		virtualMethodRef APDU/complete(S)V;
		// 133
		virtualMethodRef APDU/verifyLe()V;
		// 134
		staticMethodRef Dispatcher/processAndForward()Z;
		// 135
		staticMethodRef 1.13.5()V;		// com/sun/javacard/impl/PrivAccess.setProcessMethodFlag()V
		// 136
		staticMethodRef 1.13.8(BB)Ljavacard/framework/Applet;;		// com/sun/javacard/impl/PrivAccess.getSelectedApplet(BB)Ljavacard/framework/Applet;
		// 137
		staticFieldRef Applet Dispatcher/selectedApplet;
		// 138
		.classRef 6.0;		// javacardx/apdu/ExtendedLength
		// 139
		virtualMethodRef APDU/markExtendedSupport(Z)V;
		// 140
		virtualMethodRef Applet/process(Ljavacard/framework/APDU;)V;
		// 141
		staticMethodRef JCSystem/getTransactionDepth()B;
		// 142
		staticMethodRef TransactionException/throwIt(S)V;
		// 143
		virtualMethodRef CardRuntimeException/getReason()S;
		// 144
		staticMethodRef JCSystem/abortTransaction()V;
		// 145
		staticFieldRef 1.13 Dispatcher/thePrivAccess;
		// 146
		virtualMethodRef 1.13.15()Z;		// isGarbageCollectionRequested()Z
		// 147
		staticMethodRef 1.5.4()Z;		// com/sun/javacard/impl/GarbageCollector.startGC()Z
		// 148
		staticMethodRef APDU/getCLAChannel()B;
		// 149
		staticMethodRef 1.6.37(BB)B;		// com/sun/javacard/impl/NativeMethods.getChannelStatus(BB)B
		// 150
		staticMethodRef 1.6.40(BB)V;		// com/sun/javacard/impl/NativeMethods.setCurrentlySelectedChannel(BB)V
		// 151
		virtualMethodRef APDU/getBuffer()[B;
		// 152
		virtualMethodRef APDU/isISOInterindustryCLA()Z;
		// 153
		staticMethodRef Dispatcher/setAPDUChannel(Z)V;
		// 154
		staticFieldRef byte[] Dispatcher/theAPDUBuffer;
		// 155
		virtualMethodRef APDU/isSecureMessagingCLA()Z;
		// 156
		staticFieldRef Dispatcher Dispatcher/theDispatcher;
		// 157
		virtualMethodRef Dispatcher/selectAPDU(Ljavacard/framework/APDU;)V;
		// 158
		virtualMethodRef Dispatcher/manageChannelAPDU(Ljavacard/framework/APDU;)V;
		// 159
		.classRef SystemException;
		// 160
		staticMethodRef 1.13.15(BB)V;		// com/sun/javacard/impl/PrivAccess.deselectOnly(BB)V
		// 161
		staticMethodRef 1.6.36(BBB)B;		// com/sun/javacard/impl/NativeMethods.channelManage(BBB)B
		// 162
		virtualMethodRef APDU/setOutgoing()S;
		// 163
		staticMethodRef 1.13.12(BB)V;		// com/sun/javacard/impl/PrivAccess.selectDefaultApplet(BB)V
		// 164
		staticMethodRef 1.13.14(BBB)V;		// com/sun/javacard/impl/PrivAccess.selectOnly(BBB)V
		// 165
		virtualMethodRef CardRuntimeException/getReason()S;
		// 166
		virtualMethodRef APDU/setOutgoingLength(S)V;
		// 167
		virtualMethodRef APDU/sendBytes(SS)V;
		// 168
		virtualMethodRef APDU/setIncomingAndReceive()S;
		// 169
		staticMethodRef 1.7.2([BSB)B;		// com/sun/javacard/impl/AppletMgr.findApplet([BSB)B
		// 170
		staticMethodRef 1.13.17(Ljavacard/framework/AID;)B;		// com/sun/javacard/impl/PrivAccess.getAppState(Ljavacard/framework/AID;)B
		// 171
		staticMethodRef 1.13.13(BBB)Z;		// com/sun/javacard/impl/PrivAccess.isMultiSelectionOK(BBB)Z
		// 172
		staticMethodRef 1.13.16(BBB)V;		// com/sun/javacard/impl/PrivAccess.selectApplet(BBB)V
		// 173
		staticMethodRef 1.6.28(BBBZ)Z;		// com/sun/javacard/impl/NativeMethods.setChannelContext(BBBZ)Z
		// 174
		virtualMethodRef Dispatcher/undoReceive()V;
		// 175
		virtualMethodRef APDU/undoIncomingAndReceive()V;
		// 176
		staticFieldRef short[] Dispatcher/internArraySensitiveResultStateMachine;
		// 177
		staticFieldRef short Dispatcher/lenInternArrSensitResStateMachine;
		// 178
		staticMethodRef JCSystem/makeTransientShortArray(SB)[S;
		// 179
		staticMethodRef 1.6.108([S)V;		// com/sun/javacard/impl/NativeMethods.sensitiveResultInitialize([S)V
		// 180
		staticMethodRef 1.5.2()Z;		// com/sun/javacard/impl/GarbageCollector.getSweepStarted()Z
		// 181
		staticMethodRef 1.11.13()V;		// com/sun/javacard/impl/PackageMgr.restore()V
		// 182
		staticMethodRef Dispatcher/initSystemExceptions()V;
		// 183
		.classRef Dispatcher;
		// 184
		staticMethodRef Dispatcher/<init>()V;
		// 185
		.classRef CardException;
		// 186
		staticMethodRef CardException/<init>(S)V;
		// 187
		.classRef APDUException;
		// 188
		staticMethodRef APDUException/<init>(S)V;
		// 189
		staticMethodRef ISOException/<init>(S)V;
		// 190
		.classRef PINException;
		// 191
		staticMethodRef PINException/<init>(S)V;
		// 192
		.classRef UserException;
		// 193
		staticMethodRef UserException/<init>(S)V;
		// 194
		.classRef 7.12;		// javacard/security/CryptoException
		// 195
		staticMethodRef 7.12.0(S)V;		// javacard/security/CryptoException.<init>(S)V
		// 196
		.classRef APDU;
		// 197
		staticMethodRef APDU/<init>()V;
		// 198
		.classRef 1.13;		// com/sun/javacard/impl/PrivAccess
		// 199
		staticMethodRef 1.13.0()V;		// com/sun/javacard/impl/PrivAccess.<init>()V
		// 200
		staticMethodRef 1.13.1()Lcom/sun/javacard/impl/PackedBoolean;;		// com/sun/javacard/impl/PrivAccess.getPackedBoolean()Lcom/sun/javacard/impl/PackedBoolean;
			.descriptor	Lcom/sun/javacard/impl/PackedBoolean;	1.12;

		// 201
		virtualMethodRef 1.12.1()B;		// allocate()B
		// 202
		staticMethodRef 1.5.1(B)V;		// com/sun/javacard/impl/GarbageCollector.setGCRequested(B)V
		// 203
		staticMethodRef 1.4.1()V;		// com/sun/javacard/impl/CryptoInit.initCryptoStorage()V
		// 204
		staticMethodRef 1.13.22(Ljavacard/framework/APDU;)V;		// com/sun/javacard/impl/PrivAccess.initialize(Ljavacard/framework/APDU;)V
		// 205
		staticMethodRef 1.6.65()V;		// com/sun/javacard/impl/NativeMethods.setCardInitialized()V
		// 206
		.classRef 0.5;		// java/lang/ArrayIndexOutOfBoundsException
		// 207
		staticMethodRef 0.5.0()V;		// java/lang/ArrayIndexOutOfBoundsException.<init>()V
		// 208
		staticFieldRef 0.5 Dispatcher/arrayIndexOutOfBoundsException;
		// 209
		.classRef 0.6;		// java/lang/NegativeArraySizeException
		// 210
		staticMethodRef 0.6.0()V;		// java/lang/NegativeArraySizeException.<init>()V
		// 211
		staticFieldRef 0.6 Dispatcher/negativeArraySizeException;
		// 212
		staticMethodRef 0.7.0()V;		// java/lang/NullPointerException.<init>()V
		// 213
		staticFieldRef 0.7 Dispatcher/nullPointerException;
		// 214
		.classRef 0.8;		// java/lang/ClassCastException
		// 215
		staticMethodRef 0.8.0()V;		// java/lang/ClassCastException.<init>()V
		// 216
		staticFieldRef 0.8 Dispatcher/classCastException;
		// 217
		.classRef 0.9;		// java/lang/ArithmeticException
		// 218
		staticMethodRef 0.9.0()V;		// java/lang/ArithmeticException.<init>()V
		// 219
		staticFieldRef 0.9 Dispatcher/arithmeticException;
		// 220
		.classRef 0.10;		// java/lang/SecurityException
		// 221
		staticMethodRef 0.10.0()V;		// java/lang/SecurityException.<init>()V
		// 222
		staticMethodRef 1.14.1(Ljava/lang/SecurityException;)V;		// com/sun/javacard/impl/SecurityExceptionHelper.initSE(Ljava/lang/SecurityException;)V
			.descriptor	Ljava/lang/SecurityException;	0.10;

		// 223
		.classRef 0.11;		// java/lang/ArrayStoreException
		// 224
		staticMethodRef 0.11.0()V;		// java/lang/ArrayStoreException.<init>()V
		// 225
		staticFieldRef 0.11 Dispatcher/arrayStoreException;
		// 226
		.classRef CardRuntimeException;
		// 227
		staticMethodRef SystemException/<init>(S)V;
		// 228
		staticFieldRef SystemException Dispatcher/systemException;
		// 229
		.classRef TransactionException;
		// 230
		staticMethodRef TransactionException/<init>(S)V;
		// 231
		staticFieldRef TransactionException Dispatcher/transactionException;
		// 232
		.classRef 4.1;		// javacardx/framework/util/UtilException
		// 233
		staticMethodRef 4.1.0(S)V;		// javacardx/framework/util/UtilException.<init>(S)V
		// 234
		staticFieldRef 4.1 Dispatcher/utilException;
		// 235
		.classRef 3.0;		// javacardx/framework/time/DateTimeException
		// 236
		staticMethodRef 3.0.0(S)V;		// javacardx/framework/time/DateTimeException.<init>(S)V
		// 237
		staticFieldRef 3.0 Dispatcher/dateTimeException;
		// 238
		.classRef 2.0;		// java/io/IOException
		// 239
		staticMethodRef 2.0.0()V;		// java/io/IOException.<init>()V
		// 240
		.classRef 5.0;		// javacardx/framework/string/StringException
		// 241
		staticMethodRef 5.0.0(S)V;		// javacardx/framework/string/StringException.<init>(S)V
		// 242
		staticFieldRef 5.0 Dispatcher/stringException;
		// 243
		staticFieldRef SystemException SystemException/systemInstance;
		// 244
		virtualMethodRef CardRuntimeException/setReason(S)V;
		// 245
		staticFieldRef short[] T0APDUImpl/ramShortVars;
		// 246
		staticMethodRef T0APDUImpl/getExtendedSupportFlag()Z;
		// 247
		staticFieldRef byte[] T0APDUImpl/ramByteVars;
		// 248
		staticMethodRef Util/arrayCompare([BS[BSS)B;
		// 249
		staticMethodRef 1.6.109()V;		// com/sun/javacard/impl/NativeMethods.sensitiveResultSetBooleanTrue()V
		// 250
		virtualMethodRef 1.12.2(B)Z;		// get(B)Z
		// 251
		virtualMethodRef 1.12.4(B)V;		// set(B)V
		// 252
		virtualMethodRef 1.12.5(B)V;		// reset(B)V
		// 253
		.classRef 0.7;		// java/lang/NullPointerException
		// 254
		staticMethodRef 0.0.0()V;		// java/lang/Object.<init>()V
		// 255
		staticMethodRef SystemException/throwIt(S)V;
		// 256
		staticMethodRef 0.3.0()V;		// java/lang/RuntimeException.<init>()V
		// 257
		staticMethodRef 1.13.19()B;		// com/sun/javacard/impl/PrivAccess.getCurrentAppID()B
		// 258
		staticFieldRef CardRuntimeException CardRuntimeException/systemInstance;
		// 259
		staticMethodRef 1.6.78([BSS)V;		// com/sun/javacard/impl/NativeMethods.checkArrayArgs([BSS)V
		// 260
		staticMethodRef Util/setShort([BSS)S;
		// 261
		staticMethodRef Util/getShort([BS)S;
		// 262
		staticMethodRef Util/arrayFillNonAtomic([BSSB)S;
		// 263
		staticMethodRef T0APDUImpl/isType16CLA([B)Z;
		// 264
		staticMethodRef 1.6.23()[B;		// com/sun/javacard/impl/NativeMethods.initAPDUBuffer()[B
		// 265
		virtualMethodRef CardRuntimeException/setReason(S)V;
		// 266
		staticMethodRef 1.6.24()[B;		// com/sun/javacard/impl/NativeMethods.t0InitScratchAPDUBuffer()[B
		// 267
		staticFieldRef APDUComm T0APDUImpl/theAPDU;
		// 268
		staticMethodRef T0APDUImpl/getEnvelopeFlag()Z;
		// 269
		staticMethodRef T0APDUImpl/getDeterminedLEFlag()Z;
		// 270
		staticMethodRef 1.6.18(S)S;		// com/sun/javacard/impl/NativeMethods.t0RcvData(S)S
		// 271
		staticMethodRef 1.6.25(S)S;		// com/sun/javacard/impl/NativeMethods.t0SetStatus(S)S
		// 272
		staticMethodRef 1.6.17()S;		// com/sun/javacard/impl/NativeMethods.t0SndStatusRcvCommand()S
		// 273
		staticMethodRef T0APDUImpl/processEnvelopeData(S)S;
		// 274
		staticMethodRef T0APDUImpl/getLc()S;
		// 275
		staticMethodRef T0APDUImpl/setDeterminedLEFlag()V;
		// 276
		staticMethodRef T0APDUImpl/resetEnvelopeFlag()V;
		// 277
		staticMethodRef T0APDUImpl/setLc(S)V;
		// 278
		staticMethodRef T0APDUImpl/getOutgoingFlag()Z;
		// 279
		staticMethodRef T0APDUImpl/getRemainingInbound()V;
		// 280
		staticMethodRef T0APDUImpl/setOutgoingFlag()V;
		// 281
		staticMethodRef T0APDUImpl/setCurrState(B)V;
		// 282
		staticMethodRef T0APDUImpl/getLe()S;
		// 283
		staticMethodRef T0APDUImpl/setNoChainingFlag()V;
		// 284
		staticMethodRef T0APDUImpl/getOutgoingLenSetFlag()Z;
		// 285
		virtualMethodRef T0APDUImpl/getNoChainingFlag()Z;
		// 286
		staticMethodRef T0APDUImpl/setOutgoingLenSetFlag()V;
		// 287
		staticMethodRef T0APDUImpl/setLr(S)V;
		// 288
		staticMethodRef T0APDUImpl/setExtendedAPDUFlag()V;
		// 289
		staticMethodRef T0APDUImpl/getPreReadLength()S;
		// 290
		staticMethodRef T0APDUImpl/getIncomingFlag()Z;
		// 291
		staticMethodRef T0APDUImpl/setIncomingFlag()V;
		// 292
		staticMethodRef T0APDUImpl/setIL(S)V;
		// 293
		staticMethodRef T0APDUImpl/setLe(S)V;
		// 294
		staticMethodRef T0APDUImpl/setPreReadLength(S)V;
		// 295
		staticMethodRef 1.6.22(SS)V;		// com/sun/javacard/impl/NativeMethods.t0CopyToAPDUBuffer(SS)V
		// 296
		staticMethodRef T0APDUImpl/setIncoming()V;
		// 297
		staticMethodRef T0APDUImpl/getExtendedAPDUFlag()Z;
		// 298
		virtualMethodRef T0APDUImpl/receiveBytes(S)S;
		// 299
		virtualMethodRef T0APDUImpl/getCLAChannel()B;
		// 300
		staticMethodRef 1.6.20(B)S;		// com/sun/javacard/impl/NativeMethods.t0SndGetResponse(B)S
		// 301
		staticMethodRef T0APDUImpl/setNoGetResponseFlag()V;
		// 302
		staticMethodRef T0APDUImpl/resetSendInProgressFlag()V;
		// 303
		staticMethodRef T0APDUImpl/getNoGetResponseFlag()Z;
		// 304
		staticMethodRef T0APDUImpl/getLr()S;
		// 305
		staticMethodRef T0APDUImpl/send61xx(S)S;
		// 306
		staticMethodRef T0APDUImpl/resetIncomingFlag()V;
		// 307
		staticMethodRef T0APDUImpl/getSendInProgressFlag()Z;
		// 308
		staticMethodRef 1.6.19([BSSB)S;		// com/sun/javacard/impl/NativeMethods.t0SndData([BSSB)S
		// 309
		staticMethodRef T0APDUImpl/setSendInProgressFlag()V;
		// 310
		virtualMethodRef T0APDUImpl/sendBytes(SS)V;
		// 311
		virtualMethodRef T0APDUImpl/setOutgoing()S;
		// 312
		virtualMethodRef T0APDUImpl/setOutgoingLength(S)V;
		// 313
		staticMethodRef T0APDUImpl/getCurrState()B;
		// 314
		staticMethodRef T0APDUImpl/resetOutgoingFlag()V;
		// 315
		staticMethodRef T0APDUImpl/resetOutgoingLenSetFlag()V;
		// 316
		staticMethodRef T0APDUImpl/resetNoChainingFlag()V;
		// 317
		staticMethodRef T0APDUImpl/resetNoGetResponseFlag()V;
		// 318
		staticMethodRef T0APDUImpl/resetExtendedAPDUFlag()V;
		// 319
		staticMethodRef T0APDUImpl/resetDeterminedLEFlag()V;
		// 320
		staticMethodRef T0APDUImpl/isISOInterindustryCLA([B)Z;
		// 321
		virtualMethodRef T0APDUImpl/setIncomingAndReceive()S;
		// 322
		virtualMethodRef T0APDUImpl/resetAPDU()V;
		// 323
		staticMethodRef T0APDUImpl/preProcessAPDU()V;
		// 324
		staticMethodRef T0APDUImpl/setEnvelopeFlag()V;
		// 325
		staticMethodRef Util/makeShort(BB)S;
		// 326
		staticMethodRef T0APDUImpl/undoIncomingAndReceiveForEnvelope(S)V;
		// 327
		staticMethodRef T0APDUImpl/getChannelInfo()B;
		// 328
		staticMethodRef T0APDUImpl/setLogicalChannel(B)V;
		// 329
		staticMethodRef T0APDUImpl/resetCurrState()V;
		// 330
		staticMethodRef T0APDUImpl/resetExtendedSupportFlag()V;
		// 331
		staticMethodRef T0APDUImpl/setExtendedSupportFlag()V;
		// 332
		staticMethodRef 1.6.16()S;		// com/sun/javacard/impl/NativeMethods.t0RcvCommand()S
		// 333
		staticMethodRef T0APDUImpl/processEnvelopeAPDU()V;
		// 334
		staticMethodRef 1.6.21()S;		// com/sun/javacard/impl/NativeMethods.t0Wait()S
		// 335
		virtualMethodRef T0APDUImpl/isValidCLA()Z;
		// 336
		staticMethodRef T0APDUImpl/getIL()S;
		// 337
		staticFieldRef short[] T1APDUImpl/ramShortVars;
		// 338
		staticMethodRef T1APDUImpl/getDeterminedLEFlag()Z;
		// 339
		staticMethodRef T1APDUImpl/getExtendedAPDUFlag()Z;
		// 340
		staticFieldRef byte[] T1APDUImpl/ramByteVars;
		// 341
		staticMethodRef JCSystem/requestObjectDeletion()V;
		// 342
		staticMethodRef 1.6.125(BS)Ljava/lang/Object;;		// com/sun/javacard/impl/NativeMethods.makeGlobalArray(BS)Ljava/lang/Object;
			.descriptor	Ljava/lang/Object;	0.0;

		// 343
		staticFieldRef 1.13 JCSystem/thePrivAccess;
		// 344
		virtualMethodRef 1.13.11(B)Ljavacard/framework/AID;;		// getAID(B)Ljavacard/framework/AID;
		// 345
		staticMethodRef 1.6.112(Ljava/lang/Object;)V;		// com/sun/javacard/impl/NativeMethods.sensitiveResultSetObject(Ljava/lang/Object;)V
			.descriptor	Ljava/lang/Object;	0.0;

		// 346
		virtualMethodRef 1.13.7([BSB)Ljavacard/framework/AID;;		// getAID([BSB)Ljavacard/framework/AID;
		// 347
		staticMethodRef 1.7.0()Z;		// com/sun/javacard/impl/AppletMgr.getInstallTransactionFlag()Z
		// 348
		staticMethodRef 1.6.44()V;		// com/sun/javacard/impl/NativeMethods.beginTransactionNative()V
		// 349
		staticMethodRef 1.6.46()V;		// com/sun/javacard/impl/NativeMethods.abortTransactionNative()V
		// 350
		staticMethodRef 1.6.45()V;		// com/sun/javacard/impl/NativeMethods.commitTransactionNative()V
		// 351
		staticMethodRef 1.6.31()B;		// com/sun/javacard/impl/NativeMethods.getPreviousContext()B
		// 352
		staticFieldRef APDUComm T1APDUImpl/theAPDU;
		// 353
		staticMethodRef T1APDUImpl/isType16CLA()Z;
		// 354
		staticMethodRef T1APDUImpl/resetIncomingFlag()V;
		// 355
		staticMethodRef T1APDUImpl/resetOutgoingFlag()V;
		// 356
		staticMethodRef T1APDUImpl/resetOutgoingLenSetFlag()V;
		// 357
		staticMethodRef T1APDUImpl/resetSendInProgressFlag()V;
		// 358
		staticMethodRef T1APDUImpl/resetType16Flag()V;
		// 359
		staticMethodRef T1APDUImpl/resetExtendedAPDUFlag()V;
		// 360
		staticMethodRef T1APDUImpl/resetDeterminedLEFlag()V;
		// 361
		staticMethodRef T1APDUImpl/resetNoChainingFlag()V;
		// 362
		staticMethodRef T1APDUImpl/setPreReadLength(S)V;
		// 363
		staticMethodRef T1APDUImpl/setLe(S)V;
		// 364
		staticMethodRef T1APDUImpl/setLc(S)V;
		// 365
		staticMethodRef T1APDUImpl/setLr(S)V;
		// 366
		staticMethodRef T1APDUImpl/setIL(S)V;
		// 367
		staticMethodRef T1APDUImpl/resetCurrState()V;
		// 368
		staticMethodRef T1APDUImpl/setType16Flag()V;
		// 369
		staticMethodRef T1APDUImpl/getChannelInfo()B;
		// 370
		staticMethodRef T1APDUImpl/setLogicalChannel(B)V;
		// 371
		staticMethodRef T1APDUImpl/setAPDUParameters(SSSSS)V;
		// 372
		staticMethodRef T1APDUImpl/setDeterminedLEFlag()V;
		// 373
		staticMethodRef T1APDUImpl/setExtendedAPDUFlag()V;
		// 374
		staticMethodRef T1APDUImpl/getOutgoingFlag()Z;
		// 375
		staticMethodRef 1.6.9()Z;		// com/sun/javacard/impl/NativeMethods.t1LastBlockReceived()Z
		// 376
		staticMethodRef 1.6.5()S;		// com/sun/javacard/impl/NativeMethods.t1Abort()S
		// 377
		staticMethodRef T1APDUImpl/getSendInProgressFlag()Z;
		// 378
		staticMethodRef T1APDUImpl/getLs()S;
		// 379
		staticMethodRef T1APDUImpl/getLo()S;
		// 380
		staticMethodRef 1.6.2(SSZZ)S;		// com/sun/javacard/impl/NativeMethods.t1SndBlockRcvAck(SSZZ)S
		// 381
		staticMethodRef 1.6.12()B;		// com/sun/javacard/impl/NativeMethods.getSecondaryInterfaceEvent()B
		// 382
		staticMethodRef 1.13.10()V;		// com/sun/javacard/impl/PrivAccess.powerUpContactless()V
		// 383
		staticMethodRef 1.13.11()V;		// com/sun/javacard/impl/PrivAccess.powerDownContactless()V
		// 384
		staticMethodRef 1.6.3(SS)S;		// com/sun/javacard/impl/NativeMethods.t1RcvBlock(SS)S
		// 385
		staticMethodRef T1APDUImpl/resetExtendedSupportFlag()V;
		// 386
		virtualMethodRef T1APDUImpl/resetAPDU()V;
		// 387
		staticMethodRef T1APDUImpl/preProcessAPDU(S)V;
		// 388
		staticMethodRef T1APDUImpl/getLc()S;
		// 389
		staticMethodRef T1APDUImpl/setCurrState(B)V;
		// 390
		staticMethodRef 1.6.6()S;		// com/sun/javacard/impl/NativeMethods.t1Wait()S
		// 391
		staticMethodRef T1APDUImpl/getExtendedSupportFlag()Z;
		// 392
		virtualMethodRef T1APDUImpl/isValidCLA()Z;
		// 393
		staticMethodRef 1.6.10()S;		// com/sun/javacard/impl/NativeMethods.t1GetIFSC()S
		// 394
		staticMethodRef 1.6.11()S;		// com/sun/javacard/impl/NativeMethods.t1GetIFSD()S
		// 395
		staticMethodRef 1.6.7()B;		// com/sun/javacard/impl/NativeMethods.t1GetNAD()B
		// 396
		staticMethodRef T1APDUImpl/getIncomingFlag()Z;
		// 397
		staticMethodRef T1APDUImpl/setIncomingFlag()V;
		// 398
		staticMethodRef T1APDUImpl/getPreReadLength()S;
		// 399
		staticMethodRef T1APDUImpl/getIL()S;
		// 400
		staticMethodRef 1.6.4(SS)S;		// com/sun/javacard/impl/NativeMethods.t1RcvAndDiscardData(SS)S
		// 401
		staticMethodRef T1APDUImpl/receiveBytesAndDiscard()V;
		// 402
		staticMethodRef T1APDUImpl/setOutgoingFlag()V;
		// 403
		staticMethodRef T1APDUImpl/getLe()S;
		// 404
		staticMethodRef T1APDUImpl/setNoChainingFlag()V;
		// 405
		staticMethodRef T1APDUImpl/getOutgoingLenSetFlag()Z;
		// 406
		virtualMethodRef T1APDUImpl/getNoChainingFlag()Z;
		// 407
		staticMethodRef T1APDUImpl/setOutgoingLenSetFlag()V;
		// 408
		staticMethodRef T1APDUImpl/getLr()S;
		// 409
		staticMethodRef T1APDUImpl/setLs(S)V;
		// 410
		staticMethodRef T1APDUImpl/setLo(S)V;
		// 411
		staticMethodRef T1APDUImpl/setSendInProgressFlag()V;
		// 412
		virtualMethodRef T1APDUImpl/sendBytes(SS)V;
		// 413
		staticMethodRef T1APDUImpl/setIncoming()V;
		// 414
		virtualMethodRef T1APDUImpl/receiveBytes(S)S;
		// 415
		virtualMethodRef T1APDUImpl/setOutgoing()S;
		// 416
		virtualMethodRef T1APDUImpl/setOutgoingLength(S)V;
		// 417
		staticMethodRef T1APDUImpl/getCurrState()B;
		// 418
		staticMethodRef T1APDUImpl/setExtendedSupportFlag()V;
		// 419
		staticFieldRef TransactionException TransactionException/systemInstance;
		// 420
		virtualMethodRef CardRuntimeException/setReason(S)V;
		// 421
		staticFieldRef UserException UserException/systemInstance;
		// 422
		virtualMethodRef CardException/setReason(S)V;
	}

	.interface abstract APDUComm {

		.method public abstract getLogicalChannel()B 0 {
		}

		.method public abstract getNoChainingFlag()Z 1 {
		}

		.method public abstract resetAPDU()V 2 {
		}

		.method public abstract complete(S)V 3 {
		}

		.method public abstract undoIncomingAndReceive()V 4 {
		}

		.method public abstract getCLAChannel()B 5 {
		}

		.method public abstract waitExtension()V 6 {
		}

		.method public abstract getBuffer()[B 7 {
		}

		.method public abstract getInBlockSize()S 8 {
		}

		.method public abstract getOutBlockSize()S 9 {
		}

		.method public abstract getProtocol()B 10 {
		}

		.method public abstract getNAD()B 11 {
		}

		.method public abstract setOutgoing()S 12 {
		}

		.method public abstract setOutgoingNoChaining()S 13 {
		}

		.method public abstract setOutgoingLength(S)V 14 {
		}

		.method public abstract receiveBytes(S)S 15 {
		}

		.method public abstract setIncomingAndReceive()S 16 {
		}

		.method public abstract sendBytes(SS)V 17 {
		}

		.method public abstract sendBytesLong([BSS)V 18 {
		}

		.method public abstract setOutgoingAndSend(SS)V 19 {
		}

		.method public abstract getCurrentState()B 20 {
		}

		.method public abstract getCurrentAPDUBuffer()[B 21 {
		}

		.method public abstract markExtendedSupport(Z)V 22 {
		}

		.method public abstract getIncomingLength()S 23 {
		}

		.method public abstract getOffsetCdata()S 24 {
		}

		.method public abstract isValidCLA()Z 25 {
		}

		.method public abstract isCommandChainingCLA()Z 26 {
		}

		.method public abstract isSecureMessagingCLA()Z 27 {
		}

		.method public abstract isISOInterindustryCLA()Z 28 {
		}

		.method public abstract verifyLe()V 29 {
		}

	}

	.interface public abstract AppletEvent 18 {

		.method public abstract uninstall()V 0 {
		}

	}

	.interface public abstract ISO7816 0 {

		.fields {
			public static final short SW_NO_ERROR = -28672;		// S
			public static final short SW_BYTES_REMAINING_00 = 24832;		// S
			public static final short SW_WRONG_LENGTH = 26368;		// S
			public static final short SW_SECURITY_STATUS_NOT_SATISFIED = 27010;		// S
			public static final short SW_FILE_INVALID = 27011;		// S
			public static final short SW_AUTHENTICATION_METHOD_BLOCKED = 27011;		// S
			public static final short SW_DATA_INVALID = 27012;		// S
			public static final short SW_CONDITIONS_NOT_SATISFIED = 27013;		// S
			public static final short SW_COMMAND_NOT_ALLOWED = 27014;		// S
			public static final short SW_APPLET_SELECT_FAILED = 27033;		// S
			public static final short SW_WRONG_DATA = 27264;		// S
			public static final short SW_FUNC_NOT_SUPPORTED = 27265;		// S
			public static final short SW_FILE_NOT_FOUND = 27266;		// S
			public static final short SW_RECORD_NOT_FOUND = 27267;		// S
			public static final short SW_INCORRECT_P1P2 = 27270;		// S
			public static final short SW_WRONG_P1P2 = 27392;		// S
			public static final short SW_CORRECT_LENGTH_00 = 27648;		// S
			public static final short SW_INS_NOT_SUPPORTED = 27904;		// S
			public static final short SW_CLA_NOT_SUPPORTED = 28160;		// S
			public static final short SW_UNKNOWN = 28416;		// S
			public static final short SW_FILE_FULL = 27268;		// S
			public static final short SW_LOGICAL_CHANNEL_NOT_SUPPORTED = 26753;		// S
			public static final short SW_SECURE_MESSAGING_NOT_SUPPORTED = 26754;		// S
			public static final short SW_WARNING_STATE_UNCHANGED = 25088;		// S
			public static final short SW_LAST_COMMAND_EXPECTED = 26755;		// S
			public static final short SW_COMMAND_CHAINING_NOT_SUPPORTED = 26756;		// S
			public static final byte OFFSET_CLA = 0;		// B
			public static final byte OFFSET_INS = 1;		// B
			public static final byte OFFSET_P1 = 2;		// B
			public static final byte OFFSET_P2 = 3;		// B
			public static final byte OFFSET_LC = 4;		// B
			public static final byte OFFSET_CDATA = 5;		// B
			public static final byte OFFSET_EXT_CDATA = 7;		// B
			public static final byte CLA_ISO7816 = 0;		// B
			public static final byte INS_SELECT = -92;		// B
			public static final byte INS_EXTERNAL_AUTHENTICATE = -126;		// B
		}

	}

	.interface public abstract MultiSelectable 17 {

		.method public abstract select(Z)Z 0 {
		}

		.method public abstract deselect(Z)V 1 {
		}

	}

	.interface public abstract PIN 1 {

		.method public abstract check([BSB)Z 0 {
		}

		.method public abstract getTriesRemaining()B 1 {
		}

		.method public abstract isValidated()Z 2 {
		}

		.method public abstract reset()V 3 {
		}

	}

	.interface public abstract OwnerPINx 19 {

		.superInterfaces {
			PIN;
		}

		.method public abstract check([BSB)Z 0 {
		}

		.method public abstract getTriesRemaining()B 1 {
		}

		.method public abstract isValidated()Z 2 {
		}

		.method public abstract reset()V 3 {
		}

		.method public abstract update([BSB)V 4 {
		}

		.method public abstract getTryLimit()B 5 {
		}

		.method public abstract setTryLimit(B)V 6 {
		}

		.method public abstract setTriesRemaining(B)V 7 {
		}

	}

	.interface public abstract OwnerPINxWithPredecrement 20 {

		.superInterfaces {
			PIN;
			OwnerPINx;
		}

		.method public abstract check([BSB)Z 0 {
		}

		.method public abstract getTriesRemaining()B 1 {
		}

		.method public abstract isValidated()Z 2 {
		}

		.method public abstract reset()V 3 {
		}

		.method public abstract update([BSB)V 4 {
		}

		.method public abstract getTryLimit()B 5 {
		}

		.method public abstract setTryLimit(B)V 6 {
		}

		.method public abstract setTriesRemaining(B)V 7 {
		}

		.method public abstract decrementTriesRemaining()B 8 {
		}

	}

	.interface abstract SerialComm {

		.method public abstract getProtocol()B 0 {
		}

		.method public abstract getBuffer()[B 1 {
		}

		.method public abstract receiveBytes(S)S 2 {
		}

		.method public abstract getCurrState()B 3 {
		}

		.method public abstract setCurrState(B)V 4 {
		}

		.method public abstract resetCurrState()V 5 {
		}

		.method public abstract getIncomingLength(S)S 6 {
		}

		.method public abstract getLogicalChannel()B 7 {
		}

	}

	.interface public abstract Shareable 2 {

		.shareable;

	}

	.class public AID 6 extends 0.0 {		// extends java/lang/Object

		.fields {
			 byte[] theAID 0;		// [B
			private static byte[] bArray;		// [B
		}

		.publicMethodTable 0 6 {
			equals(Ljava/lang/Object;)Z 0;
			RIDEquals(Ljavacard/framework/AID;)Z 255;
			equals([BSB)Z 255;
			getBytes([BS)B 255;
			partialEquals([BSB)Z 255;
			getPartialBytes(S[BSB)B 255;
		}

		.packageMethodTable 0 {
		}

		.method public final getBytes([BS)B 3 {
			.stack 5;
			.locals 0;

				L0:	aload_1;
					sload_2;
					getfield_a_this 0;		// reference javacard/framework/AID.theAID
					arraylength;
					invokestatic 259;		// com/sun/javacard/impl/NativeMethods.checkArrayArgs([BSS)V
					aload_1;
					invokestatic 51;		// com/sun/javacard/impl/NativeMethods.checkPreviousContextAccess(Ljava/lang/Object;)V
					getfield_a_this 0;		// reference javacard/framework/AID.theAID
					sconst_0;
					aload_1;
					sload_2;
					getfield_a_this 0;		// reference javacard/framework/AID.theAID
					arraylength;
					invokestatic 52;		// javacard/framework/Util.arrayCopy([BS[BSS)S
					pop;
					getfield_a_this 0;		// reference javacard/framework/AID.theAID
					arraylength;
					s2b;
					sreturn;
		}

		.method public final equals(Ljava/lang/Object;)Z 0 {
			.stack 5;
			.locals 2;

			.descriptor	Ljava/lang/Object;	0.0;

				L0:	invokestatic 53;		// com/sun/javacard/impl/NativeMethods.sensitiveResultSetTagValUnassigned()V
					aload_1;
					ifnonnull L2;
				L1:	invokestatic 55;		// com/sun/javacard/impl/NativeMethods.sensitiveResultSetBooleanFalse()V
					sconst_0;
					sreturn;
				L2:	aload_1;
					invokestatic 51;		// com/sun/javacard/impl/NativeMethods.checkPreviousContextAccess(Ljava/lang/Object;)V
					getstatic_a 56;		// reference javacard/framework/AID.bArray
					ifnonnull L4;
				L3:	bspush 16;
					sconst_1;
					invokestatic 57;		// javacard/framework/JCSystem.makeTransientByteArray(SB)[B
					putstatic_a 56;		// reference javacard/framework/AID.bArray
					getstatic_a 56;		// reference javacard/framework/AID.bArray
					sconst_0;
					invokestatic 73;		// com/sun/javacard/impl/NativeMethods.setJCREentry(Ljava/lang/Object;Z)V
				L4:	aload_1;
					instanceof 0 98;		// T_CLASSORINTERFACE javacard/framework/AID
					ifne L6;
				L5:	invokestatic 55;		// com/sun/javacard/impl/NativeMethods.sensitiveResultSetBooleanFalse()V
					sconst_0;
					sreturn;
				L6:	aload_1;
					checkcast 0 98;		// T_CLASSORINTERFACE javacard/framework/AID
					getstatic_a 56;		// reference javacard/framework/AID.bArray
					sconst_0;
					invokevirtual 102;		// getBytes([BS)B
					sstore_2;
				L7:	sload_2;
					sconst_m1;
					if_scmpeq L9;
				L8:	sload_2;
					getfield_a_this 0;		// reference javacard/framework/AID.theAID
					arraylength;
					if_scmpeq L10;
				L9:	invokestatic 55;		// com/sun/javacard/impl/NativeMethods.sensitiveResultSetBooleanFalse()V
					sconst_0;
					sreturn;
				L10:	getstatic_a 56;		// reference javacard/framework/AID.bArray
					sconst_0;
					getfield_a_this 0;		// reference javacard/framework/AID.theAID
					sconst_0;
					getfield_a_this 0;		// reference javacard/framework/AID.theAID
					arraylength;
					invokestatic 248;		// javacard/framework/Util.arrayCompare([BS[BSS)B
					ifne L12;
				L11:	sconst_1;
					goto L13;
				L12:	sconst_0;
				L13:	sstore_3;
				L14:	sload_3;
					ifeq L16;
				L15:	invokestatic 249;		// com/sun/javacard/impl/NativeMethods.sensitiveResultSetBooleanTrue()V
					goto L17;
				L16:	invokestatic 55;		// com/sun/javacard/impl/NativeMethods.sensitiveResultSetBooleanFalse()V
				L17:	sload_3;
					sreturn;
		}

		.method public final equals([BSB)Z 2 {
			.stack 5;
			.locals 1;

				L0:	invokestatic 53;		// com/sun/javacard/impl/NativeMethods.sensitiveResultSetTagValUnassigned()V
				L1:	aload_1;
					sload_2;
					sload_3;
					invokestatic 259;		// com/sun/javacard/impl/NativeMethods.checkArrayArgs([BSS)V
				L2:	goto L5;
				L3:	astore 4;
				L4:	invokestatic 55;		// com/sun/javacard/impl/NativeMethods.sensitiveResultSetBooleanFalse()V
					sconst_0;
					sreturn;
				L5:	aload_1;
					invokestatic 51;		// com/sun/javacard/impl/NativeMethods.checkPreviousContextAccess(Ljava/lang/Object;)V
					sload_3;
					getfield_a_this 0;		// reference javacard/framework/AID.theAID
					arraylength;
					if_scmpne L8;
				L6:	aload_1;
					sload_2;
					getfield_a_this 0;		// reference javacard/framework/AID.theAID
					sconst_0;
					sload_3;
					invokestatic 248;		// javacard/framework/Util.arrayCompare([BS[BSS)B
					ifne L8;
				L7:	sconst_1;
					goto L9;
				L8:	sconst_0;
				L9:	sstore 4;
				L10:	sload 4;
					ifeq L12;
				L11:	invokestatic 249;		// com/sun/javacard/impl/NativeMethods.sensitiveResultSetBooleanTrue()V
					goto L13;
				L12:	invokestatic 55;		// com/sun/javacard/impl/NativeMethods.sensitiveResultSetBooleanFalse()V
				L13:	sload 4;
					sreturn;
			.exceptionTable {
				// start_block end_block handler_block catch_type_index
				L1 L2 L3 253;
			}
		}

		.method public final partialEquals([BSB)Z 4 {
			.stack 5;
			.locals 1;

				L0:	invokestatic 53;		// com/sun/javacard/impl/NativeMethods.sensitiveResultSetTagValUnassigned()V
				L1:	aload_1;
					sload_2;
					sload_3;
					invokestatic 259;		// com/sun/javacard/impl/NativeMethods.checkArrayArgs([BSS)V
				L2:	goto L5;
				L3:	astore 4;
				L4:	invokestatic 55;		// com/sun/javacard/impl/NativeMethods.sensitiveResultSetBooleanFalse()V
					sconst_0;
					sreturn;
				L5:	aload_1;
					invokestatic 51;		// com/sun/javacard/impl/NativeMethods.checkPreviousContextAccess(Ljava/lang/Object;)V
					sload_3;
					getfield_a_this 0;		// reference javacard/framework/AID.theAID
					arraylength;
					if_scmple L7;
				L6:	invokestatic 55;		// com/sun/javacard/impl/NativeMethods.sensitiveResultSetBooleanFalse()V
					sconst_0;
					sreturn;
				L7:	aload_1;
					sload_2;
					getfield_a_this 0;		// reference javacard/framework/AID.theAID
					sconst_0;
					sload_3;
					invokestatic 248;		// javacard/framework/Util.arrayCompare([BS[BSS)B
					ifne L9;
				L8:	sconst_1;
					goto L10;
				L9:	sconst_0;
				L10:	sstore 4;
				L11:	sload 4;
					ifeq L13;
				L12:	invokestatic 249;		// com/sun/javacard/impl/NativeMethods.sensitiveResultSetBooleanTrue()V
					goto L14;
				L13:	invokestatic 55;		// com/sun/javacard/impl/NativeMethods.sensitiveResultSetBooleanFalse()V
				L14:	sload 4;
					sreturn;
			.exceptionTable {
				// start_block end_block handler_block catch_type_index
				L1 L2 L3 253;
			}
		}

		.method public final RIDEquals(Ljavacard/framework/AID;)Z 1 {
			.stack 5;
			.locals 1;

				L0:	invokestatic 53;		// com/sun/javacard/impl/NativeMethods.sensitiveResultSetTagValUnassigned()V
					aload_1;
					ifnonnull L2;
				L1:	invokestatic 55;		// com/sun/javacard/impl/NativeMethods.sensitiveResultSetBooleanFalse()V
					sconst_0;
					sreturn;
				L2:	aload_1;
					invokestatic 51;		// com/sun/javacard/impl/NativeMethods.checkPreviousContextAccess(Ljava/lang/Object;)V
					getstatic_a 56;		// reference javacard/framework/AID.bArray
					ifnonnull L4;
				L3:	bspush 16;
					sconst_1;
					invokestatic 57;		// javacard/framework/JCSystem.makeTransientByteArray(SB)[B
					putstatic_a 56;		// reference javacard/framework/AID.bArray
					getstatic_a 56;		// reference javacard/framework/AID.bArray
					sconst_0;
					invokestatic 73;		// com/sun/javacard/impl/NativeMethods.setJCREentry(Ljava/lang/Object;Z)V
				L4:	aload_1;
					getstatic_a 56;		// reference javacard/framework/AID.bArray
					sconst_0;
					invokevirtual 102;		// getBytes([BS)B
					sstore_2;
				L5:	sload_2;
					sconst_m1;
					if_scmpeq L8;
				L6:	getfield_a_this 0;		// reference javacard/framework/AID.theAID
					sconst_0;
					getstatic_a 56;		// reference javacard/framework/AID.bArray
					sconst_0;
					sconst_5;
					invokestatic 248;		// javacard/framework/Util.arrayCompare([BS[BSS)B
					ifne L8;
				L7:	invokestatic 249;		// com/sun/javacard/impl/NativeMethods.sensitiveResultSetBooleanTrue()V
					sconst_1;
					sreturn;
				L8:	invokestatic 55;		// com/sun/javacard/impl/NativeMethods.sensitiveResultSetBooleanFalse()V
					sconst_0;
					sreturn;
		}

		.method public final getPartialBytes(S[BSB)B 5 {
			.stack 5;
			.locals 1;

				L0:	sload 4;
					sstore 5;
				L1:	sload 4;
					ifne L3;
				L2:	getfield_a_this 0;		// reference javacard/framework/AID.theAID
					arraylength;
					sload_1;
					ssub;
					sstore 5;
				L3:	aload_2;
					sload_3;
					sload 5;
					invokestatic 259;		// com/sun/javacard/impl/NativeMethods.checkArrayArgs([BSS)V
					aload_2;
					invokestatic 51;		// com/sun/javacard/impl/NativeMethods.checkPreviousContextAccess(Ljava/lang/Object;)V
					getfield_a_this 0;		// reference javacard/framework/AID.theAID
					sload_1;
					aload_2;
					sload_3;
					sload 5;
					invokestatic 52;		// javacard/framework/Util.arrayCopy([BS[BSS)S
					pop;
					sload 5;
					s2b;
					sreturn;
		}

		.method public <init>([BSB)V 0 {
			.stack 5;
			.locals 0;

				L0:	aload_0;
					invokespecial 254;		// java/lang/Object.<init>()V
					aload_1;
					sload_2;
					sload_3;
					invokestatic 259;		// com/sun/javacard/impl/NativeMethods.checkArrayArgs([BSS)V
					aload_1;
					invokestatic 51;		// com/sun/javacard/impl/NativeMethods.checkPreviousContextAccess(Ljava/lang/Object;)V
					sload_3;
					sconst_5;
					if_scmplt L2;
				L1:	sload_3;
					bspush 16;
					if_scmple L3;
				L2:	sconst_1;
					invokestatic 255;		// javacard/framework/SystemException.throwIt(S)V
				L3:	aload_0;
					sload_3;
					newarray 11;
					putfield_a 0;		// reference javacard/framework/AID.theAID
					aload_1;
					sload_2;
					getfield_a_this 0;		// reference javacard/framework/AID.theAID
					sconst_0;
					sload_3;
					invokestatic 52;		// javacard/framework/Util.arrayCopy([BS[BSS)S
					pop;
					return;
		}

	}

	.class public CardRuntimeException 5 extends 0.3 {		// extends java/lang/RuntimeException

		.fields {
			private byte[] theSw 0;		// [B
			private static CardRuntimeException systemInstance;		// Ljavacard/framework/CardRuntimeException;
		}

		.publicMethodTable 1 3 {
			equals(Ljava/lang/Object;)Z 0;
			getReason()S 255;
			setReason(S)V 255;
		}

		.packageMethodTable 0 {
		}

		.method public <init>(S)V 0 {
			.stack 3;
			.locals 0;

				L0:	aload_0;
					invokespecial 256;		// java/lang/RuntimeException.<init>()V
					invokestatic 257;		// com/sun/javacard/impl/PrivAccess.getCurrentAppID()B
					ifne L4;
				L1:	getstatic_a 258;		// reference javacard/framework/CardRuntimeException.systemInstance
					ifnonnull L3;
				L2:	aload_0;
					putstatic_a 258;		// reference javacard/framework/CardRuntimeException.systemInstance
				L3:	aload_0;
					sconst_2;
					sconst_1;
					invokestatic 57;		// javacard/framework/JCSystem.makeTransientByteArray(SB)[B
					putfield_a 1;		// reference javacard/framework/CardRuntimeException.theSw
					goto L5;
				L4:	aload_0;
					sconst_2;
					newarray 11;
					putfield_a 1;		// reference javacard/framework/CardRuntimeException.theSw
				L5:	getfield_a_this 1;		// reference javacard/framework/CardRuntimeException.theSw
					sconst_0;
					sload_1;
					invokestatic 260;		// javacard/framework/Util.setShort([BSS)S
					pop;
					return;
		}

		.method public getReason()S 1 {
			.stack 2;
			.locals 0;

				L0:	getfield_a_this 1;		// reference javacard/framework/CardRuntimeException.theSw
					sconst_0;
					invokestatic 261;		// javacard/framework/Util.getShort([BS)S
					sreturn;
		}

		.method public setReason(S)V 2 {
			.stack 5;
			.locals 0;

				L0:	getfield_a_this 1;		// reference javacard/framework/CardRuntimeException.theSw
					sconst_0;
					sconst_1;
					sload_1;
					bspush 8;
					sushr;
					s2b;
					invokestatic 262;		// javacard/framework/Util.arrayFillNonAtomic([BSSB)S
					pop;
					getfield_a_this 1;		// reference javacard/framework/CardRuntimeException.theSw
					sconst_1;
					sconst_1;
					sload_1;
					s2b;
					invokestatic 262;		// javacard/framework/Util.arrayFillNonAtomic([BSSB)S
					pop;
					return;
		}

		.method public static throwIt(S)V 1 {
			.stack 2;
			.locals 0;

				L0:	getstatic_a 258;		// reference javacard/framework/CardRuntimeException.systemInstance
					sload_0;
					invokevirtual 265;		// setReason(S)V
					getstatic_a 258;		// reference javacard/framework/CardRuntimeException.systemInstance
					athrow;
		}

	}

	.class public final JCSystem 8 extends 0.0 {		// extends java/lang/Object

		.fields {
			public static final byte MEMORY_TYPE_PERSISTENT = 0;		// B
			public static final byte MEMORY_TYPE_TRANSIENT_RESET = 1;		// B
			public static final byte MEMORY_TYPE_TRANSIENT_DESELECT = 2;		// B
			public static final byte ARRAY_TYPE_BOOLEAN = 1;		// B
			public static final byte ARRAY_TYPE_BYTE = 2;		// B
			public static final byte ARRAY_TYPE_SHORT = 3;		// B
			public static final byte ARRAY_TYPE_INT = 4;		// B
			public static final byte ARRAY_TYPE_OBJECT = 5;		// B
			public static final short ATTR_READABLE_VIEW = 1;		// S
			public static final short ATTR_WRITABLE_VIEW = 2;		// S
			public static final byte NOT_A_TRANSIENT_OBJECT = 0;		// B
			public static final byte CLEAR_ON_RESET = 1;		// B
			public static final byte CLEAR_ON_DESELECT = 2;		// B
			private static final short API_VERSION = 769;		// S
			static 1.13 thePrivAccess;		// Lcom/sun/javacard/impl/PrivAccess;
			private static final boolean GC_SUPPORTED = 1;		// Z
		}

		.publicMethodTable 1 1 {
			equals(Ljava/lang/Object;)Z 0;
		}

		.packageMethodTable 0 {
		}

		.method  <init>()V {
			.stack 1;
			.locals 0;

				L0:	aload_0;
					invokespecial 254;		// java/lang/Object.<init>()V
					return;
		}

		.method public static native isTransient(Ljava/lang/Object;)B 10 {
			.descriptor	Ljava/lang/Object;	0.0;

		}

		.method public static native makeTransientBooleanArray(SB)[Z 12 {
		}

		.method public static native makeTransientByteArray(SB)[B 13 {
		}

		.method public static native makeTransientShortArray(SB)[S 15 {
		}

		.method public static native makeTransientObjectArray(SB)[Ljava/lang/Object; 14 {
			.descriptor	Ljava/lang/Object;	0.0;

		}

		.method public static makeGlobalArray(BS)Ljava/lang/Object; 21 {
			.stack 2;
			.locals 0;

			.descriptor	Ljava/lang/Object;	0.0;

				L0:	invokestatic 341;		// javacard/framework/JCSystem.requestObjectDeletion()V
					sload_0;
					sload_1;
					invokestatic 342;		// com/sun/javacard/impl/NativeMethods.makeGlobalArray(BS)Ljava/lang/Object;
					areturn;
		}

		.method public static native makeArrayView(Ljava/lang/Object;SSSLjavacard/framework/Shareable;)Ljava/lang/Object; 23 {
			.descriptor	Ljava/lang/Object;	0.0;
			.descriptor	Ljava/lang/Object;	0.0;

		}

		.method public static native makeBooleanArrayView([ZSSSLjavacard/framework/Shareable;)[Z 26 {
		}

		.method public static native makeByteArrayView([BSSSLjavacard/framework/Shareable;)[B 27 {
		}

		.method public static native makeShortArrayView([SSSSLjavacard/framework/Shareable;)[S 28 {
		}

		.method public static native isArrayView(Ljava/lang/Object;)Z 24 {
			.descriptor	Ljava/lang/Object;	0.0;

		}

		.method public static native getAttributes(Ljava/lang/Object;)S 25 {
			.descriptor	Ljava/lang/Object;	0.0;

		}

		.method public static getVersion()S 9 {
			.stack 1;
			.locals 0;

				L0:	sspush 769;
					sreturn;
		}

		.method public static getAID()Ljavacard/framework/AID; 3 {
			.stack 2;
			.locals 1;

				L0:	getstatic_a 343;		// reference javacard/framework/JCSystem.thePrivAccess
					invokestatic 257;		// com/sun/javacard/impl/PrivAccess.getCurrentAppID()B
					invokevirtual 344;		// getAID(B)Ljavacard/framework/AID;
					astore_0;
				L1:	aload_0;
					invokestatic 345;		// com/sun/javacard/impl/NativeMethods.sensitiveResultSetObject(Ljava/lang/Object;)V
					aload_0;
					areturn;
		}

		.method public static lookupAID([BSB)Ljavacard/framework/AID; 11 {
			.stack 4;
			.locals 2;

				L0:	aload_0;
					sconst_0;
					baload;
					sstore_3;
				L1:	getstatic_a 343;		// reference javacard/framework/JCSystem.thePrivAccess
					aload_0;
					sload_1;
					sload_2;
					invokevirtual 346;		// getAID([BSB)Ljavacard/framework/AID;
					astore 4;
				L2:	aload 4;
					invokestatic 345;		// com/sun/javacard/impl/NativeMethods.sensitiveResultSetObject(Ljava/lang/Object;)V
					aload 4;
					areturn;
		}

		.method public static beginTransaction()V 1 {
			.stack 1;
			.locals 0;

				L0:	invokestatic 347;		// com/sun/javacard/impl/AppletMgr.getInstallTransactionFlag()Z
					ifne L2;
				L1:	invokestatic 348;		// com/sun/javacard/impl/NativeMethods.beginTransactionNative()V
				L2:	return;
		}

		.method public static abortTransaction()V 0 {
			.stack 1;
			.locals 0;

				L0:	invokestatic 347;		// com/sun/javacard/impl/AppletMgr.getInstallTransactionFlag()Z
					ifne L2;
				L1:	invokestatic 349;		// com/sun/javacard/impl/NativeMethods.abortTransactionNative()V
				L2:	return;
		}

		.method public static commitTransaction()V 2 {
			.stack 1;
			.locals 0;

				L0:	invokestatic 347;		// com/sun/javacard/impl/AppletMgr.getInstallTransactionFlag()Z
					ifne L2;
				L1:	invokestatic 350;		// com/sun/javacard/impl/NativeMethods.commitTransactionNative()V
				L2:	return;
		}

		.method public static native getTransactionDepth()B 7 {
		}

		.method public static native getUnusedCommitCapacity()S 8 {
		}

		.method public static native getMaxCommitCapacity()S 5 {
		}

		.method public static getPreviousContextAID()Ljavacard/framework/AID; 6 {
			.stack 3;
			.locals 2;

				L0:	invokestatic 351;		// com/sun/javacard/impl/NativeMethods.getPreviousContext()B
					sstore_0;
				L1:	sload_0;
					ifne L3;
				L2:	aconst_null;
					invokestatic 345;		// com/sun/javacard/impl/NativeMethods.sensitiveResultSetObject(Ljava/lang/Object;)V
					aconst_null;
					areturn;
				L3:	getstatic_a 343;		// reference javacard/framework/JCSystem.thePrivAccess
					sload_0;
					bspush 15;
					sand;
					invokevirtual 344;		// getAID(B)Ljavacard/framework/AID;
					astore_1;
				L4:	aload_1;
					invokestatic 345;		// com/sun/javacard/impl/NativeMethods.sensitiveResultSetObject(Ljava/lang/Object;)V
					aload_1;
					areturn;
		}

		.method public static getAvailableMemory(B)S 16 {
			.stack 1;
			.locals 0;

				L0:	sload_0;
					stableswitch L4 0 2 L1 L2 L3;
				L1:	invokestatic 35;		// com/sun/javacard/impl/NativeMethods.E2P_Available()S
					sreturn;
				L2:	invokestatic 36;		// com/sun/javacard/impl/NativeMethods.rtr_Available()S
					sreturn;
				L3:	invokestatic 37;		// com/sun/javacard/impl/NativeMethods.dtr_Available()S
					sreturn;
				L4:	sconst_1;
					invokestatic 255;		// javacard/framework/SystemException.throwIt(S)V
					sconst_0;
					sreturn;
		}

		.method public static getAvailableMemory([SSB)V 22 {
			.stack 2;
			.locals 0;

				L0:	sload_2;
					stableswitch L4 0 2 L1 L2 L3;
				L1:	aload_0;
					sload_1;
					invokestatic 38;		// com/sun/javacard/impl/NativeMethods.availableEEPROM([SS)V
					return;
				L2:	aload_0;
					sload_1;
					invokestatic 39;		// com/sun/javacard/impl/NativeMethods.availableRTR([SS)V
					return;
				L3:	aload_0;
					sload_1;
					invokestatic 40;		// com/sun/javacard/impl/NativeMethods.availableDTR([SS)V
					return;
				L4:	sconst_1;
					invokestatic 255;		// javacard/framework/SystemException.throwIt(S)V
					return;
		}

		.method public static getAppletShareableInterfaceObject(Ljavacard/framework/AID;B)Ljavacard/framework/Shareable; 4 {
			.stack 3;
			.locals 1;

				L0:	getstatic_a 343;		// reference javacard/framework/JCSystem.thePrivAccess
					aload_0;
					sload_1;
					invokevirtual 41;		// getSharedObject(Ljavacard/framework/AID;B)Ljavacard/framework/Shareable;
					astore_2;
				L1:	aload_2;
					invokestatic 345;		// com/sun/javacard/impl/NativeMethods.sensitiveResultSetObject(Ljava/lang/Object;)V
					aload_2;
					areturn;
		}

		.method public static isObjectDeletionSupported()Z 17 {
			.stack 1;
			.locals 0;

				L0:	sconst_1;
					sreturn;
		}

		.method public static requestObjectDeletion()V 18 {
			.stack 2;
			.locals 0;

				L0:	getstatic_a 343;		// reference javacard/framework/JCSystem.thePrivAccess
					sconst_1;
					invokevirtual 42;		// setGCRequestedFlag(Z)V
					return;
		}

		.method public static getAssignedChannel()B 19 {
			.stack 1;
			.locals 0;

				L0:	invokestatic 43;		// com/sun/javacard/impl/NativeMethods.getCurrentlySelectedChannel()B
					sreturn;
		}

		.method public static isAppletActive(Ljavacard/framework/AID;)Z 20 {
			.stack 2;
			.locals 6;

				L0:	invokestatic 44;		// com/sun/javacard/impl/NativeMethods.getMaxChannels()B
					sstore_3;
				L1:	invokestatic 45;		// com/sun/javacard/impl/NativeMethods.getCardInterfaceCount()B
					sstore 4;
				L2:	aload_0;
					aconst_null;
					invokevirtual 46;		// equals(Ljava/lang/Object;)Z
					pop;
					sconst_0;
					sstore 5;
				L3:	sload 5;
					sload_3;
					if_scmpge L13;
				L4:	sconst_0;
					sstore 6;
				L5:	sload 6;
					sload 4;
					if_scmpge L12;
				L6:	sload 5;
					sload 6;
					invokestatic 47;		// com/sun/javacard/impl/NativeMethods.getChannelContext(BB)B
					sstore_1;
				L7:	sload_1;
					bspush 15;
					if_scmpeq L11;
				L8:	sload_1;
					bspush 15;
					sand;
					sstore_2;
				L9:	getstatic_a 343;		// reference javacard/framework/JCSystem.thePrivAccess
					sload_2;
					invokevirtual 344;		// getAID(B)Ljavacard/framework/AID;
					aload_0;
					invokevirtual 46;		// equals(Ljava/lang/Object;)Z
					ifeq L11;
				L10:	sconst_1;
					sreturn;
				L11:	sload 6;
					sconst_1;
					sadd;
					s2b;
					sstore 6;
					goto L5;
				L12:	sload 5;
					sconst_1;
					sadd;
					s2b;
					sstore 5;
					goto L3;
				L13:	sconst_0;
					sreturn;
		}

	}

	.class public APDUException 12 extends CardRuntimeException {

		.fields {
			public static final short ILLEGAL_USE = 1;		// S
			public static final short BUFFER_BOUNDS = 2;		// S
			public static final short BAD_LENGTH = 3;		// S
			public static final short IO_ERROR = 4;		// S
			public static final short NO_T0_GETRESPONSE = 170;		// S
			public static final short T1_IFD_ABORT = 171;		// S
			public static final short NO_T0_REISSUE = 172;		// S
			private static APDUException systemInstance;		// Ljavacard/framework/APDUException;
		}

		.publicMethodTable 3 3 {
			equals(Ljava/lang/Object;)Z 0;
			getReason()S 1;
			setReason(S)V 2;
		}

		.packageMethodTable 0 {
		}

		.method public <init>(S)V 0 {
			.stack 2;
			.locals 0;

				L0:	aload_0;
					sload_1;
					invokespecial 48;		// javacard/framework/CardRuntimeException.<init>(S)V
					getstatic_a 49;		// reference javacard/framework/APDUException.systemInstance
					ifnonnull L2;
				L1:	aload_0;
					putstatic_a 49;		// reference javacard/framework/APDUException.systemInstance
				L2:	return;
		}

		.method public static throwIt(S)V 1 {
			.stack 2;
			.locals 0;

				L0:	getstatic_a 49;		// reference javacard/framework/APDUException.systemInstance
					sload_0;
					invokevirtual 50;		// setReason(S)V
					getstatic_a 49;		// reference javacard/framework/APDUException.systemInstance
					athrow;
		}

	}

	.class public OwnerPIN 9 extends 0.0 {		// extends java/lang/Object

		.fields {
			private byte[] pinValue 0;		// [B
			private boolean[] flags 1;		// [Z
			private byte[] triesLeft 2;		// [B
			private byte tryLimit 3;		// B
			private byte maxPINSize 4;		// B
			private byte pinSize 5;		// B
			private static final byte VALIDATED = 0;		// B
			private static final byte NUMFLAGS = 1;		// B
		}

		.publicMethodTable 1 9 {
			equals(Ljava/lang/Object;)Z 0;
			check([BSB)Z 255;
			getTriesRemaining()B 255;
			getValidatedFlag()Z 255;
			isValidated()Z 255;
			reset()V 255;
			resetAndUnblock()V 255;
			setValidatedFlag(Z)V 255;
			update([BSB)V 255;
		}

		.packageMethodTable 0 {
		}

		.implementedInterfaceInfoTable { 
			.interface PIN { 
				1;		// check([BSB)Z
				2;		// getTriesRemaining()B
				4;		// isValidated()Z
				5;		// reset()V
			}

		}

		.method protected getValidatedFlag()Z 3 {
			.stack 2;
			.locals 1;

				L0:	getfield_a_this 2;		// reference javacard/framework/OwnerPIN.flags
					sconst_0;
					baload;
					sstore_1;
				L1:	sload_1;
					ifeq L3;
				L2:	invokestatic 249;		// com/sun/javacard/impl/NativeMethods.sensitiveResultSetBooleanTrue()V
					goto L4;
				L3:	invokestatic 55;		// com/sun/javacard/impl/NativeMethods.sensitiveResultSetBooleanFalse()V
				L4:	sload_1;
					sreturn;
		}

		.method protected setValidatedFlag(Z)V 7 {
			.stack 3;
			.locals 0;

				L0:	getfield_a_this 2;		// reference javacard/framework/OwnerPIN.flags
					sconst_0;
					sload_1;
					bastore;
					return;
		}

		.method private resetTriesRemaining()V {
			.stack 4;
			.locals 0;

				L0:	getfield_a_this 3;		// reference javacard/framework/OwnerPIN.triesLeft
					sconst_0;
					sconst_1;
					getfield_b_this 4;		// byte javacard/framework/OwnerPIN.tryLimit
					invokestatic 262;		// javacard/framework/Util.arrayFillNonAtomic([BSSB)S
					pop;
					return;
		}

		.method private decrementTriesRemaining()V {
			.stack 5;
			.locals 0;

				L0:	getfield_a_this 3;		// reference javacard/framework/OwnerPIN.triesLeft
					sconst_0;
					sconst_1;
					getfield_a_this 3;		// reference javacard/framework/OwnerPIN.triesLeft
					sconst_0;
					baload;
					sconst_1;
					ssub;
					s2b;
					invokestatic 262;		// javacard/framework/Util.arrayFillNonAtomic([BSSB)S
					pop;
					return;
		}

		.method public <init>(BB)V 0 {
			.stack 3;
			.locals 0;

				L0:	aload_0;
					invokespecial 254;		// java/lang/Object.<init>()V
					sload_1;
					sconst_1;
					if_scmplt L2;
				L1:	sload_2;
					sconst_1;
					if_scmpge L3;
				L2:	sconst_1;
					invokestatic 54;		// javacard/framework/PINException.throwIt(S)V
				L3:	aload_0;
					sload_2;
					newarray 11;
					putfield_a 5;		// reference javacard/framework/OwnerPIN.pinValue
					sload_2;
					putfield_b_this 6;		// byte javacard/framework/OwnerPIN.pinSize
					sload_2;
					putfield_b_this 7;		// byte javacard/framework/OwnerPIN.maxPINSize
					sload_1;
					putfield_b_this 4;		// byte javacard/framework/OwnerPIN.tryLimit
					aload_0;
					sconst_1;
					newarray 11;
					putfield_a 3;		// reference javacard/framework/OwnerPIN.triesLeft
					aload_0;
					invokespecial 58;		// javacard/framework/OwnerPIN.resetTriesRemaining()V
					aload_0;
					sconst_1;
					sconst_1;
					invokestatic 59;		// javacard/framework/JCSystem.makeTransientBooleanArray(SB)[Z
					putfield_a 2;		// reference javacard/framework/OwnerPIN.flags
					aload_0;
					sconst_0;
					invokevirtual 60;		// setValidatedFlag(Z)V
					return;
		}

		.method public getTriesRemaining()B 2 {
			.stack 2;
			.locals 1;

				L0:	getfield_a_this 3;		// reference javacard/framework/OwnerPIN.triesLeft
					sconst_0;
					baload;
					sstore_1;
				L1:	sload_1;
					invokestatic 61;		// com/sun/javacard/impl/NativeMethods.sensitiveResultSet(S)V
					sload_1;
					sreturn;
		}

		.method public check([BSB)Z 1 {
			.stack 5;
			.locals 2;

				L0:	sconst_0;
					sstore 4;
				L1:	aload_0;
					sconst_0;
					invokevirtual 60;		// setValidatedFlag(Z)V
					aload_0;
					invokevirtual 62;		// getTriesRemaining()B
					ifne L3;
				L2:	sconst_1;
					sstore 4;
					goto L4;
				L3:	aload_0;
					invokespecial 63;		// javacard/framework/OwnerPIN.decrementTriesRemaining()V
				L4:	sload_3;
					ifle L9;
				L5:	aload_1;
					sload_2;
					sload_3;
					sadd;
					sconst_1;
					ssub;
					baload;
					sstore 5;
				L6:	sload_3;
					getfield_b_this 6;		// byte javacard/framework/OwnerPIN.pinSize
					if_scmpne L8;
				L7:	sload 4;
					ifeq L9;
				L8:	invokestatic 55;		// com/sun/javacard/impl/NativeMethods.sensitiveResultSetBooleanFalse()V
					sconst_0;
					sreturn;
				L9:	aload_1;
					sload_2;
					getfield_a_this 5;		// reference javacard/framework/OwnerPIN.pinValue
					sconst_0;
					sload_3;
					invokestatic 248;		// javacard/framework/Util.arrayCompare([BS[BSS)B
					ifne L12;
				L10:	sload_3;
					getfield_b_this 6;		// byte javacard/framework/OwnerPIN.pinSize
					if_scmpne L12;
				L11:	aload_0;
					sconst_1;
					invokevirtual 60;		// setValidatedFlag(Z)V
					aload_0;
					invokespecial 58;		// javacard/framework/OwnerPIN.resetTriesRemaining()V
					invokestatic 249;		// com/sun/javacard/impl/NativeMethods.sensitiveResultSetBooleanTrue()V
					sconst_1;
					sreturn;
				L12:	invokestatic 55;		// com/sun/javacard/impl/NativeMethods.sensitiveResultSetBooleanFalse()V
					sconst_0;
					sreturn;
		}

		.method public isValidated()Z 4 {
			.stack 1;
			.locals 1;

				L0:	aload_0;
					invokevirtual 64;		// getValidatedFlag()Z
					sstore_1;
				L1:	sload_1;
					ifeq L3;
				L2:	invokestatic 249;		// com/sun/javacard/impl/NativeMethods.sensitiveResultSetBooleanTrue()V
					goto L4;
				L3:	invokestatic 55;		// com/sun/javacard/impl/NativeMethods.sensitiveResultSetBooleanFalse()V
				L4:	sload_1;
					sreturn;
		}

		.method public reset()V 5 {
			.stack 1;
			.locals 0;

				L0:	aload_0;
					invokevirtual 65;		// isValidated()Z
					ifeq L2;
				L1:	aload_0;
					invokevirtual 66;		// resetAndUnblock()V
				L2:	return;
		}

		.method public update([BSB)V 8 {
			.stack 5;
			.locals 0;

				L0:	sload_3;
					getfield_b_this 7;		// byte javacard/framework/OwnerPIN.maxPINSize
					if_scmple L2;
				L1:	sconst_1;
					invokestatic 54;		// javacard/framework/PINException.throwIt(S)V
				L2:	aload_1;
					sload_2;
					getfield_a_this 5;		// reference javacard/framework/OwnerPIN.pinValue
					sconst_0;
					sload_3;
					invokestatic 52;		// javacard/framework/Util.arrayCopy([BS[BSS)S
					pop;
					sload_3;
					putfield_b_this 6;		// byte javacard/framework/OwnerPIN.pinSize
					getfield_a_this 3;		// reference javacard/framework/OwnerPIN.triesLeft
					sconst_0;
					getfield_b_this 4;		// byte javacard/framework/OwnerPIN.tryLimit
					bastore;
					aload_0;
					sconst_0;
					invokevirtual 60;		// setValidatedFlag(Z)V
					return;
		}

		.method public resetAndUnblock()V 6 {
			.stack 2;
			.locals 0;

				L0:	aload_0;
					invokespecial 58;		// javacard/framework/OwnerPIN.resetTriesRemaining()V
					aload_0;
					sconst_0;
					invokevirtual 60;		// setValidatedFlag(Z)V
					return;
		}

	}

	.class public OwnerPINBuilder 21 extends 0.0 {		// extends java/lang/Object

		.fields {
			public static final byte OWNER_PIN = 1;		// B
			public static final byte OWNER_PIN_X = 2;		// B
			public static final byte OWNER_PIN_X_WITH_PREDECREMENT = 3;		// B
		}

		.publicMethodTable 1 1 {
			equals(Ljava/lang/Object;)Z 0;
		}

		.packageMethodTable 0 {
		}

		.method private <init>()V {
			.stack 1;
			.locals 0;

				L0:	aload_0;
					invokespecial 254;		// java/lang/Object.<init>()V
					return;
		}

		.method public static buildOwnerPIN(BBB)Ljavacard/framework/PIN; 0 {
			.stack 4;
			.locals 0;

				L0:	sload_2;
					stableswitch L4 1 3 L1 L2 L3;
				L1:	new 67;		// javacard/framework/OwnerPIN
					dup;
					sload_0;
					sload_1;
					invokespecial 68;		// javacard/framework/OwnerPIN.<init>(BB)V
					areturn;
				L2:	new 69;		// com/sun/javacard/impl/OwnerPINxImpl
					dup;
					sload_0;
					sload_1;
					invokespecial 70;		// com/sun/javacard/impl/OwnerPINxImpl.<init>(BB)V
					areturn;
				L3:	new 71;		// com/sun/javacard/impl/OwnerPINxWithPredecrementImpl
					dup;
					sload_0;
					sload_1;
					invokespecial 72;		// com/sun/javacard/impl/OwnerPINxWithPredecrementImpl.<init>(BB)V
					areturn;
				L4:	sconst_1;
					invokestatic 54;		// javacard/framework/PINException.throwIt(S)V
					aconst_null;
					areturn;
		}

	}

	.class public abstract Applet 3 extends 0.0 {		// extends java/lang/Object

		.fields {
			private 1.13 thePrivAccess 0;		// Lcom/sun/javacard/impl/PrivAccess;
		}

		.publicMethodTable 1 8 {
			equals(Ljava/lang/Object;)Z 0;
			register()V 255;
			register([BSB)V 255;
			selectingApplet()Z 255;
			deselect()V 255;
			getShareableInterfaceObject(Ljavacard/framework/AID;B)Ljavacard/framework/Shareable; 255;
			select()Z 255;
			process(Ljavacard/framework/APDU;)V 255;
		}

		.packageMethodTable 0 {
		}

		.method protected final register()V 1 {
			.stack 2;
			.locals 0;

				L0:	getfield_a_this 8;		// reference javacard/framework/Applet.thePrivAccess
					aload_0;
					invokevirtual 74;		// register(Ljavacard/framework/Applet;)V
					return;
		}

		.method protected final register([BSB)V 2 {
			.stack 5;
			.locals 0;

				L0:	sload_3;
					sconst_5;
					if_scmplt L2;
				L1:	sload_3;
					bspush 16;
					if_scmple L3;
				L2:	sconst_1;
					invokestatic 255;		// javacard/framework/SystemException.throwIt(S)V
				L3:	getfield_a_this 8;		// reference javacard/framework/Applet.thePrivAccess
					aload_0;
					aload_1;
					sload_2;
					sload_3;
					invokevirtual 75;		// register(Ljavacard/framework/Applet;[BSB)V
					return;
		}

		.method protected final selectingApplet()Z 3 {
			.stack 1;
			.locals 0;

				L0:	getfield_a_this 8;		// reference javacard/framework/Applet.thePrivAccess
					invokevirtual 76;		// selectingApplet()Z
					sreturn;
		}

		.method protected <init>()V 0 {
			.stack 2;
			.locals 0;

				L0:	aload_0;
					invokespecial 254;		// java/lang/Object.<init>()V
					aload_0;
					invokestatic 77;		// com/sun/javacard/impl/PrivAccess.getPrivAccess()Lcom/sun/javacard/impl/PrivAccess;
					putfield_a 8;		// reference javacard/framework/Applet.thePrivAccess
					return;
		}

		.method public static install([BSB)V 1 {
			.stack 1;
			.locals 0;

				L0:	sspush 27265;
					invokestatic 78;		// javacard/framework/ISOException.throwIt(S)V
					return;
		}

		.method public select()Z 6 {
			.stack 1;
			.locals 0;

				L0:	sconst_1;
					sreturn;
		}

		.method public deselect()V 4 {
			.stack 0;
			.locals 0;

				L0:	return;
		}

		.method public getShareableInterfaceObject(Ljavacard/framework/AID;B)Ljavacard/framework/Shareable; 5 {
			.stack 1;
			.locals 0;

				L0:	aconst_null;
					areturn;
		}

		.method protected static reSelectingApplet()Z 2 {
			.stack 1;
			.locals 0;

				L0:	invokestatic 77;		// com/sun/javacard/impl/PrivAccess.getPrivAccess()Lcom/sun/javacard/impl/PrivAccess;
					invokevirtual 79;		// amIBeingReselected()Z
					sreturn;
		}

		.method public abstract process(Ljavacard/framework/APDU;)V 7 {
		}

	}

	.class public final APDU 10 extends 0.0 {		// extends java/lang/Object

		.fields {
			public static final byte STATE_INITIAL = 0;		// B
			public static final byte STATE_PARTIAL_INCOMING = 1;		// B
			public static final byte STATE_FULL_INCOMING = 2;		// B
			public static final byte STATE_OUTGOING = 3;		// B
			public static final byte STATE_OUTGOING_LENGTH_KNOWN = 4;		// B
			public static final byte STATE_PARTIAL_OUTGOING = 5;		// B
			public static final byte STATE_FULL_OUTGOING = 6;		// B
			public static final byte STATE_ERROR_NO_T0_GETRESPONSE = -1;		// B
			public static final byte STATE_ERROR_T1_IFD_ABORT = -2;		// B
			public static final byte STATE_ERROR_IO = -3;		// B
			public static final byte STATE_ERROR_NO_T0_REISSUE = -4;		// B
			public static final byte PROTOCOL_MEDIA_MASK = -16;		// B
			public static final byte PROTOCOL_TYPE_MASK = 15;		// B
			public static final byte PROTOCOL_T0 = 0;		// B
			public static final byte PROTOCOL_T1 = 1;		// B
			public static final byte PROTOCOL_MEDIA_DEFAULT = 0;		// B
			public static final byte PROTOCOL_MEDIA_CONTACTLESS_TYPE_A = -128;		// B
			public static final byte PROTOCOL_MEDIA_CONTACTLESS_TYPE_B = -112;		// B
			public static final byte PROTOCOL_MEDIA_USB = -96;		// B
			public static final byte PROTOCOL_MEDIA_HCI_APDU_GATE = -80;		// B
			public static final byte PROTOCOL_MEDIA_CONTACTLESS_TYPE_F = -80;		// B
			static final byte LOGICAL_CHN_MASK_TYPE4 = 3;		// B
			static final byte LOGICAL_CHN_MASK_TYPE16 = 15;		// B
			static final byte APDU_ISOCLASS_MASK = -128;		// B
			static final byte APDU_TYPE_MASK = 64;		// B
			static final byte APDU_SM_MASK_TYPE4 = 12;		// B
			static final byte APDU_SM_MASK_TYPE16 = 32;		// B
			static final byte APDU_CHAINING_MASK = 16;		// B
			static final byte APDU_INVALID_TYPE4_MASK = 32;		// B
			static final byte PROTOCOL_TCL = -111;		// B
			static APDUComm apduProtocol;		// Ljavacard/framework/APDUComm;
			private static APDU theAPDU;		// Ljavacard/framework/APDU;
		}

		.publicMethodTable 1 18 {
			equals(Ljava/lang/Object;)Z 0;
			getBuffer()[B 255;
			getNAD()B 255;
			receiveBytes(S)S 255;
			sendBytes(SS)V 255;
			sendBytesLong([BSS)V 255;
			setIncomingAndReceive()S 255;
			setOutgoing()S 255;
			setOutgoingAndSend(SS)V 255;
			setOutgoingLength(S)V 255;
			setOutgoingNoChaining()S 255;
			getCurrentState()B 255;
			isCommandChainingCLA()Z 255;
			isSecureMessagingCLA()Z 255;
			isISOInterindustryCLA()Z 255;
			getIncomingLength()S 255;
			getOffsetCdata()S 255;
			isValidCLA()Z 255;
		}

		.packageMethodTable 0 {
			getLogicalChannel()B;
			getNoChainingFlag()Z;
			resetAPDU()V;
			complete(S)V;
			undoIncomingAndReceive()V;
			markExtendedSupport(Z)V;
			verifyLe()V;
		}

		.method  getLogicalChannel()B 128 {
			.stack 1;
			.locals 0;

				L0:	getstatic_a 80;		// reference javacard/framework/APDU.apduProtocol
					invokeinterface 1 81 0;		// javacard/framework/APDUComm
					sreturn;
		}

		.method  getNoChainingFlag()Z 129 {
			.stack 1;
			.locals 0;

				L0:	getstatic_a 80;		// reference javacard/framework/APDU.apduProtocol
					invokeinterface 1 81 1;		// javacard/framework/APDUComm
					sreturn;
		}

		.method  <init>()V {
			.stack 2;
			.locals 1;

				L0:	aload_0;
					invokespecial 254;		// java/lang/Object.<init>()V
					invokestatic 82;		// com/sun/javacard/impl/NativeMethods.getActiveInterface()B
					invokestatic 83;		// com/sun/javacard/impl/NativeMethods.getCommProtocol(B)B
					sstore_1;
				L1:	sload_1;
					ifne L3;
				L2:	new 84;		// javacard/framework/T0APDUImpl
					dup;
					invokespecial 85;		// javacard/framework/T0APDUImpl.<init>()V
					putstatic_a 80;		// reference javacard/framework/APDU.apduProtocol
					goto L6;
				L3:	sload_1;
					sconst_1;
					if_scmpeq L5;
				L4:	sload_1;
					bspush -111;
					if_scmpne L6;
				L5:	new 86;		// javacard/framework/T1APDUImpl
					dup;
					invokespecial 87;		// javacard/framework/T1APDUImpl.<init>()V
					putstatic_a 80;		// reference javacard/framework/APDU.apduProtocol
				L6:	getstatic_a 80;		// reference javacard/framework/APDU.apduProtocol
					sconst_0;
					invokestatic 73;		// com/sun/javacard/impl/NativeMethods.setJCREentry(Ljava/lang/Object;Z)V
					aload_0;
					putstatic_a 88;		// reference javacard/framework/APDU.theAPDU
					return;
		}

		.method public getBuffer()[B 1 {
			.stack 1;
			.locals 0;

				L0:	getstatic_a 80;		// reference javacard/framework/APDU.apduProtocol
					invokeinterface 1 81 7;		// javacard/framework/APDUComm
					areturn;
		}

		.method public static getInBlockSize()S 0 {
			.stack 1;
			.locals 0;

				L0:	getstatic_a 80;		// reference javacard/framework/APDU.apduProtocol
					invokeinterface 1 81 8;		// javacard/framework/APDUComm
					sreturn;
		}

		.method public static getOutBlockSize()S 1 {
			.stack 1;
			.locals 0;

				L0:	getstatic_a 80;		// reference javacard/framework/APDU.apduProtocol
					invokeinterface 1 81 9;		// javacard/framework/APDUComm
					sreturn;
		}

		.method public static getProtocol()B 2 {
			.stack 1;
			.locals 0;

				L0:	getstatic_a 80;		// reference javacard/framework/APDU.apduProtocol
					invokeinterface 1 81 10;		// javacard/framework/APDUComm
					sreturn;
		}

		.method public getNAD()B 2 {
			.stack 1;
			.locals 0;

				L0:	getstatic_a 80;		// reference javacard/framework/APDU.apduProtocol
					invokeinterface 1 81 11;		// javacard/framework/APDUComm
					sreturn;
		}

		.method public setOutgoing()S 7 {
			.stack 1;
			.locals 0;

				L0:	invokestatic 89;		// javacard/framework/APDU.checkErrorState()V
					getstatic_a 80;		// reference javacard/framework/APDU.apduProtocol
					invokeinterface 1 81 12;		// javacard/framework/APDUComm
					sreturn;
		}

		.method public setOutgoingNoChaining()S 10 {
			.stack 1;
			.locals 0;

				L0:	invokestatic 89;		// javacard/framework/APDU.checkErrorState()V
					getstatic_a 80;		// reference javacard/framework/APDU.apduProtocol
					invokeinterface 1 81 13;		// javacard/framework/APDUComm
					sreturn;
		}

		.method public setOutgoingLength(S)V 9 {
			.stack 2;
			.locals 0;

				L0:	invokestatic 89;		// javacard/framework/APDU.checkErrorState()V
					getstatic_a 80;		// reference javacard/framework/APDU.apduProtocol
					sload_1;
					invokeinterface 2 81 14;		// javacard/framework/APDUComm
					return;
		}

		.method public receiveBytes(S)S 3 {
			.stack 2;
			.locals 0;

				L0:	invokestatic 89;		// javacard/framework/APDU.checkErrorState()V
					getstatic_a 80;		// reference javacard/framework/APDU.apduProtocol
					sload_1;
					invokeinterface 2 81 15;		// javacard/framework/APDUComm
					sreturn;
		}

		.method public setIncomingAndReceive()S 6 {
			.stack 1;
			.locals 0;

				L0:	invokestatic 89;		// javacard/framework/APDU.checkErrorState()V
					getstatic_a 80;		// reference javacard/framework/APDU.apduProtocol
					invokeinterface 1 81 16;		// javacard/framework/APDUComm
					sreturn;
		}

		.method public sendBytes(SS)V 4 {
			.stack 3;
			.locals 0;

				L0:	invokestatic 89;		// javacard/framework/APDU.checkErrorState()V
					getstatic_a 80;		// reference javacard/framework/APDU.apduProtocol
					sload_1;
					sload_2;
					invokeinterface 3 81 17;		// javacard/framework/APDUComm
					return;
		}

		.method public sendBytesLong([BSS)V 5 {
			.stack 4;
			.locals 0;

				L0:	invokestatic 89;		// javacard/framework/APDU.checkErrorState()V
					getstatic_a 80;		// reference javacard/framework/APDU.apduProtocol
					aload_1;
					sload_2;
					sload_3;
					invokeinterface 4 81 18;		// javacard/framework/APDUComm
					return;
		}

		.method public setOutgoingAndSend(SS)V 8 {
			.stack 3;
			.locals 0;

				L0:	invokestatic 89;		// javacard/framework/APDU.checkErrorState()V
					getstatic_a 80;		// reference javacard/framework/APDU.apduProtocol
					sload_1;
					sload_2;
					invokeinterface 3 81 19;		// javacard/framework/APDUComm
					return;
		}

		.method public getCurrentState()B 11 {
			.stack 1;
			.locals 0;

				L0:	getstatic_a 80;		// reference javacard/framework/APDU.apduProtocol
					invokeinterface 1 81 20;		// javacard/framework/APDUComm
					sreturn;
		}

		.method private static checkErrorState()V {
			.stack 1;
			.locals 0;

				L0:	getstatic_a 88;		// reference javacard/framework/APDU.theAPDU
					invokevirtual 90;		// getCurrentState()B
					ifge L2;
				L1:	sconst_4;
					invokestatic 91;		// javacard/framework/APDUException.throwIt(S)V
				L2:	return;
		}

		.method private static checkAPDUObjectAccess()V {
			.stack 2;
			.locals 2;

				L0:	invokestatic 43;		// com/sun/javacard/impl/NativeMethods.getCurrentlySelectedChannel()B
					sstore_0;
				L1:	invokestatic 82;		// com/sun/javacard/impl/NativeMethods.getActiveInterface()B
					sstore_1;
				L2:	sload_0;
					sload_1;
					invokestatic 92;		// com/sun/javacard/impl/PrivAccess.getSelectedAppID(BB)B
					invokestatic 257;		// com/sun/javacard/impl/PrivAccess.getCurrentAppID()B
					if_scmpne L4;
				L3:	invokestatic 77;		// com/sun/javacard/impl/PrivAccess.getPrivAccess()Lcom/sun/javacard/impl/PrivAccess;
					invokevirtual 93;		// inProcessMethod()Z
					ifne L5;
				L4:	getstatic_a 94;		// reference javacard/framework/Dispatcher.securityException
					athrow;
				L5:	return;
		}

		.method public static getCurrentAPDU()Ljavacard/framework/APDU; 4 {
			.stack 1;
			.locals 0;

				L0:	invokestatic 95;		// javacard/framework/APDU.checkAPDUObjectAccess()V
					getstatic_a 88;		// reference javacard/framework/APDU.theAPDU
					areturn;
		}

		.method public static getCurrentAPDUBuffer()[B 5 {
			.stack 1;
			.locals 0;

				L0:	invokestatic 95;		// javacard/framework/APDU.checkAPDUObjectAccess()V
					getstatic_a 80;		// reference javacard/framework/APDU.apduProtocol
					invokeinterface 1 81 21;		// javacard/framework/APDUComm
					areturn;
		}

		.method public static getCLAChannel()B 6 {
			.stack 1;
			.locals 0;

				L0:	getstatic_a 80;		// reference javacard/framework/APDU.apduProtocol
					invokeinterface 1 81 5;		// javacard/framework/APDUComm
					sreturn;
		}

		.method  resetAPDU()V 130 {
			.stack 1;
			.locals 0;

				L0:	getstatic_a 80;		// reference javacard/framework/APDU.apduProtocol
					invokeinterface 1 81 2;		// javacard/framework/APDUComm
					return;
		}

		.method  complete(S)V 131 {
			.stack 2;
			.locals 0;

				L0:	getstatic_a 80;		// reference javacard/framework/APDU.apduProtocol
					sload_1;
					invokeinterface 2 81 3;		// javacard/framework/APDUComm
					return;
		}

		.method  undoIncomingAndReceive()V 132 {
			.stack 1;
			.locals 0;

				L0:	getstatic_a 80;		// reference javacard/framework/APDU.apduProtocol
					invokeinterface 1 81 4;		// javacard/framework/APDUComm
					return;
		}

		.method public static waitExtension()V 3 {
			.stack 1;
			.locals 0;

				L0:	invokestatic 89;		// javacard/framework/APDU.checkErrorState()V
					getstatic_a 80;		// reference javacard/framework/APDU.apduProtocol
					invokeinterface 1 81 6;		// javacard/framework/APDUComm
					return;
		}

		.method  markExtendedSupport(Z)V 133 {
			.stack 2;
			.locals 0;

				L0:	getstatic_a 80;		// reference javacard/framework/APDU.apduProtocol
					sload_1;
					invokeinterface 2 81 22;		// javacard/framework/APDUComm
					return;
		}

		.method public isCommandChainingCLA()Z 12 {
			.stack 1;
			.locals 0;

				L0:	getstatic_a 80;		// reference javacard/framework/APDU.apduProtocol
					invokeinterface 1 81 26;		// javacard/framework/APDUComm
					sreturn;
		}

		.method public isSecureMessagingCLA()Z 13 {
			.stack 1;
			.locals 0;

				L0:	getstatic_a 80;		// reference javacard/framework/APDU.apduProtocol
					invokeinterface 1 81 27;		// javacard/framework/APDUComm
					sreturn;
		}

		.method public isISOInterindustryCLA()Z 14 {
			.stack 1;
			.locals 0;

				L0:	getstatic_a 80;		// reference javacard/framework/APDU.apduProtocol
					invokeinterface 1 81 28;		// javacard/framework/APDUComm
					sreturn;
		}

		.method public isValidCLA()Z 17 {
			.stack 1;
			.locals 0;

				L0:	getstatic_a 80;		// reference javacard/framework/APDU.apduProtocol
					invokeinterface 1 81 25;		// javacard/framework/APDUComm
					sreturn;
		}

		.method public getIncomingLength()S 15 {
			.stack 1;
			.locals 0;

				L0:	getstatic_a 80;		// reference javacard/framework/APDU.apduProtocol
					invokeinterface 1 81 23;		// javacard/framework/APDUComm
					sreturn;
		}

		.method public getOffsetCdata()S 16 {
			.stack 1;
			.locals 0;

				L0:	getstatic_a 80;		// reference javacard/framework/APDU.apduProtocol
					invokeinterface 1 81 24;		// javacard/framework/APDUComm
					sreturn;
		}

		.method  verifyLe()V 134 {
			.stack 1;
			.locals 0;

				L0:	getstatic_a 80;		// reference javacard/framework/APDU.apduProtocol
					invokeinterface 1 81 29;		// javacard/framework/APDUComm
					return;
		}

	}

	.class public CardException 4 extends 0.2 {		// extends java/lang/Exception

		.fields {
			private byte[] theSw 0;		// [B
			private static CardException systemInstance;		// Ljavacard/framework/CardException;
		}

		.publicMethodTable 1 3 {
			equals(Ljava/lang/Object;)Z 0;
			getReason()S 255;
			setReason(S)V 255;
		}

		.packageMethodTable 0 {
		}

		.method public <init>(S)V 0 {
			.stack 3;
			.locals 0;

				L0:	aload_0;
					invokespecial 96;		// java/lang/Exception.<init>()V
					invokestatic 257;		// com/sun/javacard/impl/PrivAccess.getCurrentAppID()B
					ifne L4;
				L1:	getstatic_a 97;		// reference javacard/framework/CardException.systemInstance
					ifnonnull L3;
				L2:	aload_0;
					putstatic_a 97;		// reference javacard/framework/CardException.systemInstance
				L3:	aload_0;
					sconst_2;
					sconst_1;
					invokestatic 57;		// javacard/framework/JCSystem.makeTransientByteArray(SB)[B
					putfield_a 9;		// reference javacard/framework/CardException.theSw
					goto L5;
				L4:	aload_0;
					sconst_2;
					newarray 11;
					putfield_a 9;		// reference javacard/framework/CardException.theSw
				L5:	getfield_a_this 9;		// reference javacard/framework/CardException.theSw
					sconst_0;
					sload_1;
					invokestatic 260;		// javacard/framework/Util.setShort([BSS)S
					pop;
					return;
		}

		.method public getReason()S 1 {
			.stack 2;
			.locals 0;

				L0:	getfield_a_this 9;		// reference javacard/framework/CardException.theSw
					sconst_0;
					invokestatic 261;		// javacard/framework/Util.getShort([BS)S
					sreturn;
		}

		.method public setReason(S)V 2 {
			.stack 5;
			.locals 0;

				L0:	getfield_a_this 9;		// reference javacard/framework/CardException.theSw
					sconst_0;
					sconst_1;
					sload_1;
					bspush 8;
					sushr;
					s2b;
					invokestatic 262;		// javacard/framework/Util.arrayFillNonAtomic([BSSB)S
					pop;
					getfield_a_this 9;		// reference javacard/framework/CardException.theSw
					sconst_1;
					sconst_1;
					sload_1;
					s2b;
					invokestatic 262;		// javacard/framework/Util.arrayFillNonAtomic([BSSB)S
					pop;
					return;
		}

		.method public static throwIt(S)V 1 {
			.stack 2;
			.locals 0;

				L0:	getstatic_a 97;		// reference javacard/framework/CardException.systemInstance
					sload_0;
					invokevirtual 99;		// setReason(S)V
					getstatic_a 97;		// reference javacard/framework/CardException.systemInstance
					athrow;
		}

	}

	.class public PINException 11 extends CardRuntimeException {

		.fields {
			public static final short ILLEGAL_VALUE = 1;		// S
			public static final short ILLEGAL_STATE = 2;		// S
			private static PINException systemInstance;		// Ljavacard/framework/PINException;
		}

		.publicMethodTable 3 3 {
			equals(Ljava/lang/Object;)Z 0;
			getReason()S 1;
			setReason(S)V 2;
		}

		.packageMethodTable 0 {
		}

		.method public <init>(S)V 0 {
			.stack 2;
			.locals 0;

				L0:	aload_0;
					sload_1;
					invokespecial 48;		// javacard/framework/CardRuntimeException.<init>(S)V
					getstatic_a 100;		// reference javacard/framework/PINException.systemInstance
					ifnonnull L2;
				L1:	aload_0;
					putstatic_a 100;		// reference javacard/framework/PINException.systemInstance
				L2:	return;
		}

		.method public static throwIt(S)V 1 {
			.stack 2;
			.locals 0;

				L0:	getstatic_a 100;		// reference javacard/framework/PINException.systemInstance
					sload_0;
					invokevirtual 101;		// setReason(S)V
					getstatic_a 100;		// reference javacard/framework/PINException.systemInstance
					athrow;
		}

	}

	.class public final Resources 23 extends 0.0 {		// extends java/lang/Object

		.fields {
			private 1.15[] staticResources 0;		// [Lcom/sun/javacard/impl/StaticResourceEntry;
		}

		.publicMethodTable 1 4 {
			equals(Ljava/lang/Object;)Z 0;
			getSize(S)S 255;
			getView(S)[B 255;
			getView(SSS)[B 255;
		}

		.packageMethodTable 0 {
		}

		.method private <init>()V {
			.stack 2;
			.locals 0;

				L0:	aload_0;
					invokespecial 254;		// java/lang/Object.<init>()V
					aconst_null;
					putfield_a_this 10;		// reference javacard/framework/Resources.staticResources
					return;
		}

		.method public static getResources()Ljavacard/framework/Resources; 0 {
			.stack 3;
			.locals 2;

				L0:	invokestatic 103;		// com/sun/javacard/impl/NativeMethods.getLibraryPackageID()B
					sstore_0;
				L1:	getstatic_a 343;		// reference javacard/framework/JCSystem.thePrivAccess
					sload_0;
					invokevirtual 104;		// getResourceObject(B)Ljavacard/framework/Resources;
					astore_1;
				L2:	aload_1;
					ifnonnull L4;
				L3:	new 105;		// javacard/framework/Resources
					dup;
					invokespecial 106;		// javacard/framework/Resources.<init>()V
					astore_1;
					aload_1;
					getstatic_a 343;		// reference javacard/framework/JCSystem.thePrivAccess
					sload_0;
					invokevirtual 107;		// getStaticResources(B)[Lcom/sun/javacard/impl/StaticResourceEntry;
					putfield_a 10;		// reference javacard/framework/Resources.staticResources
					aload_1;
					sconst_0;
					invokestatic 73;		// com/sun/javacard/impl/NativeMethods.setJCREentry(Ljava/lang/Object;Z)V
					aload_1;
					sconst_0;
					invokestatic 108;		// com/sun/javacard/impl/NativeMethods.setObjectContext(Ljava/lang/Object;B)V
					getstatic_a 343;		// reference javacard/framework/JCSystem.thePrivAccess
					sload_0;
					aload_1;
					invokevirtual 109;		// setResourceObject(BLjavacard/framework/Resources;)V
				L4:	aload_1;
					areturn;
		}

		.method public getSize(S)S 1 {
			.stack 2;
			.locals 1;

				L0:	aload_0;
					invokespecial 110;		// javacard/framework/Resources.checkNullEntries()V
					sconst_0;
					sstore_2;
				L1:	sload_2;
					getfield_a_this 10;		// reference javacard/framework/Resources.staticResources
					arraylength;
					if_scmpge L5;
				L2:	getfield_a_this 10;		// reference javacard/framework/Resources.staticResources
					sload_2;
					aaload;
					invokevirtual 111;		// getId()S
					sload_1;
					if_scmpne L4;
				L3:	getfield_a_this 10;		// reference javacard/framework/Resources.staticResources
					sload_2;
					aaload;
					invokevirtual 112;		// getSize()S
					sreturn;
				L4:	sinc 2 1;
					goto L1;
				L5:	getstatic_a 113;		// reference javacard/framework/Dispatcher.ioException
					athrow;
		}

		.method public getView(S)[B 2 {
			.stack 5;
			.locals 8;

				L0:	aload_0;
					invokespecial 110;		// javacard/framework/Resources.checkNullEntries()V
					sconst_0;
					sstore_2;
				L1:	sload_2;
					getfield_a_this 10;		// reference javacard/framework/Resources.staticResources
					arraylength;
					if_scmpge L12;
				L2:	getfield_a_this 10;		// reference javacard/framework/Resources.staticResources
					sload_2;
					aaload;
					astore_3;
				L3:	aload_3;
					invokevirtual 111;		// getId()S
					sload_1;
					if_scmpne L11;
				L4:	aload_3;
					invokevirtual 114;		// getData()[S
					astore 4;
				L5:	aload_3;
					invokevirtual 112;		// getSize()S
					sstore 5;
				L6:	sload 5;
					sconst_2;
					sdiv;
					sstore 6;
				L7:	aload 4;
					sconst_0;
					sload 6;
					sconst_1;
					aconst_null;
					invokestatic 115;		// javacard/framework/JCSystem.makeArrayView(Ljava/lang/Object;SSSLjavacard/framework/Shareable;)Ljava/lang/Object;
					checkcast 12 0;		// T_SHORT
					astore 7;
				L8:	aload 7;
					invokestatic 116;		// com/sun/javacard/impl/NativeMethods.changeArrayViewType([S)[B
					astore 8;
				L9:	aload 7;
					sload 5;
					invokestatic 117;		// com/sun/javacard/impl/NativeMethods.changeArrayViewLength([SS)V
					invokestatic 351;		// com/sun/javacard/impl/NativeMethods.getPreviousContext()B
					sstore 9;
				L10:	aload 8;
					sload 9;
					invokestatic 108;		// com/sun/javacard/impl/NativeMethods.setObjectContext(Ljava/lang/Object;B)V
					aload 8;
					areturn;
				L11:	sinc 2 1;
					goto L1;
				L12:	getstatic_a 113;		// reference javacard/framework/Dispatcher.ioException
					athrow;
		}

		.method public getView(SSS)[B 3 {
			.stack 5;
			.locals 8;

				L0:	aload_0;
					invokespecial 110;		// javacard/framework/Resources.checkNullEntries()V
					sload_2;
					iflt L2;
				L1:	sload_3;
					ifge L3;
				L2:	getstatic_a 113;		// reference javacard/framework/Dispatcher.ioException
					athrow;
				L3:	sconst_0;
					sstore 4;
				L4:	sload 4;
					getfield_a_this 10;		// reference javacard/framework/Resources.staticResources
					arraylength;
					if_scmpge L19;
				L5:	getfield_a_this 10;		// reference javacard/framework/Resources.staticResources
					sload 4;
					aaload;
					astore 5;
				L6:	aload 5;
					invokevirtual 111;		// getId()S
					sload_1;
					if_scmpne L18;
				L7:	aload 5;
					invokevirtual 114;		// getData()[S
					astore 6;
				L8:	sload_3;
					sconst_2;
					sdiv;
					sstore 7;
				L9:	sload_2;
					sconst_2;
					sdiv;
					sstore 8;
				L10:	aload 6;
					arraylength;
					aload 5;
					invokevirtual 118;		// getHalfWord()Z
					sload_2;
					sload_3;
					invokestatic 119;		// com/sun/javacard/impl/NativeMethods.validateResourceSize(SZSS)Z
					ifne L12;
				L11:	getstatic_a 113;		// reference javacard/framework/Dispatcher.ioException
					athrow;
				L12:	aload 6;
					sload_2;
					sload_3;
					invokestatic 120;		// com/sun/javacard/impl/NativeMethods.checkArrayBounds([SSS)V
					aload 6;
					sload 8;
					sload 7;
					sconst_1;
					aconst_null;
					invokestatic 115;		// javacard/framework/JCSystem.makeArrayView(Ljava/lang/Object;SSSLjavacard/framework/Shareable;)Ljava/lang/Object;
					checkcast 12 0;		// T_SHORT
					astore 9;
				L13:	aload 9;
					invokestatic 116;		// com/sun/javacard/impl/NativeMethods.changeArrayViewType([S)[B
					astore 10;
				L14:	aload 9;
					sload_3;
					invokestatic 117;		// com/sun/javacard/impl/NativeMethods.changeArrayViewLength([SS)V
					sload_2;
					sconst_2;
					srem;
					ifeq L16;
				L15:	aload 9;
					sload_2;
					invokestatic 121;		// com/sun/javacard/impl/NativeMethods.changeArrayViewDataStart([SS)V
				L16:	invokestatic 351;		// com/sun/javacard/impl/NativeMethods.getPreviousContext()B
					sstore 11;
				L17:	aload 10;
					sload 11;
					invokestatic 108;		// com/sun/javacard/impl/NativeMethods.setObjectContext(Ljava/lang/Object;B)V
					aload 10;
					areturn;
				L18:	sinc 4 1;
					goto L4;
				L19:	getstatic_a 113;		// reference javacard/framework/Dispatcher.ioException
					athrow;
		}

		.method private checkNullEntries()V {
			.stack 1;
			.locals 0;

				L0:	getfield_a_this 10;		// reference javacard/framework/Resources.staticResources
					ifnonnull L2;
				L1:	getstatic_a 113;		// reference javacard/framework/Dispatcher.ioException
					athrow;
				L2:	return;
		}

	}

	.class public SensitiveArrays 22 extends 0.0 {		// extends java/lang/Object

		.publicMethodTable 1 1 {
			equals(Ljava/lang/Object;)Z 0;
		}

		.packageMethodTable 0 {
		}

		.method private <init>()V {
			.stack 1;
			.locals 0;

				L0:	aload_0;
					invokespecial 254;		// java/lang/Object.<init>()V
					return;
		}

		.method public static native assertIntegrity(Ljava/lang/Object;)V 0 {
			.descriptor	Ljava/lang/Object;	0.0;

		}

		.method public static native isIntegritySensitive(Ljava/lang/Object;)Z 1 {
			.descriptor	Ljava/lang/Object;	0.0;

		}

		.method public static native isIntegritySensitiveArraysSupported()Z 2 {
		}

		.method public static native makeIntegritySensitiveArray(BBS)Ljava/lang/Object; 3 {
			.descriptor	Ljava/lang/Object;	0.0;

		}

		.method public static native clearArray(Ljava/lang/Object;)S 4 {
			.descriptor	Ljava/lang/Object;	0.0;

		}

	}

	.class public ISOException 7 extends CardRuntimeException {

		.fields {
			private static ISOException systemInstance;		// Ljavacard/framework/ISOException;
		}

		.publicMethodTable 3 3 {
			equals(Ljava/lang/Object;)Z 0;
			getReason()S 1;
			setReason(S)V 2;
		}

		.packageMethodTable 0 {
		}

		.method public <init>(S)V 0 {
			.stack 2;
			.locals 0;

				L0:	aload_0;
					sload_1;
					invokespecial 48;		// javacard/framework/CardRuntimeException.<init>(S)V
					getstatic_a 122;		// reference javacard/framework/ISOException.systemInstance
					ifnonnull L2;
				L1:	aload_0;
					putstatic_a 122;		// reference javacard/framework/ISOException.systemInstance
				L2:	return;
		}

		.method public static throwIt(S)V 1 {
			.stack 2;
			.locals 0;

				L0:	getstatic_a 122;		// reference javacard/framework/ISOException.systemInstance
					sload_0;
					invokevirtual 123;		// setReason(S)V
					getstatic_a 122;		// reference javacard/framework/ISOException.systemInstance
					athrow;
		}

	}

	.class  Dispatcher extends 0.0 {		// extends java/lang/Object

		.fields {
			private static final byte INS_SELECT = -92;		// B
			private static final byte INS_MANAGECHANNEL = 112;		// B
			private static final byte P1_SELECT_DFBYNAME = 4;		// B
			private static final byte P2_SELECT_OPTIONS = -29;		// B
			private static final byte P2_SELECT_OPTIONS_ONLY = 0;		// B
			private static final byte P1_OPEN_CHANNEL = 0;		// B
			private static final byte P1_CLOSE_CHANNEL = -128;		// B
			private static final byte P2_AUTOSELECT_CHANNEL = 0;		// B
			private static final byte ERR_NO_CHANNEL_AVAILABLE = -1;		// B
			private static final byte BASIC_CHANNEL = 0;		// B
			private static 0.5 arrayIndexOutOfBoundsException;		// Ljava/lang/ArrayIndexOutOfBoundsException;
			private static 0.6 negativeArraySizeException;		// Ljava/lang/NegativeArraySizeException;
			private static 0.7 nullPointerException;		// Ljava/lang/NullPointerException;
			private static 0.8 classCastException;		// Ljava/lang/ClassCastException;
			private static 0.9 arithmeticException;		// Ljava/lang/ArithmeticException;
			static 0.10 securityException;		// Ljava/lang/SecurityException;
			private static 0.11 arrayStoreException;		// Ljava/lang/ArrayStoreException;
			private static SystemException systemException;		// Ljavacard/framework/SystemException;
			private static TransactionException transactionException;		// Ljavacard/framework/TransactionException;
			private static 3.0 dateTimeException;		// Ljavacardx/framework/time/DateTimeException;
			private static 4.1 utilException;		// Ljavacardx/framework/util/UtilException;
			static 2.0 ioException;		// Ljava/io/IOException;
			private static 5.0 stringException;		// Ljavacardx/framework/string/StringException;
			private static final byte OP_CHANNEL_CLOSE = 0;		// B
			private static final byte OP_CHANNEL_OPEN = 1;		// B
			private static final byte OP_CHANNEL_OPEN_AUTOSELECT = 2;		// B
			private static final byte CHANNEL_CLOSED = 0;		// B
			private static final byte CHANNEL_DISABLED = 1;		// B
			private static final byte CHANNEL_OPEN = 2;		// B
			private static final byte CHANNEL_OPEN_MS = 3;		// B
			private static final byte CHANNEL_MS_MASK = 1;		// B
			private static final byte CHANNEL_OPEN_MASK = 2;		// B
			private static APDU theAPDU;		// Ljavacard/framework/APDU;
			private static byte[] theAPDUBuffer;		// [B
			private static 1.13 thePrivAccess;		// Lcom/sun/javacard/impl/PrivAccess;
			private static short[] internArraySensitiveResultStateMachine;		// [S
			private static short lenInternArrSensitResStateMachine = 5;		// S
			static Dispatcher theDispatcher;		// Ljavacard/framework/Dispatcher;
			static Applet selectedApplet;		// Ljavacard/framework/Applet;
		}

		.publicMethodTable 1 1 {
			equals(Ljava/lang/Object;)Z 0;
		}

		.packageMethodTable 0 {
			manageChannelAPDU(Ljavacard/framework/APDU;)V;
			selectAPDU(Ljavacard/framework/APDU;)V;
			undoReceive()V;
		}

		.method static main()V {
			.stack 2;
			.locals 5;

				L0:	invokestatic 126;		// com/sun/javacard/impl/NativeMethods.isCardInitialized()Z
					ifne L2;
				L1:	invokestatic 127;		// javacard/framework/Dispatcher.cardInit()V
				L2:	invokestatic 128;		// javacard/framework/Dispatcher.cardReset()V
					sconst_0;
					sstore_0;
				L3:	sconst_0;
					sstore_1;
				L4:	sconst_0;
					sstore_2;
				L5:	sconst_0;
					sstore_3;
				L6:	invokestatic 129;		// com/sun/javacard/impl/PrivAccess.resetSelectingAppletFlag()V
					invokestatic 130;		// com/sun/javacard/impl/PrivAccess.resetProcessMethodFlag()V
					getstatic_a 131;		// reference javacard/framework/Dispatcher.theAPDU
					sload_0;
					invokevirtual 132;		// complete(S)V
					invokestatic 82;		// com/sun/javacard/impl/NativeMethods.getActiveInterface()B
					sstore_2;
				L7:	getstatic_a 131;		// reference javacard/framework/Dispatcher.theAPDU
					invokevirtual 133;		// verifyLe()V
					invokestatic 134;		// javacard/framework/Dispatcher.processAndForward()Z
					ifeq L15;
				L8:	invokestatic 43;		// com/sun/javacard/impl/NativeMethods.getCurrentlySelectedChannel()B
					sstore_1;
					sload_1;
					sload_2;
					invokestatic 92;		// com/sun/javacard/impl/PrivAccess.getSelectedAppID(BB)B
					sconst_m1;
					if_scmpne L10;
				L9:	sspush 27033;
					invokestatic 78;		// javacard/framework/ISOException.throwIt(S)V
				L10:	invokestatic 135;		// com/sun/javacard/impl/PrivAccess.setProcessMethodFlag()V
					sload_1;
					sload_2;
					invokestatic 136;		// com/sun/javacard/impl/PrivAccess.getSelectedApplet(BB)Ljavacard/framework/Applet;
					putstatic_a 137;		// reference javacard/framework/Dispatcher.selectedApplet
					getstatic_a 137;		// reference javacard/framework/Dispatcher.selectedApplet
					instanceof 0 138;		// T_CLASSORINTERFACE javacardx/apdu/ExtendedLength
					ifeq L12;
				L11:	getstatic_a 131;		// reference javacard/framework/Dispatcher.theAPDU
					sconst_1;
					invokevirtual 139;		// markExtendedSupport(Z)V
					goto L13;
				L12:	getstatic_a 131;		// reference javacard/framework/Dispatcher.theAPDU
					sconst_0;
					invokevirtual 139;		// markExtendedSupport(Z)V
				L13:	getstatic_a 137;		// reference javacard/framework/Dispatcher.selectedApplet
					getstatic_a 131;		// reference javacard/framework/Dispatcher.theAPDU
					invokevirtual 140;		// process(Ljavacard/framework/APDU;)V
					invokestatic 141;		// javacard/framework/JCSystem.getTransactionDepth()B
					ifeq L15;
				L14:	sconst_1;
					invokestatic 142;		// javacard/framework/TransactionException.throwIt(S)V
				L15:	sspush -28672;
					sstore_0;
				L16:	goto L22;
				L17:	astore 4;
				L18:	aload 4;
					invokevirtual 143;		// getReason()S
					sstore_0;
				L19:	goto L22;
				L20:	astore 4;
				L21:	sspush 28416;
					sstore_0;
				L22:	invokestatic 141;		// javacard/framework/JCSystem.getTransactionDepth()B
					ifeq L24;
				L23:	invokestatic 144;		// javacard/framework/JCSystem.abortTransaction()V
				L24:	getstatic_a 145;		// reference javacard/framework/Dispatcher.thePrivAccess
					invokevirtual 146;		// isGarbageCollectionRequested()Z
					ifeq_w L6;
				L25:	invokestatic 147;		// com/sun/javacard/impl/GarbageCollector.startGC()Z
					pop;
					goto_w L6;
			.exceptionTable {
				// start_block end_block handler_block catch_type_index
				L7 L16 L17 124;
				L7 L16 L20 125;
			}
		}

		.method private static setAPDUChannel(Z)V {
			.stack 2;
			.locals 2;

				L0:	invokestatic 148;		// javacard/framework/APDU.getCLAChannel()B
					sstore_1;
				L1:	sload_1;
					bspush 20;
					if_scmplt L3;
				L2:	sspush 26753;
					invokestatic 78;		// javacard/framework/ISOException.throwIt(S)V
				L3:	sload_1;
					invokestatic 82;		// com/sun/javacard/impl/NativeMethods.getActiveInterface()B
					invokestatic 149;		// com/sun/javacard/impl/NativeMethods.getChannelStatus(BB)B
					sstore_2;
				L4:	sload_0;
					ifne L7;
				L5:	sload_2;
					ifne L7;
				L6:	sspush 26753;
					invokestatic 78;		// javacard/framework/ISOException.throwIt(S)V
				L7:	sload_1;
					invokestatic 82;		// com/sun/javacard/impl/NativeMethods.getActiveInterface()B
					invokestatic 150;		// com/sun/javacard/impl/NativeMethods.setCurrentlySelectedChannel(BB)V
					return;
		}

		.method private static processAndForward()Z {
			.stack 2;
			.locals 0;

				L0:	getstatic_a 131;		// reference javacard/framework/Dispatcher.theAPDU
					invokevirtual 151;		// getBuffer()[B
					sconst_0;
					baload;
					sconst_m1;
					if_scmpne L2;
				L1:	sspush 28160;
					invokestatic 78;		// javacard/framework/ISOException.throwIt(S)V
				L2:	getstatic_a 131;		// reference javacard/framework/Dispatcher.theAPDU
					invokevirtual 152;		// isISOInterindustryCLA()Z
					ifeq L11;
				L3:	sconst_1;
					invokestatic 153;		// javacard/framework/Dispatcher.setAPDUChannel(Z)V
					getstatic_a 154;		// reference javacard/framework/Dispatcher.theAPDUBuffer
					sconst_1;
					baload;
					slookupswitch L10 2 -92 L4 112 L7;
				L4:	getstatic_a 131;		// reference javacard/framework/Dispatcher.theAPDU
					invokevirtual 155;		// isSecureMessagingCLA()Z
					ifeq L6;
				L5:	goto L10;
				L6:	getstatic_a 156;		// reference javacard/framework/Dispatcher.theDispatcher
					getstatic_a 131;		// reference javacard/framework/Dispatcher.theAPDU
					invokevirtual 157;		// selectAPDU(Ljavacard/framework/APDU;)V
					sconst_1;
					sreturn;
				L7:	getstatic_a 131;		// reference javacard/framework/Dispatcher.theAPDU
					invokevirtual 155;		// isSecureMessagingCLA()Z
					ifeq L9;
				L8:	sspush 26754;
					invokestatic 78;		// javacard/framework/ISOException.throwIt(S)V
				L9:	getstatic_a 156;		// reference javacard/framework/Dispatcher.theDispatcher
					getstatic_a 131;		// reference javacard/framework/Dispatcher.theAPDU
					invokevirtual 158;		// manageChannelAPDU(Ljavacard/framework/APDU;)V
					sconst_0;
					sreturn;
				L10:	goto L12;
				L11:	sconst_0;
					invokestatic 153;		// javacard/framework/Dispatcher.setAPDUChannel(Z)V
				L12:	sconst_1;
					sreturn;
		}

		.method  manageChannelAPDU(Ljavacard/framework/APDU;)V 128 {
			.stack 3;
			.locals 8;

				L0:	sconst_m1;
					sstore_2;
				L1:	invokestatic 43;		// com/sun/javacard/impl/NativeMethods.getCurrentlySelectedChannel()B
					sstore_3;
				L2:	invokestatic 44;		// com/sun/javacard/impl/NativeMethods.getMaxChannels()B
					sstore 5;
				L3:	invokestatic 82;		// com/sun/javacard/impl/NativeMethods.getActiveInterface()B
					sstore 6;
				L4:	sload 5;
					sconst_1;
					if_scmpne L6;
				L5:	sspush 26753;
					invokestatic 78;		// javacard/framework/ISOException.throwIt(S)V
				L6:	sload_3;
					sload 6;
					invokestatic 149;		// com/sun/javacard/impl/NativeMethods.getChannelStatus(BB)B
					ifne L8;
				L7:	sspush 26753;
					invokestatic 78;		// javacard/framework/ISOException.throwIt(S)V
				L8:	getstatic_a 154;		// reference javacard/framework/Dispatcher.theAPDUBuffer
					sconst_2;
					baload;
					sstore 7;
				L9:	getstatic_a 154;		// reference javacard/framework/Dispatcher.theAPDUBuffer
					sconst_3;
					baload;
					sstore 8;
				L10:	sload 8;
					bspush 19;
					if_scmpgt L12;
				L11:	sload 8;
					ifge L13;
				L12:	sspush 27265;
					invokestatic 78;		// javacard/framework/ISOException.throwIt(S)V
				L13:	sload 8;
					sload 6;
					invokestatic 149;		// com/sun/javacard/impl/NativeMethods.getChannelStatus(BB)B
					sstore 4;
				L14:	sload 7;
					slookupswitch L46 2 -128 L15 0 L20;
				L15:	sload 8;
					ifne L17;
				L16:	sspush 27265;
					invokestatic 78;		// javacard/framework/ISOException.throwIt(S)V
				L17:	sload 4;
					sconst_2;
					sand;
					sconst_2;
					if_scmpne L19;
				L18:	sload 8;
					sload 6;
					invokestatic 160;		// com/sun/javacard/impl/PrivAccess.deselectOnly(BB)V
					sload 8;
					sload 6;
					sconst_0;
					invokestatic 161;		// com/sun/javacard/impl/NativeMethods.channelManage(BBB)B
					pop;
					goto_w L47;
				L19:	sspush 25088;
					invokestatic 78;		// javacard/framework/ISOException.throwIt(S)V
					goto_w L47;
				L20:	sload 8;
					ifne L27;
				L21:	aload_1;
					invokevirtual 162;		// setOutgoing()S
					sstore 9;
				L22:	sload 9;
					sconst_1;
					if_scmpeq L24;
				L23:	sspush 27649;
					invokestatic 78;		// javacard/framework/ISOException.throwIt(S)V
				L24:	sconst_m1;
					sload 6;
					sconst_2;
					invokestatic 161;		// com/sun/javacard/impl/NativeMethods.channelManage(BBB)B
					sstore_2;
					sload_2;
					sconst_m1;
					if_scmpne L26;
				L25:	sspush 27265;
					invokestatic 78;		// javacard/framework/ISOException.throwIt(S)V
				L26:	goto L30;
				L27:	sload 8;
					sload 6;
					sconst_1;
					invokestatic 161;		// com/sun/javacard/impl/NativeMethods.channelManage(BBB)B
					sconst_m1;
					if_scmpeq L29;
				L28:	sload 8;
					sstore_2;
					goto L30;
				L29:	sspush 27270;
					invokestatic 78;		// javacard/framework/ISOException.throwIt(S)V
				L30:	sload_3;
					ifne L32;
				L31:	sload_2;
					sload 6;
					invokestatic 163;		// com/sun/javacard/impl/PrivAccess.selectDefaultApplet(BB)V
					goto L35;
				L32:	sload_3;
					sload 6;
					invokestatic 92;		// com/sun/javacard/impl/PrivAccess.getSelectedAppID(BB)B
					sstore 9;
				L33:	sload 9;
					sconst_m1;
					if_scmpeq L35;
				L34:	sload_2;
					sload 6;
					sload 9;
					invokestatic 164;		// com/sun/javacard/impl/PrivAccess.selectOnly(BBB)V
				L35:	goto L44;
				L36:	astore 9;
				L37:	sload_2;
					sload 6;
					sconst_0;
					invokestatic 161;		// com/sun/javacard/impl/NativeMethods.channelManage(BBB)B
					pop;
					aload 9;
					invokevirtual 143;		// getReason()S
					invokestatic 78;		// javacard/framework/ISOException.throwIt(S)V
				L38:	goto L44;
				L39:	astore 9;
				L40:	sload_2;
					sload 6;
					sconst_0;
					invokestatic 161;		// com/sun/javacard/impl/NativeMethods.channelManage(BBB)B
					pop;
					aload 9;
					invokevirtual 165;		// getReason()S
					sconst_5;
					if_scmpne L44;
				L41:	sload 8;
					ifne L43;
				L42:	sspush 27265;
					invokestatic 78;		// javacard/framework/ISOException.throwIt(S)V
					goto L44;
				L43:	sspush 27270;
					invokestatic 78;		// javacard/framework/ISOException.throwIt(S)V
				L44:	sload 8;
					ifne L47;
				L45:	aload_1;
					sconst_1;
					invokevirtual 166;		// setOutgoingLength(S)V
					getstatic_a 154;		// reference javacard/framework/Dispatcher.theAPDUBuffer
					sconst_0;
					sload_2;
					bastore;
					aload_1;
					sconst_0;
					sconst_1;
					invokevirtual 167;		// sendBytes(SS)V
					goto L47;
				L46:	sspush 27265;
					invokestatic 78;		// javacard/framework/ISOException.throwIt(S)V
				L47:	return;
			.exceptionTable {
				// start_block end_block handler_block catch_type_index
				L30 L35 L36 124;
				L30 L35 L39 159;
			}
		}

		.method  selectAPDU(Ljavacard/framework/APDU;)V 129 {
			.stack 4;
			.locals 4;

				L0:	invokestatic 43;		// com/sun/javacard/impl/NativeMethods.getCurrentlySelectedChannel()B
					sstore_2;
				L1:	invokestatic 82;		// com/sun/javacard/impl/NativeMethods.getActiveInterface()B
					sstore_3;
				L2:	sload_2;
					sload_3;
					invokestatic 149;		// com/sun/javacard/impl/NativeMethods.getChannelStatus(BB)B
					ifne L6;
				L3:	sload_2;
					sload_3;
					sconst_1;
					invokestatic 161;		// com/sun/javacard/impl/NativeMethods.channelManage(BBB)B
					sstore 4;
				L4:	sload 4;
					sconst_m1;
					if_scmpne L6;
				L5:	sspush 26753;
					invokestatic 78;		// javacard/framework/ISOException.throwIt(S)V
				L6:	getstatic_a 154;		// reference javacard/framework/Dispatcher.theAPDUBuffer
					sconst_2;
					baload;
					sconst_4;
					if_scmpne L19;
				L7:	getstatic_a 154;		// reference javacard/framework/Dispatcher.theAPDUBuffer
					sconst_3;
					baload;
					bspush -29;
					sand;
					ifeq L9;
				L8:	return;
				L9:	aload_1;
					invokevirtual 168;		// setIncomingAndReceive()S
					s2b;
					sstore 4;
				L10:	sload 4;
					getstatic_a 154;		// reference javacard/framework/Dispatcher.theAPDUBuffer
					sconst_4;
					baload;
					if_scmpne L18;
				L11:	getstatic_a 154;		// reference javacard/framework/Dispatcher.theAPDUBuffer
					sconst_5;
					sload 4;
					invokestatic 169;		// com/sun/javacard/impl/AppletMgr.findApplet([BSB)B
					sstore 5;
				L12:	sload 5;
					sconst_m1;
					if_scmpeq L18;
				L13:	getstatic_a 145;		// reference javacard/framework/Dispatcher.thePrivAccess
					sload 5;
					invokevirtual 344;		// getAID(B)Ljavacard/framework/AID;
					invokestatic 170;		// com/sun/javacard/impl/PrivAccess.getAppState(Ljavacard/framework/AID;)B
					sconst_2;
					if_scmplt L17;
				L14:	sload_2;
					sload_3;
					sload 5;
					invokestatic 171;		// com/sun/javacard/impl/PrivAccess.isMultiSelectionOK(BBB)Z
					ifne L16;
				L15:	sspush 27013;
					invokestatic 78;		// javacard/framework/ISOException.throwIt(S)V
				L16:	sload_2;
					sload_3;
					sload 5;
					invokestatic 172;		// com/sun/javacard/impl/PrivAccess.selectApplet(BBB)V
					goto L18;
				L17:	sload_2;
					sload_3;
					invokestatic 160;		// com/sun/javacard/impl/PrivAccess.deselectOnly(BB)V
					sload_2;
					sload_3;
					sconst_0;
					sconst_0;
					invokestatic 173;		// com/sun/javacard/impl/NativeMethods.setChannelContext(BBBZ)Z
					pop;
				L18:	aload_0;
					invokevirtual 174;		// undoReceive()V
				L19:	goto L26;
				L20:	astore 4;
				L21:	sload_2;
					ifeq L23;
				L22:	sload_2;
					sload_3;
					sconst_0;
					invokestatic 161;		// com/sun/javacard/impl/NativeMethods.channelManage(BBB)B
					pop;
				L23:	aload 4;
					invokevirtual 165;		// getReason()S
					sconst_5;
					if_scmpne L25;
				L24:	sspush 26753;
					invokestatic 78;		// javacard/framework/ISOException.throwIt(S)V
					goto L26;
				L25:	aload 4;
					invokevirtual 165;		// getReason()S
					invokestatic 255;		// javacard/framework/SystemException.throwIt(S)V
				L26:	return;
			.exceptionTable {
				// start_block end_block handler_block catch_type_index
				L6 L8 L20 159;
				L9 L19 L20 159;
			}
		}

		.method  undoReceive()V 130 {
			.stack 1;
			.locals 0;

				L0:	getstatic_a 131;		// reference javacard/framework/Dispatcher.theAPDU
					invokevirtual 175;		// undoIncomingAndReceive()V
					return;
		}

		.method static cardReset()V {
			.stack 2;
			.locals 0;

				L0:	getstatic_a 176;		// reference javacard/framework/Dispatcher.internArraySensitiveResultStateMachine
					ifnonnull L2;
				L1:	getstatic_s 177;		// short javacard/framework/Dispatcher.lenInternArrSensitResStateMachine
					sconst_1;
					invokestatic 178;		// javacard/framework/JCSystem.makeTransientShortArray(SB)[S
					putstatic_a 176;		// reference javacard/framework/Dispatcher.internArraySensitiveResultStateMachine
				L2:	getstatic_a 176;		// reference javacard/framework/Dispatcher.internArraySensitiveResultStateMachine
					invokestatic 179;		// com/sun/javacard/impl/NativeMethods.sensitiveResultInitialize([S)V
					sconst_0;
					sconst_0;
					invokestatic 163;		// com/sun/javacard/impl/PrivAccess.selectDefaultApplet(BB)V
					invokestatic 180;		// com/sun/javacard/impl/GarbageCollector.getSweepStarted()Z
					ifeq L4;
				L3:	invokestatic 147;		// com/sun/javacard/impl/GarbageCollector.startGC()Z
					pop;
				L4:	invokestatic 181;		// com/sun/javacard/impl/PackageMgr.restore()V
					return;
		}

		.method static cardInit()V {
			.stack 3;
			.locals 1;

				L0:	invokestatic 182;		// javacard/framework/Dispatcher.initSystemExceptions()V
					getstatic_a 156;		// reference javacard/framework/Dispatcher.theDispatcher
					ifnonnull L2;
				L1:	new 183;		// javacard/framework/Dispatcher
					dup;
					invokespecial 184;		// javacard/framework/Dispatcher.<init>()V
					putstatic_a 156;		// reference javacard/framework/Dispatcher.theDispatcher
				L2:	new 185;		// javacard/framework/CardException
					dup;
					sconst_0;
					invokespecial 186;		// javacard/framework/CardException.<init>(S)V
					astore_0;
				L3:	aload_0;
					sconst_1;
					invokestatic 73;		// com/sun/javacard/impl/NativeMethods.setJCREentry(Ljava/lang/Object;Z)V
					new 187;		// javacard/framework/APDUException
					dup;
					sconst_0;
					invokespecial 188;		// javacard/framework/APDUException.<init>(S)V
					astore_0;
					aload_0;
					sconst_1;
					invokestatic 73;		// com/sun/javacard/impl/NativeMethods.setJCREentry(Ljava/lang/Object;Z)V
					new 124;		// javacard/framework/ISOException
					dup;
					sconst_0;
					invokespecial 189;		// javacard/framework/ISOException.<init>(S)V
					astore_0;
					aload_0;
					sconst_1;
					invokestatic 73;		// com/sun/javacard/impl/NativeMethods.setJCREentry(Ljava/lang/Object;Z)V
					new 190;		// javacard/framework/PINException
					dup;
					sconst_0;
					invokespecial 191;		// javacard/framework/PINException.<init>(S)V
					astore_0;
					aload_0;
					sconst_1;
					invokestatic 73;		// com/sun/javacard/impl/NativeMethods.setJCREentry(Ljava/lang/Object;Z)V
					new 192;		// javacard/framework/UserException
					dup;
					sconst_0;
					invokespecial 193;		// javacard/framework/UserException.<init>(S)V
					astore_0;
					aload_0;
					sconst_1;
					invokestatic 73;		// com/sun/javacard/impl/NativeMethods.setJCREentry(Ljava/lang/Object;Z)V
					new 194;		// javacard/security/CryptoException
					dup;
					sconst_0;
					invokespecial 195;		// javacard/security/CryptoException.<init>(S)V
					astore_0;
					aload_0;
					sconst_1;
					invokestatic 73;		// com/sun/javacard/impl/NativeMethods.setJCREentry(Ljava/lang/Object;Z)V
					new 196;		// javacard/framework/APDU
					dup;
					invokespecial 197;		// javacard/framework/APDU.<init>()V
					putstatic_a 131;		// reference javacard/framework/Dispatcher.theAPDU
					getstatic_a 131;		// reference javacard/framework/Dispatcher.theAPDU
					sconst_1;
					invokestatic 73;		// com/sun/javacard/impl/NativeMethods.setJCREentry(Ljava/lang/Object;Z)V
					new 198;		// com/sun/javacard/impl/PrivAccess
					dup;
					invokespecial 199;		// com/sun/javacard/impl/PrivAccess.<init>()V
					dup;
					putstatic_a 343;		// reference javacard/framework/JCSystem.thePrivAccess
					putstatic_a 145;		// reference javacard/framework/Dispatcher.thePrivAccess
					getstatic_a 145;		// reference javacard/framework/Dispatcher.thePrivAccess
					sconst_0;
					invokestatic 73;		// com/sun/javacard/impl/NativeMethods.setJCREentry(Ljava/lang/Object;Z)V
					invokestatic 200;		// com/sun/javacard/impl/PrivAccess.getPackedBoolean()Lcom/sun/javacard/impl/PackedBoolean;
					invokevirtual 201;		// allocate()B
					invokestatic 202;		// com/sun/javacard/impl/GarbageCollector.setGCRequested(B)V
					getstatic_a 131;		// reference javacard/framework/Dispatcher.theAPDU
					invokevirtual 151;		// getBuffer()[B
					putstatic_a 154;		// reference javacard/framework/Dispatcher.theAPDUBuffer
					getstatic_a 154;		// reference javacard/framework/Dispatcher.theAPDUBuffer
					sconst_1;
					invokestatic 73;		// com/sun/javacard/impl/NativeMethods.setJCREentry(Ljava/lang/Object;Z)V
					invokestatic 203;		// com/sun/javacard/impl/CryptoInit.initCryptoStorage()V
					getstatic_a 131;		// reference javacard/framework/Dispatcher.theAPDU
					invokestatic 204;		// com/sun/javacard/impl/PrivAccess.initialize(Ljavacard/framework/APDU;)V
					invokestatic 205;		// com/sun/javacard/impl/NativeMethods.setCardInitialized()V
					return;
		}

		.method private static initSystemExceptions()V {
			.stack 3;
			.locals 1;

				L0:	new 206;		// java/lang/ArrayIndexOutOfBoundsException
					dup;
					invokespecial 207;		// java/lang/ArrayIndexOutOfBoundsException.<init>()V
					putstatic_a 208;		// reference javacard/framework/Dispatcher.arrayIndexOutOfBoundsException
					getstatic_a 208;		// reference javacard/framework/Dispatcher.arrayIndexOutOfBoundsException
					sconst_1;
					invokestatic 73;		// com/sun/javacard/impl/NativeMethods.setJCREentry(Ljava/lang/Object;Z)V
					new 209;		// java/lang/NegativeArraySizeException
					dup;
					invokespecial 210;		// java/lang/NegativeArraySizeException.<init>()V
					putstatic_a 211;		// reference javacard/framework/Dispatcher.negativeArraySizeException
					getstatic_a 211;		// reference javacard/framework/Dispatcher.negativeArraySizeException
					sconst_1;
					invokestatic 73;		// com/sun/javacard/impl/NativeMethods.setJCREentry(Ljava/lang/Object;Z)V
					new 253;		// java/lang/NullPointerException
					dup;
					invokespecial 212;		// java/lang/NullPointerException.<init>()V
					putstatic_a 213;		// reference javacard/framework/Dispatcher.nullPointerException
					getstatic_a 213;		// reference javacard/framework/Dispatcher.nullPointerException
					sconst_1;
					invokestatic 73;		// com/sun/javacard/impl/NativeMethods.setJCREentry(Ljava/lang/Object;Z)V
					new 214;		// java/lang/ClassCastException
					dup;
					invokespecial 215;		// java/lang/ClassCastException.<init>()V
					putstatic_a 216;		// reference javacard/framework/Dispatcher.classCastException
					getstatic_a 216;		// reference javacard/framework/Dispatcher.classCastException
					sconst_1;
					invokestatic 73;		// com/sun/javacard/impl/NativeMethods.setJCREentry(Ljava/lang/Object;Z)V
					new 217;		// java/lang/ArithmeticException
					dup;
					invokespecial 218;		// java/lang/ArithmeticException.<init>()V
					putstatic_a 219;		// reference javacard/framework/Dispatcher.arithmeticException
					getstatic_a 219;		// reference javacard/framework/Dispatcher.arithmeticException
					sconst_1;
					invokestatic 73;		// com/sun/javacard/impl/NativeMethods.setJCREentry(Ljava/lang/Object;Z)V
					new 220;		// java/lang/SecurityException
					dup;
					invokespecial 221;		// java/lang/SecurityException.<init>()V
					putstatic_a 94;		// reference javacard/framework/Dispatcher.securityException
					getstatic_a 94;		// reference javacard/framework/Dispatcher.securityException
					sconst_1;
					invokestatic 73;		// com/sun/javacard/impl/NativeMethods.setJCREentry(Ljava/lang/Object;Z)V
					getstatic_a 94;		// reference javacard/framework/Dispatcher.securityException
					invokestatic 222;		// com/sun/javacard/impl/SecurityExceptionHelper.initSE(Ljava/lang/SecurityException;)V
					new 223;		// java/lang/ArrayStoreException
					dup;
					invokespecial 224;		// java/lang/ArrayStoreException.<init>()V
					putstatic_a 225;		// reference javacard/framework/Dispatcher.arrayStoreException
					getstatic_a 225;		// reference javacard/framework/Dispatcher.arrayStoreException
					sconst_1;
					invokestatic 73;		// com/sun/javacard/impl/NativeMethods.setJCREentry(Ljava/lang/Object;Z)V
					new 226;		// javacard/framework/CardRuntimeException
					dup;
					sconst_0;
					invokespecial 48;		// javacard/framework/CardRuntimeException.<init>(S)V
					astore_0;
				L1:	aload_0;
					sconst_1;
					invokestatic 73;		// com/sun/javacard/impl/NativeMethods.setJCREentry(Ljava/lang/Object;Z)V
					new 159;		// javacard/framework/SystemException
					dup;
					sconst_0;
					invokespecial 227;		// javacard/framework/SystemException.<init>(S)V
					putstatic_a 228;		// reference javacard/framework/Dispatcher.systemException
					getstatic_a 228;		// reference javacard/framework/Dispatcher.systemException
					sconst_1;
					invokestatic 73;		// com/sun/javacard/impl/NativeMethods.setJCREentry(Ljava/lang/Object;Z)V
					new 229;		// javacard/framework/TransactionException
					dup;
					sconst_0;
					invokespecial 230;		// javacard/framework/TransactionException.<init>(S)V
					putstatic_a 231;		// reference javacard/framework/Dispatcher.transactionException
					getstatic_a 231;		// reference javacard/framework/Dispatcher.transactionException
					sconst_1;
					invokestatic 73;		// com/sun/javacard/impl/NativeMethods.setJCREentry(Ljava/lang/Object;Z)V
					new 232;		// javacardx/framework/util/UtilException
					dup;
					sconst_0;
					invokespecial 233;		// javacardx/framework/util/UtilException.<init>(S)V
					putstatic_a 234;		// reference javacard/framework/Dispatcher.utilException
					getstatic_a 234;		// reference javacard/framework/Dispatcher.utilException
					sconst_1;
					invokestatic 73;		// com/sun/javacard/impl/NativeMethods.setJCREentry(Ljava/lang/Object;Z)V
					new 235;		// javacardx/framework/time/DateTimeException
					dup;
					sconst_0;
					invokespecial 236;		// javacardx/framework/time/DateTimeException.<init>(S)V
					putstatic_a 237;		// reference javacard/framework/Dispatcher.dateTimeException
					getstatic_a 237;		// reference javacard/framework/Dispatcher.dateTimeException
					sconst_1;
					invokestatic 73;		// com/sun/javacard/impl/NativeMethods.setJCREentry(Ljava/lang/Object;Z)V
					new 238;		// java/io/IOException
					dup;
					invokespecial 239;		// java/io/IOException.<init>()V
					putstatic_a 113;		// reference javacard/framework/Dispatcher.ioException
					getstatic_a 113;		// reference javacard/framework/Dispatcher.ioException
					sconst_1;
					invokestatic 73;		// com/sun/javacard/impl/NativeMethods.setJCREentry(Ljava/lang/Object;Z)V
					new 240;		// javacardx/framework/string/StringException
					dup;
					sconst_0;
					invokespecial 241;		// javacardx/framework/string/StringException.<init>(S)V
					putstatic_a 242;		// reference javacard/framework/Dispatcher.stringException
					getstatic_a 242;		// reference javacard/framework/Dispatcher.stringException
					sconst_1;
					invokestatic 73;		// com/sun/javacard/impl/NativeMethods.setJCREentry(Ljava/lang/Object;Z)V
					return;
		}

		.method  <init>()V {
			.stack 1;
			.locals 0;

				L0:	aload_0;
					invokespecial 254;		// java/lang/Object.<init>()V
					return;
		}

	}

	.class public SystemException 13 extends CardRuntimeException {

		.fields {
			public static final short ILLEGAL_VALUE = 1;		// S
			public static final short NO_TRANSIENT_SPACE = 2;		// S
			public static final short ILLEGAL_TRANSIENT = 3;		// S
			public static final short ILLEGAL_AID = 4;		// S
			public static final short NO_RESOURCE = 5;		// S
			public static final short ILLEGAL_USE = 6;		// S
			private static SystemException systemInstance;		// Ljavacard/framework/SystemException;
		}

		.publicMethodTable 3 3 {
			equals(Ljava/lang/Object;)Z 0;
			getReason()S 1;
			setReason(S)V 2;
		}

		.packageMethodTable 0 {
		}

		.method public <init>(S)V 0 {
			.stack 2;
			.locals 0;

				L0:	aload_0;
					sload_1;
					invokespecial 48;		// javacard/framework/CardRuntimeException.<init>(S)V
					getstatic_a 243;		// reference javacard/framework/SystemException.systemInstance
					ifnonnull L2;
				L1:	aload_0;
					putstatic_a 243;		// reference javacard/framework/SystemException.systemInstance
				L2:	return;
		}

		.method public static throwIt(S)V 1 {
			.stack 2;
			.locals 0;

				L0:	getstatic_a 243;		// reference javacard/framework/SystemException.systemInstance
					sload_0;
					invokevirtual 244;		// setReason(S)V
					getstatic_a 243;		// reference javacard/framework/SystemException.systemInstance
					athrow;
		}

	}

	.class  T0APDUImpl extends 0.0 {		// extends java/lang/Object

		.fields {
			private byte[] buffer 0;		// [B
			private byte[] scratchBuffer 1;		// [B
			private 1.12 thePackedBoolean 2;		// Lcom/sun/javacard/impl/PackedBoolean;
			private byte incomingFlag 3;		// B
			private byte outgoingFlag 4;		// B
			private byte outgoingLenSetFlag 5;		// B
			private byte sendInProgressFlag 6;		// B
			private byte noChainingFlag 7;		// B
			private byte noGetResponseFlag 8;		// B
			private byte extendedAPDUFlag 9;		// B
			private byte envelopeFlag 10;		// B
			private byte extendedSupportFlag 11;		// B
			private byte determinedLE 12;		// B
			private static final short BUFFERSIZE = 133;		// S
			private static final short MAX_XFER_DATA_LENGTH = 128;		// S
			private static final byte IFSC = 1;		// B
			private static final short IFSD = 258;		// S
			private static APDUComm theAPDU;		// Ljavacard/framework/APDUComm;
			private static byte[] ramByteVars;		// [B
			private static short[] ramShortVars;		// [S
			private static final byte LE = 0;		// B
			private static final byte LR = 1;		// B
			private static final byte LC = 2;		// B
			private static final byte PRE_READ_LENGTH = 3;		// B
			private static final byte INCOMIMG_LENGTH = 4;		// B
			private static final byte RAM_SHORT_VARS_LENGTH = 5;		// B
			private static final byte CURRENT_STATE = 0;		// B
			private static final byte LOGICAL_CHN = 1;		// B
			private static final byte RAM_BYTE_VARS_LENGTH = 2;		// B
			private static final short BUFFER_OVERFLOW = -16383;		// S
			private static final short READ_ERROR = -16381;		// S
			private static final short WRITE_ERROR = -16380;		// S
			private static final short INVALID_GET_RESPONSE = -16378;		// S
			private static final byte ENVELOPE_INS = -62;		// B
			private static final short MAX_LE = 256;		// S
			private static final short MAX_EXT_LE = 32767;		// S
			private static final byte ACK_NONE = 0;		// B
			private static final byte ACK_INS = 1;		// B
			private static final byte ACK_NOT_INS = 2;		// B
		}

		.publicMethodTable 1 31 {
			equals(Ljava/lang/Object;)Z 0;
			getLogicalChannel()B 255;
			getNoChainingFlag()Z 255;
			getBuffer()[B 255;
			getInBlockSize()S 255;
			getOutBlockSize()S 255;
			getProtocol()B 255;
			getNAD()B 255;
			setOutgoing()S 255;
			setOutgoingNoChaining()S 255;
			setOutgoingLength(S)V 255;
			receiveBytes(S)S 255;
			setIncomingAndReceive()S 255;
			sendBytes(SS)V 255;
			sendBytesLong([BSS)V 255;
			setOutgoingAndSend(SS)V 255;
			getCurrentState()B 255;
			getCurrentAPDUBuffer()[B 255;
			getCLAChannel()B 255;
			resetAPDU()V 255;
			markExtendedSupport(Z)V 255;
			complete(S)V 255;
			undoIncomingAndReceive()V 255;
			waitExtension()V 255;
			isValidCLA()Z 255;
			isCommandChainingCLA()Z 255;
			isSecureMessagingCLA()Z 255;
			isISOInterindustryCLA()Z 255;
			getIncomingLength()S 255;
			getOffsetCdata()S 255;
			verifyLe()V 255;
		}

		.packageMethodTable 0 {
		}

		.implementedInterfaceInfoTable { 
			.interface APDUComm { 
				1;		// getLogicalChannel()B
				2;		// getNoChainingFlag()Z
				19;		// resetAPDU()V
				21;		// complete(S)V
				22;		// undoIncomingAndReceive()V
				18;		// getCLAChannel()B
				23;		// waitExtension()V
				3;		// getBuffer()[B
				4;		// getInBlockSize()S
				5;		// getOutBlockSize()S
				6;		// getProtocol()B
				7;		// getNAD()B
				8;		// setOutgoing()S
				9;		// setOutgoingNoChaining()S
				10;		// setOutgoingLength(S)V
				11;		// receiveBytes(S)S
				12;		// setIncomingAndReceive()S
				13;		// sendBytes(SS)V
				14;		// sendBytesLong([BSS)V
				15;		// setOutgoingAndSend(SS)V
				16;		// getCurrentState()B
				17;		// getCurrentAPDUBuffer()[B
				20;		// markExtendedSupport(Z)V
				28;		// getIncomingLength()S
				29;		// getOffsetCdata()S
				24;		// isValidCLA()Z
				25;		// isCommandChainingCLA()Z
				26;		// isSecureMessagingCLA()Z
				27;		// isISOInterindustryCLA()Z
				30;		// verifyLe()V
			}

		}

		.method private getLe()S {
			.stack 2;
			.locals 0;

				L0:	getstatic_a 245;		// reference javacard/framework/T0APDUImpl.ramShortVars
					sconst_0;
					saload;
					ifne L4;
				L1:	aload_0;
					invokespecial 246;		// javacard/framework/T0APDUImpl.getExtendedSupportFlag()Z
					ifeq L3;
				L2:	sspush 32767;
					sreturn;
				L3:	sspush 256;
					sreturn;
				L4:	getstatic_a 245;		// reference javacard/framework/T0APDUImpl.ramShortVars
					sconst_0;
					saload;
					sreturn;
		}

		.method private setLe(S)V {
			.stack 4;
			.locals 0;

				L0:	getstatic_a 245;		// reference javacard/framework/T0APDUImpl.ramShortVars
					sconst_0;
					sload_1;
					sspush 32767;
					sand;
					sastore;
					return;
		}

		.method private getIL()S {
			.stack 2;
			.locals 0;

				L0:	getstatic_a 245;		// reference javacard/framework/T0APDUImpl.ramShortVars
					sconst_4;
					saload;
					sreturn;
		}

		.method private setIL(S)V {
			.stack 3;
			.locals 0;

				L0:	getstatic_a 245;		// reference javacard/framework/T0APDUImpl.ramShortVars
					sconst_4;
					sload_1;
					sastore;
					return;
		}

		.method private getLr()S {
			.stack 2;
			.locals 0;

				L0:	getstatic_a 245;		// reference javacard/framework/T0APDUImpl.ramShortVars
					sconst_1;
					saload;
					sreturn;
		}

		.method private setLr(S)V {
			.stack 3;
			.locals 0;

				L0:	getstatic_a 245;		// reference javacard/framework/T0APDUImpl.ramShortVars
					sconst_1;
					sload_1;
					sastore;
					return;
		}

		.method private getLc()S {
			.stack 2;
			.locals 0;

				L0:	getstatic_a 245;		// reference javacard/framework/T0APDUImpl.ramShortVars
					sconst_2;
					saload;
					sreturn;
		}

		.method private setLc(S)V {
			.stack 3;
			.locals 0;

				L0:	getstatic_a 245;		// reference javacard/framework/T0APDUImpl.ramShortVars
					sconst_2;
					sload_1;
					sastore;
					return;
		}

		.method private getPreReadLength()S {
			.stack 2;
			.locals 0;

				L0:	getstatic_a 245;		// reference javacard/framework/T0APDUImpl.ramShortVars
					sconst_3;
					saload;
					sreturn;
		}

		.method private setPreReadLength(S)V {
			.stack 3;
			.locals 0;

				L0:	getstatic_a 245;		// reference javacard/framework/T0APDUImpl.ramShortVars
					sconst_3;
					sload_1;
					sastore;
					return;
		}

		.method private getCurrState()B {
			.stack 2;
			.locals 0;

				L0:	getstatic_a 247;		// reference javacard/framework/T0APDUImpl.ramByteVars
					sconst_0;
					baload;
					sreturn;
		}

		.method private setCurrState(B)V {
			.stack 3;
			.locals 0;

				L0:	getstatic_a 247;		// reference javacard/framework/T0APDUImpl.ramByteVars
					sconst_0;
					sload_1;
					bastore;
					return;
		}

		.method private resetCurrState()V {
			.stack 3;
			.locals 0;

				L0:	getstatic_a 247;		// reference javacard/framework/T0APDUImpl.ramByteVars
					sconst_0;
					sconst_0;
					bastore;
					return;
		}

		.method public getLogicalChannel()B 1 {
			.stack 2;
			.locals 0;

				L0:	getstatic_a 247;		// reference javacard/framework/T0APDUImpl.ramByteVars
					sconst_1;
					baload;
					sreturn;
		}

		.method private setLogicalChannel(B)V {
			.stack 3;
			.locals 0;

				L0:	getstatic_a 247;		// reference javacard/framework/T0APDUImpl.ramByteVars
					sconst_1;
					sload_1;
					bastore;
					return;
		}

		.method private getIncomingFlag()Z {
			.stack 2;
			.locals 0;

				L0:	getfield_a_this 11;		// reference javacard/framework/T0APDUImpl.thePackedBoolean
					getfield_b_this 12;		// byte javacard/framework/T0APDUImpl.incomingFlag
					invokevirtual 250;		// get(B)Z
					sreturn;
		}

		.method private setIncomingFlag()V {
			.stack 2;
			.locals 0;

				L0:	getfield_a_this 11;		// reference javacard/framework/T0APDUImpl.thePackedBoolean
					getfield_b_this 12;		// byte javacard/framework/T0APDUImpl.incomingFlag
					invokevirtual 251;		// set(B)V
					return;
		}

		.method private resetIncomingFlag()V {
			.stack 2;
			.locals 0;

				L0:	getfield_a_this 11;		// reference javacard/framework/T0APDUImpl.thePackedBoolean
					getfield_b_this 12;		// byte javacard/framework/T0APDUImpl.incomingFlag
					invokevirtual 252;		// reset(B)V
					return;
		}

		.method private getDeterminedLEFlag()Z {
			.stack 2;
			.locals 0;

				L0:	getfield_a_this 11;		// reference javacard/framework/T0APDUImpl.thePackedBoolean
					getfield_b_this 13;		// byte javacard/framework/T0APDUImpl.determinedLE
					invokevirtual 250;		// get(B)Z
					sreturn;
		}

		.method private setDeterminedLEFlag()V {
			.stack 2;
			.locals 0;

				L0:	getfield_a_this 11;		// reference javacard/framework/T0APDUImpl.thePackedBoolean
					getfield_b_this 13;		// byte javacard/framework/T0APDUImpl.determinedLE
					invokevirtual 251;		// set(B)V
					return;
		}

		.method private resetDeterminedLEFlag()V {
			.stack 2;
			.locals 0;

				L0:	getfield_a_this 11;		// reference javacard/framework/T0APDUImpl.thePackedBoolean
					getfield_b_this 13;		// byte javacard/framework/T0APDUImpl.determinedLE
					invokevirtual 252;		// reset(B)V
					return;
		}

		.method private getSendInProgressFlag()Z {
			.stack 2;
			.locals 0;

				L0:	getfield_a_this 11;		// reference javacard/framework/T0APDUImpl.thePackedBoolean
					getfield_b_this 14;		// byte javacard/framework/T0APDUImpl.sendInProgressFlag
					invokevirtual 250;		// get(B)Z
					sreturn;
		}

		.method private setSendInProgressFlag()V {
			.stack 2;
			.locals 0;

				L0:	getfield_a_this 11;		// reference javacard/framework/T0APDUImpl.thePackedBoolean
					getfield_b_this 14;		// byte javacard/framework/T0APDUImpl.sendInProgressFlag
					invokevirtual 251;		// set(B)V
					return;
		}

		.method private resetSendInProgressFlag()V {
			.stack 2;
			.locals 0;

				L0:	getfield_a_this 11;		// reference javacard/framework/T0APDUImpl.thePackedBoolean
					getfield_b_this 14;		// byte javacard/framework/T0APDUImpl.sendInProgressFlag
					invokevirtual 252;		// reset(B)V
					return;
		}

		.method private getOutgoingFlag()Z {
			.stack 2;
			.locals 0;

				L0:	getfield_a_this 11;		// reference javacard/framework/T0APDUImpl.thePackedBoolean
					getfield_b_this 15;		// byte javacard/framework/T0APDUImpl.outgoingFlag
					invokevirtual 250;		// get(B)Z
					sreturn;
		}

		.method private setOutgoingFlag()V {
			.stack 2;
			.locals 0;

				L0:	getfield_a_this 11;		// reference javacard/framework/T0APDUImpl.thePackedBoolean
					getfield_b_this 15;		// byte javacard/framework/T0APDUImpl.outgoingFlag
					invokevirtual 251;		// set(B)V
					return;
		}

		.method private resetOutgoingFlag()V {
			.stack 2;
			.locals 0;

				L0:	getfield_a_this 11;		// reference javacard/framework/T0APDUImpl.thePackedBoolean
					getfield_b_this 15;		// byte javacard/framework/T0APDUImpl.outgoingFlag
					invokevirtual 252;		// reset(B)V
					return;
		}

		.method private getOutgoingLenSetFlag()Z {
			.stack 2;
			.locals 0;

				L0:	getfield_a_this 11;		// reference javacard/framework/T0APDUImpl.thePackedBoolean
					getfield_b_this 16;		// byte javacard/framework/T0APDUImpl.outgoingLenSetFlag
					invokevirtual 250;		// get(B)Z
					sreturn;
		}

		.method private setOutgoingLenSetFlag()V {
			.stack 2;
			.locals 0;

				L0:	getfield_a_this 11;		// reference javacard/framework/T0APDUImpl.thePackedBoolean
					getfield_b_this 16;		// byte javacard/framework/T0APDUImpl.outgoingLenSetFlag
					invokevirtual 251;		// set(B)V
					return;
		}

		.method private resetOutgoingLenSetFlag()V {
			.stack 2;
			.locals 0;

				L0:	getfield_a_this 11;		// reference javacard/framework/T0APDUImpl.thePackedBoolean
					getfield_b_this 16;		// byte javacard/framework/T0APDUImpl.outgoingLenSetFlag
					invokevirtual 252;		// reset(B)V
					return;
		}

		.method public getNoChainingFlag()Z 2 {
			.stack 2;
			.locals 0;

				L0:	getfield_a_this 11;		// reference javacard/framework/T0APDUImpl.thePackedBoolean
					getfield_b_this 17;		// byte javacard/framework/T0APDUImpl.noChainingFlag
					invokevirtual 250;		// get(B)Z
					sreturn;
		}

		.method private setNoChainingFlag()V {
			.stack 2;
			.locals 0;

				L0:	getfield_a_this 11;		// reference javacard/framework/T0APDUImpl.thePackedBoolean
					getfield_b_this 17;		// byte javacard/framework/T0APDUImpl.noChainingFlag
					invokevirtual 251;		// set(B)V
					return;
		}

		.method private resetNoChainingFlag()V {
			.stack 2;
			.locals 0;

				L0:	getfield_a_this 11;		// reference javacard/framework/T0APDUImpl.thePackedBoolean
					getfield_b_this 17;		// byte javacard/framework/T0APDUImpl.noChainingFlag
					invokevirtual 252;		// reset(B)V
					return;
		}

		.method private getNoGetResponseFlag()Z {
			.stack 2;
			.locals 0;

				L0:	getfield_a_this 11;		// reference javacard/framework/T0APDUImpl.thePackedBoolean
					getfield_b_this 18;		// byte javacard/framework/T0APDUImpl.noGetResponseFlag
					invokevirtual 250;		// get(B)Z
					sreturn;
		}

		.method private setNoGetResponseFlag()V {
			.stack 2;
			.locals 0;

				L0:	getfield_a_this 11;		// reference javacard/framework/T0APDUImpl.thePackedBoolean
					getfield_b_this 18;		// byte javacard/framework/T0APDUImpl.noGetResponseFlag
					invokevirtual 251;		// set(B)V
					return;
		}

		.method private resetNoGetResponseFlag()V {
			.stack 2;
			.locals 0;

				L0:	getfield_a_this 11;		// reference javacard/framework/T0APDUImpl.thePackedBoolean
					getfield_b_this 18;		// byte javacard/framework/T0APDUImpl.noGetResponseFlag
					invokevirtual 252;		// reset(B)V
					return;
		}

		.method private getExtendedAPDUFlag()Z {
			.stack 2;
			.locals 0;

				L0:	getfield_a_this 11;		// reference javacard/framework/T0APDUImpl.thePackedBoolean
					getfield_b_this 19;		// byte javacard/framework/T0APDUImpl.extendedAPDUFlag
					invokevirtual 250;		// get(B)Z
					sreturn;
		}

		.method private setExtendedAPDUFlag()V {
			.stack 2;
			.locals 0;

				L0:	getfield_a_this 11;		// reference javacard/framework/T0APDUImpl.thePackedBoolean
					getfield_b_this 19;		// byte javacard/framework/T0APDUImpl.extendedAPDUFlag
					invokevirtual 251;		// set(B)V
					return;
		}

		.method private resetExtendedAPDUFlag()V {
			.stack 2;
			.locals 0;

				L0:	getfield_a_this 11;		// reference javacard/framework/T0APDUImpl.thePackedBoolean
					getfield_b_this 19;		// byte javacard/framework/T0APDUImpl.extendedAPDUFlag
					invokevirtual 252;		// reset(B)V
					return;
		}

		.method private getEnvelopeFlag()Z {
			.stack 2;
			.locals 0;

				L0:	getfield_a_this 11;		// reference javacard/framework/T0APDUImpl.thePackedBoolean
					getfield_b_this 20;		// byte javacard/framework/T0APDUImpl.envelopeFlag
					invokevirtual 250;		// get(B)Z
					sreturn;
		}

		.method private setEnvelopeFlag()V {
			.stack 2;
			.locals 0;

				L0:	getfield_a_this 11;		// reference javacard/framework/T0APDUImpl.thePackedBoolean
					getfield_b_this 20;		// byte javacard/framework/T0APDUImpl.envelopeFlag
					invokevirtual 251;		// set(B)V
					return;
		}

		.method private resetEnvelopeFlag()V {
			.stack 2;
			.locals 0;

				L0:	getfield_a_this 11;		// reference javacard/framework/T0APDUImpl.thePackedBoolean
					getfield_b_this 20;		// byte javacard/framework/T0APDUImpl.envelopeFlag
					invokevirtual 252;		// reset(B)V
					return;
		}

		.method private getExtendedSupportFlag()Z {
			.stack 2;
			.locals 0;

				L0:	getfield_a_this 11;		// reference javacard/framework/T0APDUImpl.thePackedBoolean
					getfield_b_this 21;		// byte javacard/framework/T0APDUImpl.extendedSupportFlag
					invokevirtual 250;		// get(B)Z
					sreturn;
		}

		.method private setExtendedSupportFlag()V {
			.stack 2;
			.locals 0;

				L0:	getfield_a_this 11;		// reference javacard/framework/T0APDUImpl.thePackedBoolean
					getfield_b_this 21;		// byte javacard/framework/T0APDUImpl.extendedSupportFlag
					invokevirtual 251;		// set(B)V
					return;
		}

		.method private resetExtendedSupportFlag()V {
			.stack 2;
			.locals 0;

				L0:	getfield_a_this 11;		// reference javacard/framework/T0APDUImpl.thePackedBoolean
					getfield_b_this 21;		// byte javacard/framework/T0APDUImpl.extendedSupportFlag
					invokevirtual 252;		// reset(B)V
					return;
		}

		.method private getChannelInfo()B {
			.stack 2;
			.locals 1;

				L0:	getfield_a_this 22;		// reference javacard/framework/T0APDUImpl.scratchBuffer
					sconst_0;
					baload;
					sspush 255;
					sand;
					sspush 255;
					if_scmpne L3;
				L1:	sconst_0;
					sstore_1;
				L2:	goto L10;
				L3:	aload_0;
					getfield_a_this 22;		// reference javacard/framework/T0APDUImpl.scratchBuffer
					invokespecial 263;		// javacard/framework/T0APDUImpl.isType16CLA([B)Z
					ifeq L6;
				L4:	getfield_a_this 22;		// reference javacard/framework/T0APDUImpl.scratchBuffer
					sconst_0;
					baload;
					bspush 15;
					sand;
					sstore_1;
				L5:	sload_1;
					sconst_4;
					sadd;
					s2b;
					sstore_1;
					goto L10;
				L6:	getfield_a_this 22;		// reference javacard/framework/T0APDUImpl.scratchBuffer
					sconst_0;
					baload;
					bspush 32;
					sand;
					ifeq L9;
				L7:	sconst_0;
					sstore_1;
				L8:	goto L10;
				L9:	getfield_a_this 22;		// reference javacard/framework/T0APDUImpl.scratchBuffer
					sconst_0;
					baload;
					sconst_3;
					sand;
					sstore_1;
				L10:	sload_1;
					sreturn;
		}

		.method  <init>()V {
			.stack 2;
			.locals 0;

				L0:	aload_0;
					invokespecial 254;		// java/lang/Object.<init>()V
					aload_0;
					invokestatic 264;		// com/sun/javacard/impl/NativeMethods.initAPDUBuffer()[B
					putfield_a 23;		// reference javacard/framework/T0APDUImpl.buffer
					aload_0;
					invokestatic 266;		// com/sun/javacard/impl/NativeMethods.t0InitScratchAPDUBuffer()[B
					putfield_a 22;		// reference javacard/framework/T0APDUImpl.scratchBuffer
					sconst_2;
					sconst_1;
					invokestatic 57;		// javacard/framework/JCSystem.makeTransientByteArray(SB)[B
					putstatic_a 247;		// reference javacard/framework/T0APDUImpl.ramByteVars
					sconst_5;
					sconst_1;
					invokestatic 178;		// javacard/framework/JCSystem.makeTransientShortArray(SB)[S
					putstatic_a 245;		// reference javacard/framework/T0APDUImpl.ramShortVars
					aload_0;
					invokestatic 200;		// com/sun/javacard/impl/PrivAccess.getPackedBoolean()Lcom/sun/javacard/impl/PackedBoolean;
					putfield_a 11;		// reference javacard/framework/T0APDUImpl.thePackedBoolean
					aload_0;
					getfield_a_this 11;		// reference javacard/framework/T0APDUImpl.thePackedBoolean
					invokevirtual 201;		// allocate()B
					putfield_b 12;		// byte javacard/framework/T0APDUImpl.incomingFlag
					aload_0;
					getfield_a_this 11;		// reference javacard/framework/T0APDUImpl.thePackedBoolean
					invokevirtual 201;		// allocate()B
					putfield_b 14;		// byte javacard/framework/T0APDUImpl.sendInProgressFlag
					aload_0;
					getfield_a_this 11;		// reference javacard/framework/T0APDUImpl.thePackedBoolean
					invokevirtual 201;		// allocate()B
					putfield_b 15;		// byte javacard/framework/T0APDUImpl.outgoingFlag
					aload_0;
					getfield_a_this 11;		// reference javacard/framework/T0APDUImpl.thePackedBoolean
					invokevirtual 201;		// allocate()B
					putfield_b 16;		// byte javacard/framework/T0APDUImpl.outgoingLenSetFlag
					aload_0;
					getfield_a_this 11;		// reference javacard/framework/T0APDUImpl.thePackedBoolean
					invokevirtual 201;		// allocate()B
					putfield_b 17;		// byte javacard/framework/T0APDUImpl.noChainingFlag
					aload_0;
					getfield_a_this 11;		// reference javacard/framework/T0APDUImpl.thePackedBoolean
					invokevirtual 201;		// allocate()B
					putfield_b 18;		// byte javacard/framework/T0APDUImpl.noGetResponseFlag
					aload_0;
					getfield_a_this 11;		// reference javacard/framework/T0APDUImpl.thePackedBoolean
					invokevirtual 201;		// allocate()B
					putfield_b 19;		// byte javacard/framework/T0APDUImpl.extendedAPDUFlag
					aload_0;
					getfield_a_this 11;		// reference javacard/framework/T0APDUImpl.thePackedBoolean
					invokevirtual 201;		// allocate()B
					putfield_b 20;		// byte javacard/framework/T0APDUImpl.envelopeFlag
					aload_0;
					getfield_a_this 11;		// reference javacard/framework/T0APDUImpl.thePackedBoolean
					invokevirtual 201;		// allocate()B
					putfield_b 21;		// byte javacard/framework/T0APDUImpl.extendedSupportFlag
					aload_0;
					getfield_a_this 11;		// reference javacard/framework/T0APDUImpl.thePackedBoolean
					invokevirtual 201;		// allocate()B
					putfield_b 13;		// byte javacard/framework/T0APDUImpl.determinedLE
					aload_0;
					putstatic_a 267;		// reference javacard/framework/T0APDUImpl.theAPDU
					return;
		}

		.method public getBuffer()[B 3 {
			.stack 1;
			.locals 0;

				L0:	getfield_a_this 23;		// reference javacard/framework/T0APDUImpl.buffer
					areturn;
		}

		.method public getInBlockSize()S 4 {
			.stack 1;
			.locals 0;

				L0:	sconst_1;
					sreturn;
		}

		.method public getOutBlockSize()S 5 {
			.stack 1;
			.locals 0;

				L0:	sspush 258;
					sreturn;
		}

		.method public getProtocol()B 6 {
			.stack 1;
			.locals 0;

				L0:	sconst_0;
					sreturn;
		}

		.method public getNAD()B 7 {
			.stack 1;
			.locals 0;

				L0:	sconst_0;
					sreturn;
		}

		.method private getRemainingInbound()V {
			.stack 2;
			.locals 3;

				L0:	aload_0;
					invokespecial 268;		// javacard/framework/T0APDUImpl.getEnvelopeFlag()Z
					ifeq L19;
				L1:	aload_0;
					invokespecial 268;		// javacard/framework/T0APDUImpl.getEnvelopeFlag()Z
					ifne L3;
				L2:	aload_0;
					invokespecial 269;		// javacard/framework/T0APDUImpl.getDeterminedLEFlag()Z
					ifne L19;
				L3:	sconst_5;
					invokestatic 270;		// com/sun/javacard/impl/NativeMethods.t0RcvData(S)S
					sstore_1;
				L4:	sload_1;
					ifne L7;
				L5:	sspush -28672;
					invokestatic 271;		// com/sun/javacard/impl/NativeMethods.t0SetStatus(S)S
					pop;
					invokestatic 272;		// com/sun/javacard/impl/NativeMethods.t0SndStatusRcvCommand()S
					sstore_2;
				L6:	aload_0;
					sconst_5;
					invokespecial 273;		// javacard/framework/T0APDUImpl.processEnvelopeData(S)S
					sstore_1;
				L7:	sload_1;
					sconst_m1;
					if_scmpne L9;
				L8:	sconst_4;
					invokestatic 91;		// javacard/framework/APDUException.throwIt(S)V
				L9:	aload_0;
					invokespecial 274;		// javacard/framework/T0APDUImpl.getLc()S
					sstore_2;
				L10:	sload_2;
					sload_1;
					ssub;
					sstore_2;
					sload_2;
					ifge L17;
				L11:	sconst_5;
					sstore_3;
				L12:	sload_2;
					sconst_m1;
					if_scmpne L16;
				L13:	aload_0;
					invokespecial 269;		// javacard/framework/T0APDUImpl.getDeterminedLEFlag()Z
					ifne L15;
				L14:	aload_0;
					invokespecial 275;		// javacard/framework/T0APDUImpl.setDeterminedLEFlag()V
					sconst_0;
					sstore_2;
					goto L17;
				L15:	aload_0;
					invokespecial 276;		// javacard/framework/T0APDUImpl.resetEnvelopeFlag()V
					sconst_0;
					sstore_2;
					goto L17;
				L16:	sconst_0;
					sstore_2;
					sinc 1 -2;
					aload_0;
					invokespecial 275;		// javacard/framework/T0APDUImpl.setDeterminedLEFlag()V
					aload_0;
					invokespecial 276;		// javacard/framework/T0APDUImpl.resetEnvelopeFlag()V
				L17:	aload_0;
					sload_2;
					invokespecial 277;		// javacard/framework/T0APDUImpl.setLc(S)V
				L18:	goto L1;
				L19:	return;
		}

		.method public setOutgoing()S 8 {
			.stack 2;
			.locals 0;

				L0:	aload_0;
					invokespecial 278;		// javacard/framework/T0APDUImpl.getOutgoingFlag()Z
					ifeq L2;
				L1:	sconst_1;
					invokestatic 91;		// javacard/framework/APDUException.throwIt(S)V
				L2:	aload_0;
					invokespecial 279;		// javacard/framework/T0APDUImpl.getRemainingInbound()V
					aload_0;
					invokespecial 280;		// javacard/framework/T0APDUImpl.setOutgoingFlag()V
					aload_0;
					sconst_3;
					invokespecial 281;		// javacard/framework/T0APDUImpl.setCurrState(B)V
					aload_0;
					invokespecial 282;		// javacard/framework/T0APDUImpl.getLe()S
					sreturn;
		}

		.method public setOutgoingNoChaining()S 9 {
			.stack 2;
			.locals 1;

				L0:	aload_0;
					invokespecial 278;		// javacard/framework/T0APDUImpl.getOutgoingFlag()Z
					ifeq L2;
				L1:	sconst_1;
					invokestatic 91;		// javacard/framework/APDUException.throwIt(S)V
				L2:	aload_0;
					invokespecial 279;		// javacard/framework/T0APDUImpl.getRemainingInbound()V
					aload_0;
					invokespecial 280;		// javacard/framework/T0APDUImpl.setOutgoingFlag()V
					aload_0;
					invokespecial 283;		// javacard/framework/T0APDUImpl.setNoChainingFlag()V
					aload_0;
					sconst_3;
					invokespecial 281;		// javacard/framework/T0APDUImpl.setCurrState(B)V
					aload_0;
					invokespecial 282;		// javacard/framework/T0APDUImpl.getLe()S
					sstore_1;
				L3:	sload_1;
					sspush 32767;
					if_scmpne L5;
				L4:	sspush 256;
					sstore_1;
				L5:	sload_1;
					sreturn;
		}

		.method public setOutgoingLength(S)V 10 {
			.stack 2;
			.locals 0;

				L0:	aload_0;
					invokespecial 278;		// javacard/framework/T0APDUImpl.getOutgoingFlag()Z
					ifne L2;
				L1:	sconst_1;
					invokestatic 91;		// javacard/framework/APDUException.throwIt(S)V
				L2:	aload_0;
					invokespecial 284;		// javacard/framework/T0APDUImpl.getOutgoingLenSetFlag()Z
					ifeq L4;
				L3:	sconst_1;
					invokestatic 91;		// javacard/framework/APDUException.throwIt(S)V
				L4:	sload_1;
					sspush 256;
					if_scmple L7;
				L5:	aload_0;
					invokespecial 246;		// javacard/framework/T0APDUImpl.getExtendedSupportFlag()Z
					ifne L7;
				L6:	sconst_3;
					invokestatic 91;		// javacard/framework/APDUException.throwIt(S)V
				L7:	sload_1;
					sspush 256;
					if_scmple L10;
				L8:	aload_0;
					invokevirtual 285;		// getNoChainingFlag()Z
					ifeq L10;
				L9:	sconst_3;
					invokestatic 91;		// javacard/framework/APDUException.throwIt(S)V
				L10:	sload_1;
					ifge L12;
				L11:	sconst_3;
					invokestatic 91;		// javacard/framework/APDUException.throwIt(S)V
				L12:	aload_0;
					invokespecial 286;		// javacard/framework/T0APDUImpl.setOutgoingLenSetFlag()V
					aload_0;
					sconst_4;
					invokespecial 281;		// javacard/framework/T0APDUImpl.setCurrState(B)V
					aload_0;
					sload_1;
					invokespecial 287;		// javacard/framework/T0APDUImpl.setLr(S)V
					sload_1;
					sspush 256;
					if_scmple L14;
				L13:	aload_0;
					invokespecial 288;		// javacard/framework/T0APDUImpl.setExtendedAPDUFlag()V
				L14:	return;
		}

		.method private setIncoming()V {
			.stack 2;
			.locals 1;

				L0:	aload_0;
					invokespecial 289;		// javacard/framework/T0APDUImpl.getPreReadLength()S
					ifeq L2;
				L1:	return;
				L2:	aload_0;
					invokespecial 290;		// javacard/framework/T0APDUImpl.getIncomingFlag()Z
					ifne L4;
				L3:	aload_0;
					invokespecial 278;		// javacard/framework/T0APDUImpl.getOutgoingFlag()Z
					ifeq L5;
				L4:	sconst_1;
					invokestatic 91;		// javacard/framework/APDUException.throwIt(S)V
				L5:	aload_0;
					invokespecial 291;		// javacard/framework/T0APDUImpl.setIncomingFlag()V
					aload_0;
					invokespecial 282;		// javacard/framework/T0APDUImpl.getLe()S
					sstore_1;
				L6:	aload_0;
					invokespecial 246;		// javacard/framework/T0APDUImpl.getExtendedSupportFlag()Z
					ifne L9;
				L7:	sload_1;
					sspush 256;
					if_scmple L9;
				L8:	sspush 26368;
					invokestatic 91;		// javacard/framework/APDUException.throwIt(S)V
				L9:	aload_0;
					sload_1;
					invokespecial 277;		// javacard/framework/T0APDUImpl.setLc(S)V
					aload_0;
					sload_1;
					invokespecial 292;		// javacard/framework/T0APDUImpl.setIL(S)V
					aload_0;
					sconst_0;
					invokespecial 293;		// javacard/framework/T0APDUImpl.setLe(S)V
					return;
		}

		.method public receiveBytes(S)S 11 {
			.stack 4;
			.locals 3;

				L0:	aload_0;
					invokespecial 290;		// javacard/framework/T0APDUImpl.getIncomingFlag()Z
					ifeq L2;
				L1:	aload_0;
					invokespecial 278;		// javacard/framework/T0APDUImpl.getOutgoingFlag()Z
					ifeq L3;
				L2:	sconst_1;
					invokestatic 91;		// javacard/framework/APDUException.throwIt(S)V
				L3:	aload_0;
					invokespecial 274;		// javacard/framework/T0APDUImpl.getLc()S
					sspush 32767;
					sand;
					sstore_2;
				L4:	sload_1;
					ifge L6;
				L5:	sconst_2;
					invokestatic 91;		// javacard/framework/APDUException.throwIt(S)V
				L6:	aload_0;
					invokespecial 289;		// javacard/framework/T0APDUImpl.getPreReadLength()S
					sspush 32767;
					sand;
					sstore_3;
				L7:	sload_3;
					ifeq L12;
				L8:	aload_0;
					sconst_0;
					invokespecial 294;		// javacard/framework/T0APDUImpl.setPreReadLength(S)V
					sload_2;
					ifne L10;
				L9:	aload_0;
					sconst_2;
					invokespecial 281;		// javacard/framework/T0APDUImpl.setCurrState(B)V
					goto L11;
				L10:	aload_0;
					sconst_1;
					invokespecial 281;		// javacard/framework/T0APDUImpl.setCurrState(B)V
				L11:	sload_3;
					sreturn;
				L12:	sload_2;
					ifeq L30;
				L13:	aload_0;
					invokespecial 268;		// javacard/framework/T0APDUImpl.getEnvelopeFlag()Z
					ifne L17;
				L14:	sload_1;
					invokestatic 270;		// com/sun/javacard/impl/NativeMethods.t0RcvData(S)S
					sstore 4;
				L15:	sload 4;
					ifge L22;
				L16:	sconst_4;
					invokestatic 91;		// javacard/framework/APDUException.throwIt(S)V
					goto L22;
				L17:	sload_1;
					invokestatic 270;		// com/sun/javacard/impl/NativeMethods.t0RcvData(S)S
					sstore 4;
				L18:	sload 4;
					ifge L20;
				L19:	sconst_4;
					invokestatic 91;		// javacard/framework/APDUException.throwIt(S)V
				L20:	sload 4;
					ifne L22;
				L21:	sspush -28672;
					invokestatic 271;		// com/sun/javacard/impl/NativeMethods.t0SetStatus(S)S
					pop;
					invokestatic 272;		// com/sun/javacard/impl/NativeMethods.t0SndStatusRcvCommand()S
					pop;
					aload_0;
					sload_1;
					invokespecial 273;		// javacard/framework/T0APDUImpl.processEnvelopeData(S)S
					sstore 4;
				L22:	sload_1;
					sload 4;
					invokestatic 295;		// com/sun/javacard/impl/NativeMethods.t0CopyToAPDUBuffer(SS)V
					sload_2;
					sload 4;
					ssub;
					sstore_2;
					sload_2;
					ifge L26;
				L23:	sload_2;
					sconst_m1;
					if_scmpne L25;
				L24:	sconst_0;
					sstore_2;
					sinc 4 -1;
					aload_0;
					invokespecial 275;		// javacard/framework/T0APDUImpl.setDeterminedLEFlag()V
					goto L26;
				L25:	sconst_0;
					sstore_2;
					sinc 4 -2;
					aload_0;
					invokespecial 275;		// javacard/framework/T0APDUImpl.setDeterminedLEFlag()V
					aload_0;
					invokespecial 276;		// javacard/framework/T0APDUImpl.resetEnvelopeFlag()V
				L26:	aload_0;
					sload_2;
					invokespecial 277;		// javacard/framework/T0APDUImpl.setLc(S)V
					sload_2;
					ifne L28;
				L27:	aload_0;
					sconst_2;
					invokespecial 281;		// javacard/framework/T0APDUImpl.setCurrState(B)V
					goto L29;
				L28:	aload_0;
					sconst_1;
					invokespecial 281;		// javacard/framework/T0APDUImpl.setCurrState(B)V
				L29:	sload 4;
					sreturn;
				L30:	aload_0;
					invokespecial 268;		// javacard/framework/T0APDUImpl.getEnvelopeFlag()Z
					ifeq L38;
				L31:	aload_0;
					invokespecial 269;		// javacard/framework/T0APDUImpl.getDeterminedLEFlag()Z
					ifeq L38;
				L32:	sload_1;
					invokestatic 270;		// com/sun/javacard/impl/NativeMethods.t0RcvData(S)S
					sstore 4;
				L33:	sload 4;
					ifge L35;
				L34:	sconst_4;
					invokestatic 91;		// javacard/framework/APDUException.throwIt(S)V
				L35:	sload 4;
					ifne L37;
				L36:	getfield_a_this 23;		// reference javacard/framework/T0APDUImpl.buffer
					sconst_0;
					sspush 133;
					sconst_0;
					invokestatic 262;		// javacard/framework/Util.arrayFillNonAtomic([BSSB)S
					pop;
					sspush -28672;
					invokestatic 271;		// com/sun/javacard/impl/NativeMethods.t0SetStatus(S)S
					pop;
					invokestatic 272;		// com/sun/javacard/impl/NativeMethods.t0SndStatusRcvCommand()S
					pop;
					aload_0;
					sload_1;
					invokespecial 273;		// javacard/framework/T0APDUImpl.processEnvelopeData(S)S
					sstore 4;
				L37:	sload_1;
					sload 4;
					invokestatic 295;		// com/sun/javacard/impl/NativeMethods.t0CopyToAPDUBuffer(SS)V
					aload_0;
					invokespecial 276;		// javacard/framework/T0APDUImpl.resetEnvelopeFlag()V
				L38:	aload_0;
					sconst_2;
					invokespecial 281;		// javacard/framework/T0APDUImpl.setCurrState(B)V
					sconst_0;
					sreturn;
		}

		.method public setIncomingAndReceive()S 12 {
			.stack 2;
			.locals 0;

				L0:	aload_0;
					invokespecial 296;		// javacard/framework/T0APDUImpl.setIncoming()V
					aload_0;
					invokespecial 297;		// javacard/framework/T0APDUImpl.getExtendedAPDUFlag()Z
					ifeq L2;
				L1:	aload_0;
					bspush 7;
					invokevirtual 298;		// receiveBytes(S)S
					sreturn;
				L2:	aload_0;
					sconst_5;
					invokevirtual 298;		// receiveBytes(S)S
					sreturn;
		}

		.method private send61xx(S)S {
			.stack 3;
			.locals 3;

				L0:	aload_0;
					invokevirtual 299;		// getCLAChannel()B
					sstore_2;
				L1:	sload_1;
					sstore_3;
				L2:	sload_1;
					sspush 256;
					if_scmplt L4;
				L3:	sspush 24832;
					invokestatic 271;		// com/sun/javacard/impl/NativeMethods.t0SetStatus(S)S
					pop;
					goto L5;
				L4:	sspush 24832;
					sload_1;
					sspush 255;
					sand;
					sadd;
					invokestatic 271;		// com/sun/javacard/impl/NativeMethods.t0SetStatus(S)S
					pop;
				L5:	sload_2;
					invokestatic 300;		// com/sun/javacard/impl/NativeMethods.t0SndGetResponse(B)S
					sstore 4;
				L6:	sload 4;
					sspush -16378;
					if_scmpne L8;
				L7:	aload_0;
					invokespecial 301;		// javacard/framework/T0APDUImpl.setNoGetResponseFlag()V
					sspush 170;
					invokestatic 91;		// javacard/framework/APDUException.throwIt(S)V
					goto L11;
				L8:	sload 4;
					ifle L10;
				L9:	aload_0;
					sload 4;
					invokespecial 293;		// javacard/framework/T0APDUImpl.setLe(S)V
					aload_0;
					invokespecial 282;		// javacard/framework/T0APDUImpl.getLe()S
					sstore_3;
					goto L11;
				L10:	sconst_4;
					invokestatic 91;		// javacard/framework/APDUException.throwIt(S)V
				L11:	sload_3;
					sload_1;
					if_scmpgt L2;
				L12:	aload_0;
					invokespecial 302;		// javacard/framework/T0APDUImpl.resetSendInProgressFlag()V
					sload_3;
					sreturn;
		}

		.method public sendBytes(SS)V 13 {
			.stack 4;
			.locals 4;

				L0:	sload_1;
					iflt L3;
				L1:	sload_2;
					iflt L3;
				L2:	sload_1;
					sload_2;
					sadd;
					sspush 133;
					if_scmple L4;
				L3:	sconst_2;
					invokestatic 91;		// javacard/framework/APDUException.throwIt(S)V
				L4:	aload_0;
					invokespecial 284;		// javacard/framework/T0APDUImpl.getOutgoingLenSetFlag()Z
					ifeq L6;
				L5:	aload_0;
					invokespecial 303;		// javacard/framework/T0APDUImpl.getNoGetResponseFlag()Z
					ifeq L7;
				L6:	sconst_1;
					invokestatic 91;		// javacard/framework/APDUException.throwIt(S)V
				L7:	sload_2;
					ifne L9;
				L8:	return;
				L9:	aload_0;
					invokespecial 304;		// javacard/framework/T0APDUImpl.getLr()S
					sstore 4;
				L10:	sload_2;
					sload 4;
					if_scmple L12;
				L11:	sconst_1;
					invokestatic 91;		// javacard/framework/APDUException.throwIt(S)V
				L12:	aload_0;
					invokespecial 282;		// javacard/framework/T0APDUImpl.getLe()S
					sstore 5;
				L13:	aload_0;
					invokevirtual 285;		// getNoChainingFlag()Z
					ifeq_w L32;
				L14:	aload_0;
					invokespecial 290;		// javacard/framework/T0APDUImpl.getIncomingFlag()Z
					ifne L16;
				L15:	sload 4;
					sload 5;
					if_scmpge L17;
				L16:	aload_0;
					sload 4;
					invokespecial 305;		// javacard/framework/T0APDUImpl.send61xx(S)S
					sstore 5;
					aload_0;
					invokespecial 306;		// javacard/framework/T0APDUImpl.resetIncomingFlag()V
				L17:	sload_2;
					sload 5;
					if_scmple L25;
				L18:	aload_0;
					invokespecial 307;		// javacard/framework/T0APDUImpl.getSendInProgressFlag()Z
					ifne L21;
				L19:	getfield_a_this 23;		// reference javacard/framework/T0APDUImpl.buffer
					sload_1;
					sload 5;
					sconst_1;
					invokestatic 308;		// com/sun/javacard/impl/NativeMethods.t0SndData([BSSB)S
					sstore_3;
				L20:	aload_0;
					invokespecial 309;		// javacard/framework/T0APDUImpl.setSendInProgressFlag()V
					goto L22;
				L21:	getfield_a_this 23;		// reference javacard/framework/T0APDUImpl.buffer
					sload_1;
					sload 5;
					sconst_0;
					invokestatic 308;		// com/sun/javacard/impl/NativeMethods.t0SndData([BSSB)S
					sstore_3;
				L22:	sload_3;
					ifeq L24;
				L23:	sconst_4;
					invokestatic 91;		// javacard/framework/APDUException.throwIt(S)V
				L24:	sload_1;
					sload 5;
					sadd;
					sstore_1;
					sload_2;
					sload 5;
					ssub;
					sstore_2;
					sload 4;
					sload 5;
					ssub;
					sstore 4;
					aload_0;
					sload 4;
					invokespecial 305;		// javacard/framework/T0APDUImpl.send61xx(S)S
					sstore 5;
					goto L17;
				L25:	aload_0;
					invokespecial 307;		// javacard/framework/T0APDUImpl.getSendInProgressFlag()Z
					ifne L28;
				L26:	getfield_a_this 23;		// reference javacard/framework/T0APDUImpl.buffer
					sload_1;
					sload_2;
					sconst_1;
					invokestatic 308;		// com/sun/javacard/impl/NativeMethods.t0SndData([BSSB)S
					sstore_3;
				L27:	aload_0;
					invokespecial 309;		// javacard/framework/T0APDUImpl.setSendInProgressFlag()V
					goto L29;
				L28:	getfield_a_this 23;		// reference javacard/framework/T0APDUImpl.buffer
					sload_1;
					sload_2;
					sconst_0;
					invokestatic 308;		// com/sun/javacard/impl/NativeMethods.t0SndData([BSSB)S
					sstore_3;
				L29:	sload_3;
					ifeq L31;
				L30:	sconst_4;
					invokestatic 91;		// javacard/framework/APDUException.throwIt(S)V
				L31:	sload 4;
					sload_2;
					ssub;
					sstore 4;
					sload 5;
					sload_2;
					ssub;
					sstore 5;
					goto L44;
				L32:	sload_2;
					ifle L44;
				L33:	sload_2;
					sstore 6;
				L34:	sload_2;
					sload 4;
					if_scmpne L38;
				L35:	aload_0;
					invokespecial 290;		// javacard/framework/T0APDUImpl.getIncomingFlag()Z
					ifne L38;
				L36:	sload 4;
					sload 5;
					if_scmpne L38;
				L37:	aload_0;
					invokespecial 307;		// javacard/framework/T0APDUImpl.getSendInProgressFlag()Z
					ifeq L39;
				L38:	aload_0;
					sload_2;
					invokespecial 305;		// javacard/framework/T0APDUImpl.send61xx(S)S
					sstore 6;
					aload_0;
					invokespecial 306;		// javacard/framework/T0APDUImpl.resetIncomingFlag()V
				L39:	getfield_a_this 23;		// reference javacard/framework/T0APDUImpl.buffer
					sload_1;
					sload 6;
					sconst_1;
					invokestatic 308;		// com/sun/javacard/impl/NativeMethods.t0SndData([BSSB)S
					sstore_3;
				L40:	aload_0;
					invokespecial 309;		// javacard/framework/T0APDUImpl.setSendInProgressFlag()V
					sload_3;
					ifeq L42;
				L41:	sconst_4;
					invokestatic 91;		// javacard/framework/APDUException.throwIt(S)V
				L42:	sload_1;
					sload 6;
					sadd;
					sstore_1;
					sload_2;
					sload 6;
					ssub;
					sstore_2;
					sload 4;
					sload 6;
					ssub;
					sstore 4;
					sload 4;
					sstore 5;
				L43:	goto L32;
				L44:	sload 4;
					ifne L46;
				L45:	aload_0;
					bspush 6;
					invokespecial 281;		// javacard/framework/T0APDUImpl.setCurrState(B)V
					goto L47;
				L46:	aload_0;
					sconst_5;
					invokespecial 281;		// javacard/framework/T0APDUImpl.setCurrState(B)V
				L47:	aload_0;
					sload 5;
					invokespecial 293;		// javacard/framework/T0APDUImpl.setLe(S)V
					aload_0;
					sload 4;
					invokespecial 287;		// javacard/framework/T0APDUImpl.setLr(S)V
					return;
		}

		.method public sendBytesLong([BSS)V 14 {
			.stack 5;
			.locals 1;

				L0:	aload_1;
					sload_2;
					sload_3;
					invokestatic 259;		// com/sun/javacard/impl/NativeMethods.checkArrayArgs([BSS)V
					aload_1;
					invokestatic 51;		// com/sun/javacard/impl/NativeMethods.checkPreviousContextAccess(Ljava/lang/Object;)V
					getfield_a_this 23;		// reference javacard/framework/T0APDUImpl.buffer
					arraylength;
					sstore 4;
				L1:	sload_3;
					ifle L5;
				L2:	sload_3;
					sload 4;
					if_scmpge L4;
				L3:	sload_3;
					sstore 4;
				L4:	aload_1;
					sload_2;
					getfield_a_this 23;		// reference javacard/framework/T0APDUImpl.buffer
					sconst_0;
					sload 4;
					invokestatic 52;		// javacard/framework/Util.arrayCopy([BS[BSS)S
					pop;
					aload_0;
					sconst_0;
					sload 4;
					invokevirtual 310;		// sendBytes(SS)V
					sload_3;
					sload 4;
					ssub;
					sstore_3;
					sload_2;
					sload 4;
					sadd;
					sstore_2;
					goto L1;
				L5:	return;
		}

		.method public setOutgoingAndSend(SS)V 15 {
			.stack 3;
			.locals 0;

				L0:	aload_0;
					invokevirtual 311;		// setOutgoing()S
					pop;
					aload_0;
					sload_2;
					invokevirtual 312;		// setOutgoingLength(S)V
					aload_0;
					sload_1;
					sload_2;
					invokevirtual 310;		// sendBytes(SS)V
					return;
		}

		.method public getCurrentState()B 16 {
			.stack 1;
			.locals 0;

				L0:	aload_0;
					invokespecial 313;		// javacard/framework/T0APDUImpl.getCurrState()B
					sreturn;
		}

		.method public getCurrentAPDUBuffer()[B 17 {
			.stack 1;
			.locals 0;

				L0:	getstatic_a 267;		// reference javacard/framework/T0APDUImpl.theAPDU
					invokeinterface 1 81 7;		// javacard/framework/APDUComm
					areturn;
		}

		.method public getCLAChannel()B 18 {
			.stack 1;
			.locals 0;

				L0:	getstatic_a 267;		// reference javacard/framework/T0APDUImpl.theAPDU
					invokeinterface 1 81 0;		// javacard/framework/APDUComm
					sreturn;
		}

		.method public resetAPDU()V 19 {
			.stack 2;
			.locals 0;

				L0:	aload_0;
					invokespecial 306;		// javacard/framework/T0APDUImpl.resetIncomingFlag()V
					aload_0;
					invokespecial 314;		// javacard/framework/T0APDUImpl.resetOutgoingFlag()V
					aload_0;
					invokespecial 315;		// javacard/framework/T0APDUImpl.resetOutgoingLenSetFlag()V
					aload_0;
					invokespecial 302;		// javacard/framework/T0APDUImpl.resetSendInProgressFlag()V
					aload_0;
					invokespecial 316;		// javacard/framework/T0APDUImpl.resetNoChainingFlag()V
					aload_0;
					invokespecial 317;		// javacard/framework/T0APDUImpl.resetNoGetResponseFlag()V
					aload_0;
					invokespecial 318;		// javacard/framework/T0APDUImpl.resetExtendedAPDUFlag()V
					aload_0;
					invokespecial 276;		// javacard/framework/T0APDUImpl.resetEnvelopeFlag()V
					aload_0;
					invokespecial 319;		// javacard/framework/T0APDUImpl.resetDeterminedLEFlag()V
					aload_0;
					sconst_0;
					invokespecial 294;		// javacard/framework/T0APDUImpl.setPreReadLength(S)V
					return;
		}

		.method private processEnvelopeData(S)S {
			.stack 2;
			.locals 1;

				L0:	aload_0;
					getfield_a_this 22;		// reference javacard/framework/T0APDUImpl.scratchBuffer
					invokespecial 320;		// javacard/framework/T0APDUImpl.isISOInterindustryCLA([B)Z
					ifeq L6;
				L1:	getfield_a_this 22;		// reference javacard/framework/T0APDUImpl.scratchBuffer
					sconst_1;
					baload;
					bspush -62;
					if_scmpne L6;
				L2:	sload_1;
					invokestatic 270;		// com/sun/javacard/impl/NativeMethods.t0RcvData(S)S
					sstore_2;
				L3:	sload_2;
					ifge L5;
				L4:	sconst_4;
					invokestatic 91;		// javacard/framework/APDUException.throwIt(S)V
				L5:	sload_2;
					sreturn;
				L6:	sconst_4;
					invokestatic 91;		// javacard/framework/APDUException.throwIt(S)V
					sconst_m1;
					sreturn;
		}

		.method private processEnvelopeAPDU()V {
			.stack 5;
			.locals 4;

				L0:	aload_0;
					getfield_a_this 22;		// reference javacard/framework/T0APDUImpl.scratchBuffer
					invokespecial 320;		// javacard/framework/T0APDUImpl.isISOInterindustryCLA([B)Z
					ifeq_w L16;
				L1:	getfield_a_this 22;		// reference javacard/framework/T0APDUImpl.scratchBuffer
					sconst_1;
					baload;
					bspush -62;
					if_scmpne_w L16;
				L2:	aload_0;
					invokevirtual 321;		// setIncomingAndReceive()S
					sstore_1;
				L3:	sconst_0;
					sstore_2;
				L4:	sload_2;
					sload_1;
					if_scmpge L6;
				L5:	getfield_a_this 22;		// reference javacard/framework/T0APDUImpl.scratchBuffer
					sload_2;
					getfield_a_this 22;		// reference javacard/framework/T0APDUImpl.scratchBuffer
					sconst_5;
					sload_2;
					sadd;
					baload;
					bastore;
					sinc 2 1;
					goto L4;
				L6:	getfield_a_this 22;		// reference javacard/framework/T0APDUImpl.scratchBuffer
					sload_1;
					sspush 133;
					sload_1;
					ssub;
					sconst_0;
					invokestatic 262;		// javacard/framework/Util.arrayFillNonAtomic([BSSB)S
					pop;
					sload_1;
					sconst_5;
					ssub;
					sstore_2;
				L7:	aload_0;
					invokevirtual 322;		// resetAPDU()V
					aload_0;
					invokespecial 323;		// javacard/framework/T0APDUImpl.preProcessAPDU()V
					aload_0;
					invokespecial 324;		// javacard/framework/T0APDUImpl.setEnvelopeFlag()V
					aload_0;
					aload_0;
					invokespecial 282;		// javacard/framework/T0APDUImpl.getLe()S
					invokespecial 277;		// javacard/framework/T0APDUImpl.setLc(S)V
					aload_0;
					aload_0;
					invokespecial 274;		// javacard/framework/T0APDUImpl.getLc()S
					invokespecial 292;		// javacard/framework/T0APDUImpl.setIL(S)V
					aload_0;
					invokespecial 274;		// javacard/framework/T0APDUImpl.getLc()S
					sstore_3;
				L8:	getfield_a_this 22;		// reference javacard/framework/T0APDUImpl.scratchBuffer
					sconst_5;
					baload;
					getfield_a_this 22;		// reference javacard/framework/T0APDUImpl.scratchBuffer
					bspush 6;
					baload;
					invokestatic 325;		// javacard/framework/Util.makeShort(BB)S
					sstore 4;
				L9:	sload_3;
					sload_2;
					if_scmpne L11;
				L10:	aload_0;
					sconst_0;
					invokespecial 293;		// javacard/framework/T0APDUImpl.setLe(S)V
					goto L15;
				L11:	sload_3;
					sload_2;
					sconst_1;
					ssub;
					if_scmpne L13;
				L12:	aload_0;
					getfield_a_this 22;		// reference javacard/framework/T0APDUImpl.scratchBuffer
					sload_1;
					sconst_1;
					ssub;
					baload;
					invokespecial 293;		// javacard/framework/T0APDUImpl.setLe(S)V
					goto L15;
				L13:	sload 4;
					sload_2;
					if_scmple L15;
				L14:	aload_0;
					invokespecial 288;		// javacard/framework/T0APDUImpl.setExtendedAPDUFlag()V
					aload_0;
					sload 4;
					sload_2;
					sconst_2;
					ssub;
					ssub;
					invokespecial 277;		// javacard/framework/T0APDUImpl.setLc(S)V
					aload_0;
					sload 4;
					invokespecial 292;		// javacard/framework/T0APDUImpl.setIL(S)V
					aload_0;
					sconst_0;
					invokespecial 293;		// javacard/framework/T0APDUImpl.setLe(S)V
				L15:	aload_0;
					sload 4;
					aload_0;
					invokespecial 274;		// javacard/framework/T0APDUImpl.getLc()S
					ssub;
					invokespecial 326;		// javacard/framework/T0APDUImpl.undoIncomingAndReceiveForEnvelope(S)V
					aload_0;
					aload_0;
					invokespecial 327;		// javacard/framework/T0APDUImpl.getChannelInfo()B
					invokespecial 328;		// javacard/framework/T0APDUImpl.setLogicalChannel(B)V
				L16:	sconst_0;
					sspush 133;
					invokestatic 295;		// com/sun/javacard/impl/NativeMethods.t0CopyToAPDUBuffer(SS)V
					return;
		}

		.method private undoIncomingAndReceiveForEnvelope(S)V {
			.stack 2;
			.locals 0;

				L0:	aload_0;
					sload_1;
					invokespecial 294;		// javacard/framework/T0APDUImpl.setPreReadLength(S)V
					aload_0;
					sconst_0;
					invokespecial 281;		// javacard/framework/T0APDUImpl.setCurrState(B)V
					aload_0;
					invokespecial 291;		// javacard/framework/T0APDUImpl.setIncomingFlag()V
					aload_0;
					invokespecial 314;		// javacard/framework/T0APDUImpl.resetOutgoingFlag()V
					return;
		}

		.method private preProcessAPDU()V {
			.stack 3;
			.locals 0;

				L0:	aload_0;
					getfield_a_this 22;		// reference javacard/framework/T0APDUImpl.scratchBuffer
					sconst_4;
					baload;
					sspush 255;
					sand;
					invokespecial 293;		// javacard/framework/T0APDUImpl.setLe(S)V
					aload_0;
					sconst_0;
					invokespecial 277;		// javacard/framework/T0APDUImpl.setLc(S)V
					aload_0;
					getfield_a_this 22;		// reference javacard/framework/T0APDUImpl.scratchBuffer
					sconst_4;
					baload;
					sspush 255;
					sand;
					invokespecial 292;		// javacard/framework/T0APDUImpl.setIL(S)V
					aload_0;
					invokespecial 329;		// javacard/framework/T0APDUImpl.resetCurrState()V
					aload_0;
					aload_0;
					invokespecial 327;		// javacard/framework/T0APDUImpl.getChannelInfo()B
					invokespecial 328;		// javacard/framework/T0APDUImpl.setLogicalChannel(B)V
					aload_0;
					sconst_0;
					invokespecial 287;		// javacard/framework/T0APDUImpl.setLr(S)V
					return;
		}

		.method public markExtendedSupport(Z)V 20 {
			.stack 2;
			.locals 0;

				L0:	sload_1;
					ifne L6;
				L1:	aload_0;
					invokespecial 330;		// javacard/framework/T0APDUImpl.resetExtendedSupportFlag()V
					aload_0;
					invokespecial 297;		// javacard/framework/T0APDUImpl.getExtendedAPDUFlag()Z
					ifeq L3;
				L2:	sspush 26368;
					invokestatic 78;		// javacard/framework/ISOException.throwIt(S)V
				L3:	aload_0;
					invokespecial 282;		// javacard/framework/T0APDUImpl.getLe()S
					ifne L9;
				L4:	aload_0;
					invokespecial 268;		// javacard/framework/T0APDUImpl.getEnvelopeFlag()Z
					ifne L9;
				L5:	aload_0;
					sspush 256;
					invokespecial 293;		// javacard/framework/T0APDUImpl.setLe(S)V
					goto L9;
				L6:	aload_0;
					invokespecial 331;		// javacard/framework/T0APDUImpl.setExtendedSupportFlag()V
					aload_0;
					invokespecial 282;		// javacard/framework/T0APDUImpl.getLe()S
					sspush 256;
					if_scmpne L9;
				L7:	aload_0;
					invokespecial 268;		// javacard/framework/T0APDUImpl.getEnvelopeFlag()Z
					ifne L9;
				L8:	aload_0;
					sspush 32767;
					invokespecial 293;		// javacard/framework/T0APDUImpl.setLe(S)V
				L9:	return;
		}

		.method public complete(S)V 21 {
			.stack 4;
			.locals 3;

				L0:	getfield_a_this 23;		// reference javacard/framework/T0APDUImpl.buffer
					sconst_0;
					sspush 133;
					sconst_0;
					invokestatic 262;		// javacard/framework/Util.arrayFillNonAtomic([BSSB)S
					pop;
					aload_0;
					invokespecial 303;		// javacard/framework/T0APDUImpl.getNoGetResponseFlag()Z
					ifne L11;
				L1:	aload_0;
					invokespecial 307;		// javacard/framework/T0APDUImpl.getSendInProgressFlag()Z
					ifeq L11;
				L2:	aload_0;
					invokespecial 282;		// javacard/framework/T0APDUImpl.getLe()S
					s2b;
					sstore_3;
				L3:	sspush 128;
					sstore 4;
				L4:	sload_3;
					ifle L11;
				L5:	sload_3;
					sspush 128;
					if_scmpge L7;
				L6:	sload_3;
					sstore 4;
				L7:	getfield_a_this 23;		// reference javacard/framework/T0APDUImpl.buffer
					sconst_0;
					sload 4;
					sconst_0;
					invokestatic 308;		// com/sun/javacard/impl/NativeMethods.t0SndData([BSSB)S
					sstore_2;
				L8:	sload_2;
					ifeq L10;
				L9:	sconst_4;
					invokestatic 91;		// javacard/framework/APDUException.throwIt(S)V
				L10:	sload_3;
					sload 4;
					ssub;
					sstore_3;
					goto L4;
				L11:	getfield_a_this 23;		// reference javacard/framework/T0APDUImpl.buffer
					sconst_0;
					sload_1;
					bspush 8;
					sshr;
					s2b;
					bastore;
					getfield_a_this 23;		// reference javacard/framework/T0APDUImpl.buffer
					sconst_1;
					sload_1;
					s2b;
					bastore;
					sload_1;
					ifne L14;
				L12:	invokestatic 332;		// com/sun/javacard/impl/NativeMethods.t0RcvCommand()S
					sstore_2;
				L13:	goto L15;
				L14:	aload_0;
					invokespecial 279;		// javacard/framework/T0APDUImpl.getRemainingInbound()V
					sload_1;
					invokestatic 271;		// com/sun/javacard/impl/NativeMethods.t0SetStatus(S)S
					pop;
					invokestatic 272;		// com/sun/javacard/impl/NativeMethods.t0SndStatusRcvCommand()S
					sstore_2;
				L15:	sload_2;
					ifeq L17;
				L16:	sconst_4;
					invokestatic 91;		// javacard/framework/APDUException.throwIt(S)V
				L17:	aload_0;
					invokespecial 330;		// javacard/framework/T0APDUImpl.resetExtendedSupportFlag()V
					aload_0;
					invokevirtual 322;		// resetAPDU()V
					aload_0;
					invokespecial 323;		// javacard/framework/T0APDUImpl.preProcessAPDU()V
					aload_0;
					invokespecial 333;		// javacard/framework/T0APDUImpl.processEnvelopeAPDU()V
					return;
		}

		.method public undoIncomingAndReceive()V 22 {
			.stack 3;
			.locals 0;

				L0:	aload_0;
					getfield_a_this 23;		// reference javacard/framework/T0APDUImpl.buffer
					sconst_4;
					baload;
					aload_0;
					invokespecial 274;		// javacard/framework/T0APDUImpl.getLc()S
					ssub;
					sspush 32767;
					sand;
					invokespecial 294;		// javacard/framework/T0APDUImpl.setPreReadLength(S)V
					aload_0;
					sconst_0;
					invokespecial 281;		// javacard/framework/T0APDUImpl.setCurrState(B)V
					return;
		}

		.method public waitExtension()V 23 {
			.stack 1;
			.locals 1;

				L0:	getstatic_a 267;		// reference javacard/framework/T0APDUImpl.theAPDU
					invokeinterface 1 81 1;		// javacard/framework/APDUComm
					ifeq L2;
				L1:	sconst_1;
					invokestatic 91;		// javacard/framework/APDUException.throwIt(S)V
				L2:	invokestatic 334;		// com/sun/javacard/impl/NativeMethods.t0Wait()S
					sstore_1;
				L3:	sload_1;
					ifeq L5;
				L4:	sconst_4;
					invokestatic 91;		// javacard/framework/APDUException.throwIt(S)V
				L5:	return;
		}

		.method public isValidCLA()Z 24 {
			.stack 2;
			.locals 1;

				L0:	getfield_a_this 23;		// reference javacard/framework/T0APDUImpl.buffer
					sconst_0;
					baload;
					sstore_1;
				L1:	sload_1;
					sspush 224;
					sand;
					s2b;
					bspush 32;
					if_scmpeq L3;
				L2:	sload_1;
					sconst_m1;
					if_scmpne L4;
				L3:	sconst_0;
					goto L5;
				L4:	sconst_1;
				L5:	sreturn;
		}

		.method public isCommandChainingCLA()Z 25 {
			.stack 2;
			.locals 1;

				L0:	aload_0;
					invokevirtual 335;		// isValidCLA()Z
					ifne L2;
				L1:	sconst_0;
					sreturn;
				L2:	getfield_a_this 23;		// reference javacard/framework/T0APDUImpl.buffer
					sconst_0;
					baload;
					bspush 16;
					sand;
					sstore_1;
				L3:	sload_1;
					bspush 16;
					if_scmpne L5;
				L4:	sconst_1;
					sreturn;
				L5:	sconst_0;
					sreturn;
		}

		.method public isSecureMessagingCLA()Z 26 {
			.stack 2;
			.locals 1;

				L0:	aload_0;
					invokevirtual 335;		// isValidCLA()Z
					ifne L2;
				L1:	sconst_0;
					sreturn;
				L2:	aload_0;
					getfield_a_this 23;		// reference javacard/framework/T0APDUImpl.buffer
					invokespecial 263;		// javacard/framework/T0APDUImpl.isType16CLA([B)Z
					ifeq L5;
				L3:	getfield_a_this 23;		// reference javacard/framework/T0APDUImpl.buffer
					sconst_0;
					baload;
					bspush 32;
					sand;
					sstore_1;
				L4:	goto L6;
				L5:	getfield_a_this 23;		// reference javacard/framework/T0APDUImpl.buffer
					sconst_0;
					baload;
					bspush 12;
					sand;
					sstore_1;
				L6:	sload_1;
					ifne L8;
				L7:	sconst_0;
					sreturn;
				L8:	sconst_1;
					sreturn;
		}

		.method public isISOInterindustryCLA()Z 27 {
			.stack 2;
			.locals 0;

				L0:	aload_0;
					getfield_a_this 23;		// reference javacard/framework/T0APDUImpl.buffer
					invokespecial 320;		// javacard/framework/T0APDUImpl.isISOInterindustryCLA([B)Z
					sreturn;
		}

		.method private isISOInterindustryCLA([B)Z {
			.stack 2;
			.locals 1;

				L0:	aload_1;
					sconst_0;
					baload;
					bspush -128;
					sand;
					sstore_2;
				L1:	sload_2;
					ifne L3;
				L2:	sconst_1;
					sreturn;
				L3:	sconst_0;
					sreturn;
		}

		.method private isType16CLA([B)Z {
			.stack 2;
			.locals 1;

				L0:	aload_1;
					sconst_0;
					baload;
					bspush 64;
					sand;
					sstore_2;
				L1:	sload_2;
					bspush 64;
					if_scmpne L3;
				L2:	sconst_1;
					sreturn;
				L3:	sconst_0;
					sreturn;
		}

		.method public getIncomingLength()S 28 {
			.stack 1;
			.locals 0;

				L0:	aload_0;
					invokespecial 336;		// javacard/framework/T0APDUImpl.getIL()S
					sreturn;
		}

		.method public getOffsetCdata()S 29 {
			.stack 1;
			.locals 0;

				L0:	aload_0;
					invokespecial 297;		// javacard/framework/T0APDUImpl.getExtendedAPDUFlag()Z
					ifne L2;
				L1:	sconst_5;
					sreturn;
				L2:	bspush 7;
					sreturn;
		}

		.method public verifyLe()V 30 {
			.stack 0;
			.locals 0;

				L0:	return;
		}

	}

	.class  T1APDUImpl extends 0.0 {		// extends java/lang/Object

		.fields {
			private byte[] buffer 0;		// [B
			private 1.12 thePackedBoolean 1;		// Lcom/sun/javacard/impl/PackedBoolean;
			private byte incomingFlag 2;		// B
			private byte outgoingFlag 3;		// B
			private byte outgoingLenSetFlag 4;		// B
			private byte sendInProgressFlag 5;		// B
			private byte noChainingFlag 6;		// B
			private byte extendedAPDUFlag 7;		// B
			private byte determinedLE 8;		// B
			private byte type16Flag 9;		// B
			private byte extendedSupportFlag 10;		// B
			private static final short BUFFERSIZE = 133;		// S
			private static APDUComm theAPDU;		// Ljavacard/framework/APDUComm;
			private static byte[] ramByteVars;		// [B
			private static short[] ramShortVars;		// [S
			private static final byte LE = 0;		// B
			private static final byte LR = 1;		// B
			private static final byte LC = 2;		// B
			private static final byte LS = 3;		// B
			private static final byte LO = 4;		// B
			private static final byte PRE_READ_LENGTH = 5;		// B
			private static final byte INCOMIMG_LENGTH = 6;		// B
			private static final byte DATA_PROCESSED_LENGTH = 7;		// B
			private static final byte RAM_SHORT_VARS_LENGTH = 8;		// B
			private static final byte CURRENT_STATE = 0;		// B
			private static final byte LOGICAL_CHN = 1;		// B
			private static final byte RAM_BYTE_VARS_LENGTH = 2;		// B
			private static final short CASE_1 = 1;		// S
			private static final short CASE_2S = 2;		// S
			private static final short CASE_3S = 3;		// S
			private static final short CASE_4S = 4;		// S
			private static final short CASE_2E = 6;		// S
			private static final short CASE_3E = 7;		// S
			private static final short CASE_4E = 8;		// S
			private static final byte T1_EVENT_NONE = 0;		// B
			private static final byte T1_EVENT_POWERUP = 1;		// B
			private static final byte T1_EVENT_POWERDOWN = 2;		// B
			private static final byte T1_EVENT_POWERRESET = 3;		// B
			private static final byte T1_NAD_MASTER_TO_SE = 33;		// B
			private static final byte T1_NAD_SE_TO_MASTER = 18;		// B
			private static final short MAX_LE = 256;		// S
			private static final short MAX_EXT_LE = 32767;		// S
		}

		.publicMethodTable 1 31 {
			equals(Ljava/lang/Object;)Z 0;
			getLogicalChannel()B 255;
			getNoChainingFlag()Z 255;
			resetAPDU()V 255;
			complete(S)V 255;
			undoIncomingAndReceive()V 255;
			getCLAChannel()B 255;
			waitExtension()V 255;
			isValidCLA()Z 255;
			isCommandChainingCLA()Z 255;
			isSecureMessagingCLA()Z 255;
			isISOInterindustryCLA()Z 255;
			getBuffer()[B 255;
			getInBlockSize()S 255;
			getOutBlockSize()S 255;
			getProtocol()B 255;
			getNAD()B 255;
			setOutgoing()S 255;
			setOutgoingNoChaining()S 255;
			setOutgoingLength(S)V 255;
			receiveBytes(S)S 255;
			sendBytes(SS)V 255;
			sendBytesLong([BSS)V 255;
			setIncomingAndReceive()S 255;
			setOutgoingAndSend(SS)V 255;
			getCurrentState()B 255;
			getCurrentAPDUBuffer()[B 255;
			markExtendedSupport(Z)V 255;
			getIncomingLength()S 255;
			getOffsetCdata()S 255;
			verifyLe()V 255;
		}

		.packageMethodTable 0 {
		}

		.implementedInterfaceInfoTable { 
			.interface APDUComm { 
				1;		// getLogicalChannel()B
				2;		// getNoChainingFlag()Z
				3;		// resetAPDU()V
				4;		// complete(S)V
				5;		// undoIncomingAndReceive()V
				6;		// getCLAChannel()B
				7;		// waitExtension()V
				12;		// getBuffer()[B
				13;		// getInBlockSize()S
				14;		// getOutBlockSize()S
				15;		// getProtocol()B
				16;		// getNAD()B
				17;		// setOutgoing()S
				18;		// setOutgoingNoChaining()S
				19;		// setOutgoingLength(S)V
				20;		// receiveBytes(S)S
				23;		// setIncomingAndReceive()S
				21;		// sendBytes(SS)V
				22;		// sendBytesLong([BSS)V
				24;		// setOutgoingAndSend(SS)V
				25;		// getCurrentState()B
				26;		// getCurrentAPDUBuffer()[B
				27;		// markExtendedSupport(Z)V
				28;		// getIncomingLength()S
				29;		// getOffsetCdata()S
				8;		// isValidCLA()Z
				9;		// isCommandChainingCLA()Z
				10;		// isSecureMessagingCLA()Z
				11;		// isISOInterindustryCLA()Z
				30;		// verifyLe()V
			}

		}

		.method private getLe()S {
			.stack 2;
			.locals 0;

				L0:	getstatic_a 337;		// reference javacard/framework/T1APDUImpl.ramShortVars
					sconst_0;
					saload;
					ifne L5;
				L1:	aload_0;
					invokespecial 338;		// javacard/framework/T1APDUImpl.getDeterminedLEFlag()Z
					ifeq L5;
				L2:	aload_0;
					invokespecial 339;		// javacard/framework/T1APDUImpl.getExtendedAPDUFlag()Z
					ifeq L4;
				L3:	sspush 32767;
					sreturn;
				L4:	sspush 256;
					sreturn;
				L5:	getstatic_a 337;		// reference javacard/framework/T1APDUImpl.ramShortVars
					sconst_0;
					saload;
					sreturn;
		}

		.method private setLe(S)V {
			.stack 3;
			.locals 0;

				L0:	getstatic_a 337;		// reference javacard/framework/T1APDUImpl.ramShortVars
					sconst_0;
					sload_1;
					sastore;
					return;
		}

		.method private getIL()S {
			.stack 2;
			.locals 0;

				L0:	getstatic_a 337;		// reference javacard/framework/T1APDUImpl.ramShortVars
					bspush 6;
					saload;
					sreturn;
		}

		.method private setIL(S)V {
			.stack 3;
			.locals 0;

				L0:	getstatic_a 337;		// reference javacard/framework/T1APDUImpl.ramShortVars
					bspush 6;
					sload_1;
					sastore;
					return;
		}

		.method private getLr()S {
			.stack 2;
			.locals 0;

				L0:	getstatic_a 337;		// reference javacard/framework/T1APDUImpl.ramShortVars
					sconst_1;
					saload;
					sreturn;
		}

		.method private setLr(S)V {
			.stack 3;
			.locals 0;

				L0:	getstatic_a 337;		// reference javacard/framework/T1APDUImpl.ramShortVars
					sconst_1;
					sload_1;
					sastore;
					return;
		}

		.method private getLc()S {
			.stack 2;
			.locals 0;

				L0:	getstatic_a 337;		// reference javacard/framework/T1APDUImpl.ramShortVars
					sconst_2;
					saload;
					sreturn;
		}

		.method private setLc(S)V {
			.stack 3;
			.locals 0;

				L0:	getstatic_a 337;		// reference javacard/framework/T1APDUImpl.ramShortVars
					sconst_2;
					sload_1;
					sastore;
					return;
		}

		.method private getLs()S {
			.stack 2;
			.locals 0;

				L0:	getstatic_a 337;		// reference javacard/framework/T1APDUImpl.ramShortVars
					sconst_3;
					saload;
					sreturn;
		}

		.method private setLs(S)V {
			.stack 4;
			.locals 0;

				L0:	getstatic_a 337;		// reference javacard/framework/T1APDUImpl.ramShortVars
					sconst_3;
					sload_1;
					sspush 32767;
					sand;
					sastore;
					return;
		}

		.method private getLo()S {
			.stack 2;
			.locals 0;

				L0:	getstatic_a 337;		// reference javacard/framework/T1APDUImpl.ramShortVars
					sconst_4;
					saload;
					sreturn;
		}

		.method private setLo(S)V {
			.stack 3;
			.locals 0;

				L0:	getstatic_a 337;		// reference javacard/framework/T1APDUImpl.ramShortVars
					sconst_4;
					sload_1;
					sastore;
					return;
		}

		.method private getPreReadLength()S {
			.stack 2;
			.locals 0;

				L0:	getstatic_a 337;		// reference javacard/framework/T1APDUImpl.ramShortVars
					sconst_5;
					saload;
					sreturn;
		}

		.method private setPreReadLength(S)V {
			.stack 3;
			.locals 0;

				L0:	getstatic_a 337;		// reference javacard/framework/T1APDUImpl.ramShortVars
					sconst_5;
					sload_1;
					sastore;
					return;
		}

		.method private getCurrState()B {
			.stack 2;
			.locals 0;

				L0:	getstatic_a 340;		// reference javacard/framework/T1APDUImpl.ramByteVars
					sconst_0;
					baload;
					sreturn;
		}

		.method private setCurrState(B)V {
			.stack 3;
			.locals 0;

				L0:	getstatic_a 340;		// reference javacard/framework/T1APDUImpl.ramByteVars
					sconst_0;
					sload_1;
					bastore;
					return;
		}

		.method private resetCurrState()V {
			.stack 3;
			.locals 0;

				L0:	getstatic_a 340;		// reference javacard/framework/T1APDUImpl.ramByteVars
					sconst_0;
					sconst_0;
					bastore;
					return;
		}

		.method private setLogicalChannel(B)V {
			.stack 3;
			.locals 0;

				L0:	getstatic_a 340;		// reference javacard/framework/T1APDUImpl.ramByteVars
					sconst_1;
					sload_1;
					bastore;
					return;
		}

		.method private getIncomingFlag()Z {
			.stack 2;
			.locals 0;

				L0:	getfield_a_this 24;		// reference javacard/framework/T1APDUImpl.thePackedBoolean
					getfield_b_this 25;		// byte javacard/framework/T1APDUImpl.incomingFlag
					invokevirtual 250;		// get(B)Z
					sreturn;
		}

		.method private setIncomingFlag()V {
			.stack 2;
			.locals 0;

				L0:	getfield_a_this 24;		// reference javacard/framework/T1APDUImpl.thePackedBoolean
					getfield_b_this 25;		// byte javacard/framework/T1APDUImpl.incomingFlag
					invokevirtual 251;		// set(B)V
					return;
		}

		.method private resetIncomingFlag()V {
			.stack 2;
			.locals 0;

				L0:	getfield_a_this 24;		// reference javacard/framework/T1APDUImpl.thePackedBoolean
					getfield_b_this 25;		// byte javacard/framework/T1APDUImpl.incomingFlag
					invokevirtual 252;		// reset(B)V
					return;
		}

		.method private getDeterminedLEFlag()Z {
			.stack 2;
			.locals 0;

				L0:	getfield_a_this 24;		// reference javacard/framework/T1APDUImpl.thePackedBoolean
					getfield_b_this 26;		// byte javacard/framework/T1APDUImpl.determinedLE
					invokevirtual 250;		// get(B)Z
					sreturn;
		}

		.method private setDeterminedLEFlag()V {
			.stack 2;
			.locals 0;

				L0:	getfield_a_this 24;		// reference javacard/framework/T1APDUImpl.thePackedBoolean
					getfield_b_this 26;		// byte javacard/framework/T1APDUImpl.determinedLE
					invokevirtual 251;		// set(B)V
					return;
		}

		.method private resetDeterminedLEFlag()V {
			.stack 2;
			.locals 0;

				L0:	getfield_a_this 24;		// reference javacard/framework/T1APDUImpl.thePackedBoolean
					getfield_b_this 26;		// byte javacard/framework/T1APDUImpl.determinedLE
					invokevirtual 252;		// reset(B)V
					return;
		}

		.method private getSendInProgressFlag()Z {
			.stack 2;
			.locals 0;

				L0:	getfield_a_this 24;		// reference javacard/framework/T1APDUImpl.thePackedBoolean
					getfield_b_this 27;		// byte javacard/framework/T1APDUImpl.sendInProgressFlag
					invokevirtual 250;		// get(B)Z
					sreturn;
		}

		.method private setSendInProgressFlag()V {
			.stack 2;
			.locals 0;

				L0:	getfield_a_this 24;		// reference javacard/framework/T1APDUImpl.thePackedBoolean
					getfield_b_this 27;		// byte javacard/framework/T1APDUImpl.sendInProgressFlag
					invokevirtual 251;		// set(B)V
					return;
		}

		.method private resetSendInProgressFlag()V {
			.stack 2;
			.locals 0;

				L0:	getfield_a_this 24;		// reference javacard/framework/T1APDUImpl.thePackedBoolean
					getfield_b_this 27;		// byte javacard/framework/T1APDUImpl.sendInProgressFlag
					invokevirtual 252;		// reset(B)V
					return;
		}

		.method private getOutgoingFlag()Z {
			.stack 2;
			.locals 0;

				L0:	getfield_a_this 24;		// reference javacard/framework/T1APDUImpl.thePackedBoolean
					getfield_b_this 28;		// byte javacard/framework/T1APDUImpl.outgoingFlag
					invokevirtual 250;		// get(B)Z
					sreturn;
		}

		.method private setOutgoingFlag()V {
			.stack 2;
			.locals 0;

				L0:	getfield_a_this 24;		// reference javacard/framework/T1APDUImpl.thePackedBoolean
					getfield_b_this 28;		// byte javacard/framework/T1APDUImpl.outgoingFlag
					invokevirtual 251;		// set(B)V
					return;
		}

		.method private resetOutgoingFlag()V {
			.stack 2;
			.locals 0;

				L0:	getfield_a_this 24;		// reference javacard/framework/T1APDUImpl.thePackedBoolean
					getfield_b_this 28;		// byte javacard/framework/T1APDUImpl.outgoingFlag
					invokevirtual 252;		// reset(B)V
					return;
		}

		.method private getOutgoingLenSetFlag()Z {
			.stack 2;
			.locals 0;

				L0:	getfield_a_this 24;		// reference javacard/framework/T1APDUImpl.thePackedBoolean
					getfield_b_this 29;		// byte javacard/framework/T1APDUImpl.outgoingLenSetFlag
					invokevirtual 250;		// get(B)Z
					sreturn;
		}

		.method private setOutgoingLenSetFlag()V {
			.stack 2;
			.locals 0;

				L0:	getfield_a_this 24;		// reference javacard/framework/T1APDUImpl.thePackedBoolean
					getfield_b_this 29;		// byte javacard/framework/T1APDUImpl.outgoingLenSetFlag
					invokevirtual 251;		// set(B)V
					return;
		}

		.method private resetOutgoingLenSetFlag()V {
			.stack 2;
			.locals 0;

				L0:	getfield_a_this 24;		// reference javacard/framework/T1APDUImpl.thePackedBoolean
					getfield_b_this 29;		// byte javacard/framework/T1APDUImpl.outgoingLenSetFlag
					invokevirtual 252;		// reset(B)V
					return;
		}

		.method private getExtendedAPDUFlag()Z {
			.stack 2;
			.locals 0;

				L0:	getfield_a_this 24;		// reference javacard/framework/T1APDUImpl.thePackedBoolean
					getfield_b_this 30;		// byte javacard/framework/T1APDUImpl.extendedAPDUFlag
					invokevirtual 250;		// get(B)Z
					sreturn;
		}

		.method private setExtendedAPDUFlag()V {
			.stack 2;
			.locals 0;

				L0:	getfield_a_this 24;		// reference javacard/framework/T1APDUImpl.thePackedBoolean
					getfield_b_this 30;		// byte javacard/framework/T1APDUImpl.extendedAPDUFlag
					invokevirtual 251;		// set(B)V
					return;
		}

		.method private resetExtendedAPDUFlag()V {
			.stack 2;
			.locals 0;

				L0:	getfield_a_this 24;		// reference javacard/framework/T1APDUImpl.thePackedBoolean
					getfield_b_this 30;		// byte javacard/framework/T1APDUImpl.extendedAPDUFlag
					invokevirtual 252;		// reset(B)V
					return;
		}

		.method private getType16Flag()Z {
			.stack 2;
			.locals 0;

				L0:	getfield_a_this 24;		// reference javacard/framework/T1APDUImpl.thePackedBoolean
					getfield_b_this 31;		// byte javacard/framework/T1APDUImpl.type16Flag
					invokevirtual 250;		// get(B)Z
					sreturn;
		}

		.method private setType16Flag()V {
			.stack 2;
			.locals 0;

				L0:	getfield_a_this 24;		// reference javacard/framework/T1APDUImpl.thePackedBoolean
					getfield_b_this 31;		// byte javacard/framework/T1APDUImpl.type16Flag
					invokevirtual 251;		// set(B)V
					return;
		}

		.method private resetType16Flag()V {
			.stack 2;
			.locals 0;

				L0:	getfield_a_this 24;		// reference javacard/framework/T1APDUImpl.thePackedBoolean
					getfield_b_this 31;		// byte javacard/framework/T1APDUImpl.type16Flag
					invokevirtual 252;		// reset(B)V
					return;
		}

		.method private getExtendedSupportFlag()Z {
			.stack 2;
			.locals 0;

				L0:	getfield_a_this 24;		// reference javacard/framework/T1APDUImpl.thePackedBoolean
					getfield_b_this 32;		// byte javacard/framework/T1APDUImpl.extendedSupportFlag
					invokevirtual 250;		// get(B)Z
					sreturn;
		}

		.method private setExtendedSupportFlag()V {
			.stack 2;
			.locals 0;

				L0:	getfield_a_this 24;		// reference javacard/framework/T1APDUImpl.thePackedBoolean
					getfield_b_this 32;		// byte javacard/framework/T1APDUImpl.extendedSupportFlag
					invokevirtual 251;		// set(B)V
					return;
		}

		.method private resetExtendedSupportFlag()V {
			.stack 2;
			.locals 0;

				L0:	getfield_a_this 24;		// reference javacard/framework/T1APDUImpl.thePackedBoolean
					getfield_b_this 32;		// byte javacard/framework/T1APDUImpl.extendedSupportFlag
					invokevirtual 252;		// reset(B)V
					return;
		}

		.method  <init>()V {
			.stack 2;
			.locals 0;

				L0:	aload_0;
					invokespecial 254;		// java/lang/Object.<init>()V
					aload_0;
					invokestatic 264;		// com/sun/javacard/impl/NativeMethods.initAPDUBuffer()[B
					putfield_a 33;		// reference javacard/framework/T1APDUImpl.buffer
					sconst_2;
					sconst_1;
					invokestatic 57;		// javacard/framework/JCSystem.makeTransientByteArray(SB)[B
					putstatic_a 340;		// reference javacard/framework/T1APDUImpl.ramByteVars
					bspush 8;
					sconst_1;
					invokestatic 178;		// javacard/framework/JCSystem.makeTransientShortArray(SB)[S
					putstatic_a 337;		// reference javacard/framework/T1APDUImpl.ramShortVars
					aload_0;
					invokestatic 200;		// com/sun/javacard/impl/PrivAccess.getPackedBoolean()Lcom/sun/javacard/impl/PackedBoolean;
					putfield_a 24;		// reference javacard/framework/T1APDUImpl.thePackedBoolean
					aload_0;
					getfield_a_this 24;		// reference javacard/framework/T1APDUImpl.thePackedBoolean
					invokevirtual 201;		// allocate()B
					putfield_b 25;		// byte javacard/framework/T1APDUImpl.incomingFlag
					aload_0;
					getfield_a_this 24;		// reference javacard/framework/T1APDUImpl.thePackedBoolean
					invokevirtual 201;		// allocate()B
					putfield_b 27;		// byte javacard/framework/T1APDUImpl.sendInProgressFlag
					aload_0;
					getfield_a_this 24;		// reference javacard/framework/T1APDUImpl.thePackedBoolean
					invokevirtual 201;		// allocate()B
					putfield_b 28;		// byte javacard/framework/T1APDUImpl.outgoingFlag
					aload_0;
					getfield_a_this 24;		// reference javacard/framework/T1APDUImpl.thePackedBoolean
					invokevirtual 201;		// allocate()B
					putfield_b 29;		// byte javacard/framework/T1APDUImpl.outgoingLenSetFlag
					aload_0;
					getfield_a_this 24;		// reference javacard/framework/T1APDUImpl.thePackedBoolean
					invokevirtual 201;		// allocate()B
					putfield_b 30;		// byte javacard/framework/T1APDUImpl.extendedAPDUFlag
					aload_0;
					getfield_a_this 24;		// reference javacard/framework/T1APDUImpl.thePackedBoolean
					invokevirtual 201;		// allocate()B
					putfield_b 34;		// byte javacard/framework/T1APDUImpl.noChainingFlag
					aload_0;
					getfield_a_this 24;		// reference javacard/framework/T1APDUImpl.thePackedBoolean
					invokevirtual 201;		// allocate()B
					putfield_b 26;		// byte javacard/framework/T1APDUImpl.determinedLE
					aload_0;
					getfield_a_this 24;		// reference javacard/framework/T1APDUImpl.thePackedBoolean
					invokevirtual 201;		// allocate()B
					putfield_b 31;		// byte javacard/framework/T1APDUImpl.type16Flag
					aload_0;
					getfield_a_this 24;		// reference javacard/framework/T1APDUImpl.thePackedBoolean
					invokevirtual 201;		// allocate()B
					putfield_b 32;		// byte javacard/framework/T1APDUImpl.extendedSupportFlag
					aload_0;
					putstatic_a 352;		// reference javacard/framework/T1APDUImpl.theAPDU
					return;
		}

		.method private getChannelInfo()B {
			.stack 2;
			.locals 1;

				L0:	getfield_a_this 33;		// reference javacard/framework/T1APDUImpl.buffer
					sconst_0;
					baload;
					sspush 255;
					sand;
					sspush 255;
					if_scmpne L3;
				L1:	sconst_0;
					sstore_1;
				L2:	goto L10;
				L3:	aload_0;
					invokespecial 353;		// javacard/framework/T1APDUImpl.isType16CLA()Z
					ifeq L6;
				L4:	getfield_a_this 33;		// reference javacard/framework/T1APDUImpl.buffer
					sconst_0;
					baload;
					bspush 15;
					sand;
					sstore_1;
				L5:	sload_1;
					sconst_4;
					sadd;
					s2b;
					sstore_1;
					goto L10;
				L6:	getfield_a_this 33;		// reference javacard/framework/T1APDUImpl.buffer
					sconst_0;
					baload;
					bspush 32;
					sand;
					ifeq L9;
				L7:	sconst_0;
					sstore_1;
				L8:	goto L10;
				L9:	getfield_a_this 33;		// reference javacard/framework/T1APDUImpl.buffer
					sconst_0;
					baload;
					sconst_3;
					sand;
					sstore_1;
				L10:	sload_1;
					sreturn;
		}

		.method public getLogicalChannel()B 1 {
			.stack 2;
			.locals 0;

				L0:	getstatic_a 340;		// reference javacard/framework/T1APDUImpl.ramByteVars
					sconst_1;
					baload;
					sreturn;
		}

		.method public getNoChainingFlag()Z 2 {
			.stack 2;
			.locals 0;

				L0:	getfield_a_this 24;		// reference javacard/framework/T1APDUImpl.thePackedBoolean
					getfield_b_this 34;		// byte javacard/framework/T1APDUImpl.noChainingFlag
					invokevirtual 250;		// get(B)Z
					sreturn;
		}

		.method private setNoChainingFlag()V {
			.stack 2;
			.locals 0;

				L0:	getfield_a_this 24;		// reference javacard/framework/T1APDUImpl.thePackedBoolean
					getfield_b_this 34;		// byte javacard/framework/T1APDUImpl.noChainingFlag
					invokevirtual 251;		// set(B)V
					return;
		}

		.method private resetNoChainingFlag()V {
			.stack 2;
			.locals 0;

				L0:	getfield_a_this 24;		// reference javacard/framework/T1APDUImpl.thePackedBoolean
					getfield_b_this 34;		// byte javacard/framework/T1APDUImpl.noChainingFlag
					invokevirtual 252;		// reset(B)V
					return;
		}

		.method public resetAPDU()V 3 {
			.stack 3;
			.locals 0;

				L0:	aload_0;
					invokespecial 354;		// javacard/framework/T1APDUImpl.resetIncomingFlag()V
					aload_0;
					invokespecial 355;		// javacard/framework/T1APDUImpl.resetOutgoingFlag()V
					aload_0;
					invokespecial 356;		// javacard/framework/T1APDUImpl.resetOutgoingLenSetFlag()V
					aload_0;
					invokespecial 357;		// javacard/framework/T1APDUImpl.resetSendInProgressFlag()V
					aload_0;
					invokespecial 358;		// javacard/framework/T1APDUImpl.resetType16Flag()V
					aload_0;
					invokespecial 359;		// javacard/framework/T1APDUImpl.resetExtendedAPDUFlag()V
					aload_0;
					invokespecial 360;		// javacard/framework/T1APDUImpl.resetDeterminedLEFlag()V
					aload_0;
					invokespecial 361;		// javacard/framework/T1APDUImpl.resetNoChainingFlag()V
					aload_0;
					sconst_0;
					invokespecial 362;		// javacard/framework/T1APDUImpl.setPreReadLength(S)V
					getstatic_a 337;		// reference javacard/framework/T1APDUImpl.ramShortVars
					bspush 7;
					sconst_0;
					sastore;
					return;
		}

		.method private setAPDUParameters(SSSSS)V {
			.stack 2;
			.locals 0;

				L0:	aload_0;
					sload_2;
					invokespecial 363;		// javacard/framework/T1APDUImpl.setLe(S)V
					aload_0;
					sload_1;
					invokespecial 364;		// javacard/framework/T1APDUImpl.setLc(S)V
					aload_0;
					sload_3;
					invokespecial 365;		// javacard/framework/T1APDUImpl.setLr(S)V
					aload_0;
					sload 5;
					invokespecial 366;		// javacard/framework/T1APDUImpl.setIL(S)V
					aload_0;
					invokespecial 367;		// javacard/framework/T1APDUImpl.resetCurrState()V
					aload_0;
					sload 4;
					invokespecial 362;		// javacard/framework/T1APDUImpl.setPreReadLength(S)V
					aload_0;
					invokespecial 353;		// javacard/framework/T1APDUImpl.isType16CLA()Z
					ifeq L2;
				L1:	aload_0;
					invokespecial 368;		// javacard/framework/T1APDUImpl.setType16Flag()V
				L2:	aload_0;
					aload_0;
					invokespecial 369;		// javacard/framework/T1APDUImpl.getChannelInfo()B
					invokespecial 370;		// javacard/framework/T1APDUImpl.setLogicalChannel(B)V
					return;
		}

		.method private preProcessAPDU(S)V {
			.stack 7;
			.locals 6;

				L0:	sload_1;
					sconst_4;
					if_scmpne L2;
				L1:	aload_0;
					sconst_0;
					sconst_0;
					sconst_0;
					sconst_0;
					sconst_0;
					invokespecial 371;		// javacard/framework/T1APDUImpl.setAPDUParameters(SSSSS)V
					aload_0;
					invokespecial 372;		// javacard/framework/T1APDUImpl.setDeterminedLEFlag()V
					return;
				L2:	sload_1;
					sconst_5;
					if_scmpne L5;
				L3:	getfield_a_this 33;		// reference javacard/framework/T1APDUImpl.buffer
					sconst_4;
					baload;
					sspush 255;
					sand;
					sstore_3;
				L4:	aload_0;
					sconst_0;
					sload_3;
					sconst_0;
					sconst_0;
					sconst_0;
					invokespecial 371;		// javacard/framework/T1APDUImpl.setAPDUParameters(SSSSS)V
					aload_0;
					invokespecial 372;		// javacard/framework/T1APDUImpl.setDeterminedLEFlag()V
					return;
				L5:	sload_1;
					bspush 7;
					if_scmpne L15;
				L6:	getfield_a_this 33;		// reference javacard/framework/T1APDUImpl.buffer
					sconst_4;
					baload;
					sstore 7;
				L7:	sload 7;
					ifne L10;
				L8:	getfield_a_this 33;		// reference javacard/framework/T1APDUImpl.buffer
					sconst_5;
					baload;
					sspush 255;
					sand;
					sstore_3;
				L9:	sload_3;
					bspush 8;
					sshl;
					getfield_a_this 33;		// reference javacard/framework/T1APDUImpl.buffer
					bspush 6;
					baload;
					sspush 255;
					sand;
					sor;
					sstore_3;
					aload_0;
					sconst_0;
					sload_3;
					sconst_0;
					sconst_0;
					sconst_0;
					invokespecial 371;		// javacard/framework/T1APDUImpl.setAPDUParameters(SSSSS)V
					aload_0;
					invokespecial 372;		// javacard/framework/T1APDUImpl.setDeterminedLEFlag()V
					aload_0;
					invokespecial 373;		// javacard/framework/T1APDUImpl.setExtendedAPDUFlag()V
					return;
				L10:	sload 7;
					sspush 255;
					sand;
					sstore 4;
				L11:	sload 7;
					sconst_2;
					if_scmpeq L14;
				L12:	getfield_a_this 33;		// reference javacard/framework/T1APDUImpl.buffer
					bspush 6;
					baload;
					sspush 255;
					sand;
					sstore_3;
				L13:	sinc 4 -1;
					aload_0;
					sload 4;
					sload_3;
					sconst_0;
					sconst_1;
					sconst_1;
					invokespecial 371;		// javacard/framework/T1APDUImpl.setAPDUParameters(SSSSS)V
					aload_0;
					invokespecial 372;		// javacard/framework/T1APDUImpl.setDeterminedLEFlag()V
					return;
				L14:	sinc 4 -2;
					aload_0;
					sload 4;
					sconst_0;
					sconst_0;
					sconst_2;
					sconst_2;
					invokespecial 371;		// javacard/framework/T1APDUImpl.setAPDUParameters(SSSSS)V
					aload_0;
					invokespecial 372;		// javacard/framework/T1APDUImpl.setDeterminedLEFlag()V
					return;
				L15:	sload_1;
					sconst_5;
					if_scmple_w L38;
				L16:	getfield_a_this 33;		// reference javacard/framework/T1APDUImpl.buffer
					sconst_4;
					baload;
					sstore 7;
				L17:	sload 7;
					ifne L27;
				L18:	getfield_a_this 33;		// reference javacard/framework/T1APDUImpl.buffer
					sconst_5;
					baload;
					sspush 255;
					sand;
					sstore 4;
				L19:	sload 4;
					bspush 8;
					sshl;
					getfield_a_this 33;		// reference javacard/framework/T1APDUImpl.buffer
					bspush 6;
					baload;
					sspush 255;
					sand;
					sor;
					sstore 4;
					sload_1;
					sload 4;
					bspush 9;
					sadd;
					if_scmpne L23;
				L20:	sload_1;
					bspush 9;
					ssub;
					sstore 6;
				L21:	getfield_a_this 33;		// reference javacard/framework/T1APDUImpl.buffer
					bspush 7;
					sload 6;
					sadd;
					baload;
					sspush 255;
					sand;
					sstore_3;
				L22:	sload_3;
					bspush 8;
					sshl;
					getfield_a_this 33;		// reference javacard/framework/T1APDUImpl.buffer
					bspush 7;
					sload 6;
					sadd;
					sconst_1;
					sadd;
					baload;
					sspush 255;
					sand;
					sor;
					sstore_3;
					bspush -2;
					sstore 4;
					goto L26;
				L23:	sload_1;
					bspush 7;
					ssub;
					sstore 6;
				L24:	sconst_0;
					sstore_3;
				L25:	sload 4;
					sload 6;
					ssub;
					sstore 4;
				L26:	aload_0;
					sload 4;
					sload_3;
					sconst_0;
					sload 6;
					sload 4;
					sload 6;
					sadd;
					invokespecial 371;		// javacard/framework/T1APDUImpl.setAPDUParameters(SSSSS)V
					aload_0;
					invokespecial 373;		// javacard/framework/T1APDUImpl.setExtendedAPDUFlag()V
					aload_0;
					invokespecial 360;		// javacard/framework/T1APDUImpl.resetDeterminedLEFlag()V
					return;
				L27:	sload 7;
					sspush 255;
					sand;
					sstore 4;
				L28:	sload 4;
					sspush 128;
					if_scmple L31;
				L29:	sload_1;
					sconst_5;
					ssub;
					sstore 6;
				L30:	sload 4;
					sload 6;
					ssub;
					sstore 4;
					aload_0;
					sload 4;
					sconst_0;
					sconst_0;
					sload 6;
					sload 4;
					sload 6;
					sadd;
					invokespecial 371;		// javacard/framework/T1APDUImpl.setAPDUParameters(SSSSS)V
					aload_0;
					invokespecial 360;		// javacard/framework/T1APDUImpl.resetDeterminedLEFlag()V
					return;
				L31:	sload 4;
					sload_1;
					sconst_5;
					ssub;
					if_scmpge L35;
				L32:	getfield_a_this 33;		// reference javacard/framework/T1APDUImpl.buffer
					sload_1;
					sconst_1;
					ssub;
					baload;
					sspush 255;
					sand;
					sstore_3;
				L33:	sload_1;
					bspush 6;
					ssub;
					sstore 6;
				L34:	sload 4;
					sload 6;
					ssub;
					sstore 4;
					aload_0;
					sload 4;
					sload_3;
					sconst_0;
					sload 6;
					sload 4;
					sload 6;
					sadd;
					invokespecial 371;		// javacard/framework/T1APDUImpl.setAPDUParameters(SSSSS)V
					aload_0;
					invokespecial 372;		// javacard/framework/T1APDUImpl.setDeterminedLEFlag()V
					return;
				L35:	sconst_0;
					sstore_3;
				L36:	sload_1;
					sconst_5;
					ssub;
					sstore 6;
				L37:	sload 4;
					sload 6;
					ssub;
					sstore 4;
					aload_0;
					sload 4;
					sload_3;
					sconst_0;
					sload 6;
					sload 4;
					sload 6;
					sadd;
					invokespecial 371;		// javacard/framework/T1APDUImpl.setAPDUParameters(SSSSS)V
					aload_0;
					invokespecial 360;		// javacard/framework/T1APDUImpl.resetDeterminedLEFlag()V
					return;
				L38:	return;
		}

		.method public complete(S)V 4 {
			.stack 4;
			.locals 5;

				L0:	sconst_0;
					sstore_2;
				L1:	sload_1;
					ifeq_w L20;
				L2:	aload_0;
					invokespecial 374;		// javacard/framework/T1APDUImpl.getOutgoingFlag()Z
					ifne L6;
				L3:	invokestatic 375;		// com/sun/javacard/impl/NativeMethods.t1LastBlockReceived()Z
					ifne L6;
				L4:	invokestatic 376;		// com/sun/javacard/impl/NativeMethods.t1Abort()S
					sstore_2;
					sload_2;
					ifge L6;
				L5:	sspush 28416;
					sstore_1;
				L6:	aload_0;
					invokespecial 377;		// javacard/framework/T1APDUImpl.getSendInProgressFlag()Z
					ifeq L15;
				L7:	aload_0;
					invokespecial 378;		// javacard/framework/T1APDUImpl.getLs()S
					sstore_3;
				L8:	aload_0;
					invokespecial 379;		// javacard/framework/T1APDUImpl.getLo()S
					sstore 4;
				L9:	sload_3;
					sload 4;
					sadd;
					sconst_1;
					sadd;
					sspush 133;
					if_scmplt L11;
				L10:	sload 4;
					sload_3;
					sconst_0;
					sconst_0;
					invokestatic 380;		// com/sun/javacard/impl/NativeMethods.t1SndBlockRcvAck(SSZZ)S
					sstore_2;
					sconst_0;
					sstore_3;
					sconst_0;
					sstore 4;
				L11:	sload_1;
					bspush 8;
					sshr;
					s2b;
					sspush 255;
					sand;
					s2b;
					sstore 5;
				L12:	sload_1;
					sspush 255;
					sand;
					s2b;
					sstore 6;
				L13:	getfield_a_this 33;		// reference javacard/framework/T1APDUImpl.buffer
					sload_3;
					sload 4;
					sadd;
					sload 5;
					bastore;
					getfield_a_this 33;		// reference javacard/framework/T1APDUImpl.buffer
					sload_3;
					sload 4;
					sadd;
					sconst_1;
					sadd;
					sload 6;
					bastore;
					sload 4;
					sload_3;
					sconst_2;
					sadd;
					sconst_1;
					sconst_1;
					invokestatic 380;		// com/sun/javacard/impl/NativeMethods.t1SndBlockRcvAck(SSZZ)S
					sstore_2;
				L14:	goto L18;
				L15:	sload_1;
					bspush 8;
					sshr;
					s2b;
					sspush 255;
					sand;
					s2b;
					sstore_3;
				L16:	sload_1;
					sspush 255;
					sand;
					s2b;
					sstore 4;
				L17:	getfield_a_this 33;		// reference javacard/framework/T1APDUImpl.buffer
					sconst_0;
					sload_3;
					bastore;
					getfield_a_this 33;		// reference javacard/framework/T1APDUImpl.buffer
					sconst_1;
					sload 4;
					bastore;
					sconst_0;
					sconst_2;
					sconst_1;
					sconst_1;
					invokestatic 380;		// com/sun/javacard/impl/NativeMethods.t1SndBlockRcvAck(SSZZ)S
					sstore_2;
				L18:	sload_2;
					ifeq L20;
				L19:	sconst_4;
					invokestatic 91;		// javacard/framework/APDUException.throwIt(S)V
				L20:	getfield_a_this 33;		// reference javacard/framework/T1APDUImpl.buffer
					sconst_0;
					sspush 133;
					sconst_0;
					invokestatic 262;		// javacard/framework/Util.arrayFillNonAtomic([BSSB)S
					pop;
					invokestatic 381;		// com/sun/javacard/impl/NativeMethods.getSecondaryInterfaceEvent()B
					sstore_3;
				L21:	sload_3;
					sconst_1;
					if_scmpne L23;
				L22:	invokestatic 382;		// com/sun/javacard/impl/PrivAccess.powerUpContactless()V
					goto L27;
				L23:	sload_3;
					sconst_2;
					if_scmpne L25;
				L24:	invokestatic 383;		// com/sun/javacard/impl/PrivAccess.powerDownContactless()V
					goto L27;
				L25:	sload_3;
					sconst_3;
					if_scmpne L27;
				L26:	invokestatic 383;		// com/sun/javacard/impl/PrivAccess.powerDownContactless()V
					invokestatic 382;		// com/sun/javacard/impl/PrivAccess.powerUpContactless()V
				L27:	sconst_0;
					sstore 4;
				L28:	sconst_0;
					sstore 5;
				L29:	sload 4;
					sspush 133;
					if_scmpge L34;
				L30:	invokestatic 375;		// com/sun/javacard/impl/NativeMethods.t1LastBlockReceived()Z
					ifne L34;
				L31:	sload 4;
					sspush 133;
					invokestatic 384;		// com/sun/javacard/impl/NativeMethods.t1RcvBlock(SS)S
					sstore_2;
					sload_2;
					ifge L33;
				L32:	sconst_4;
					invokestatic 91;		// javacard/framework/APDUException.throwIt(S)V
				L33:	sload 4;
					sload_2;
					sadd;
					sstore 4;
					sload 5;
					sload_2;
					sadd;
					sstore 5;
					goto L29;
				L34:	aload_0;
					invokespecial 385;		// javacard/framework/T1APDUImpl.resetExtendedSupportFlag()V
					aload_0;
					invokevirtual 386;		// resetAPDU()V
					aload_0;
					sload 5;
					invokespecial 387;		// javacard/framework/T1APDUImpl.preProcessAPDU(S)V
					return;
		}

		.method public undoIncomingAndReceive()V 5 {
			.stack 3;
			.locals 0;

				L0:	aload_0;
					getfield_a_this 33;		// reference javacard/framework/T1APDUImpl.buffer
					sconst_4;
					baload;
					aload_0;
					invokespecial 388;		// javacard/framework/T1APDUImpl.getLc()S
					ssub;
					sspush 32767;
					sand;
					invokespecial 362;		// javacard/framework/T1APDUImpl.setPreReadLength(S)V
					aload_0;
					sconst_0;
					invokespecial 389;		// javacard/framework/T1APDUImpl.setCurrState(B)V
					return;
		}

		.method public getCLAChannel()B 6 {
			.stack 1;
			.locals 0;

				L0:	getstatic_a 352;		// reference javacard/framework/T1APDUImpl.theAPDU
					invokeinterface 1 81 0;		// javacard/framework/APDUComm
					sreturn;
		}

		.method public waitExtension()V 7 {
			.stack 1;
			.locals 1;

				L0:	getstatic_a 352;		// reference javacard/framework/T1APDUImpl.theAPDU
					invokeinterface 1 81 1;		// javacard/framework/APDUComm
					ifeq L2;
				L1:	sconst_1;
					invokestatic 91;		// javacard/framework/APDUException.throwIt(S)V
				L2:	invokestatic 390;		// com/sun/javacard/impl/NativeMethods.t1Wait()S
					sstore_1;
				L3:	sload_1;
					ifeq L5;
				L4:	sconst_4;
					invokestatic 91;		// javacard/framework/APDUException.throwIt(S)V
				L5:	return;
		}

		.method private isExtended()Z {
			.stack 1;
			.locals 0;

				L0:	aload_0;
					invokespecial 391;		// javacard/framework/T1APDUImpl.getExtendedSupportFlag()Z
					sreturn;
		}

		.method public isValidCLA()Z 8 {
			.stack 2;
			.locals 1;

				L0:	getfield_a_this 33;		// reference javacard/framework/T1APDUImpl.buffer
					sconst_0;
					baload;
					sstore_1;
				L1:	sload_1;
					sspush 224;
					sand;
					s2b;
					bspush 32;
					if_scmpeq L3;
				L2:	sload_1;
					sconst_m1;
					if_scmpne L4;
				L3:	sconst_0;
					goto L5;
				L4:	sconst_1;
				L5:	sreturn;
		}

		.method public isCommandChainingCLA()Z 9 {
			.stack 2;
			.locals 1;

				L0:	aload_0;
					invokevirtual 392;		// isValidCLA()Z
					ifne L2;
				L1:	sconst_0;
					sreturn;
				L2:	getfield_a_this 33;		// reference javacard/framework/T1APDUImpl.buffer
					sconst_0;
					baload;
					bspush 16;
					sand;
					sstore_1;
				L3:	sload_1;
					bspush 16;
					if_scmpne L5;
				L4:	sconst_1;
					sreturn;
				L5:	sconst_0;
					sreturn;
		}

		.method public isSecureMessagingCLA()Z 10 {
			.stack 2;
			.locals 1;

				L0:	aload_0;
					invokevirtual 392;		// isValidCLA()Z
					ifne L2;
				L1:	sconst_0;
					sreturn;
				L2:	aload_0;
					invokespecial 353;		// javacard/framework/T1APDUImpl.isType16CLA()Z
					ifeq L5;
				L3:	getfield_a_this 33;		// reference javacard/framework/T1APDUImpl.buffer
					sconst_0;
					baload;
					bspush 32;
					sand;
					sstore_1;
				L4:	goto L6;
				L5:	getfield_a_this 33;		// reference javacard/framework/T1APDUImpl.buffer
					sconst_0;
					baload;
					bspush 12;
					sand;
					sstore_1;
				L6:	sload_1;
					ifne L8;
				L7:	sconst_0;
					sreturn;
				L8:	sconst_1;
					sreturn;
		}

		.method public isISOInterindustryCLA()Z 11 {
			.stack 2;
			.locals 1;

				L0:	getfield_a_this 33;		// reference javacard/framework/T1APDUImpl.buffer
					sconst_0;
					baload;
					bspush -128;
					sand;
					sstore_1;
				L1:	sload_1;
					ifne L3;
				L2:	sconst_1;
					sreturn;
				L3:	sconst_0;
					sreturn;
		}

		.method private isType16CLA()Z {
			.stack 2;
			.locals 1;

				L0:	getfield_a_this 33;		// reference javacard/framework/T1APDUImpl.buffer
					sconst_0;
					baload;
					bspush 64;
					sand;
					sstore_1;
				L1:	sload_1;
					bspush 64;
					if_scmpne L3;
				L2:	sconst_1;
					sreturn;
				L3:	sconst_0;
					sreturn;
		}

		.method public getBuffer()[B 12 {
			.stack 1;
			.locals 0;

				L0:	getfield_a_this 33;		// reference javacard/framework/T1APDUImpl.buffer
					areturn;
		}

		.method public getInBlockSize()S 13 {
			.stack 1;
			.locals 0;

				L0:	invokestatic 393;		// com/sun/javacard/impl/NativeMethods.t1GetIFSC()S
					sreturn;
		}

		.method public getOutBlockSize()S 14 {
			.stack 1;
			.locals 0;

				L0:	invokestatic 394;		// com/sun/javacard/impl/NativeMethods.t1GetIFSD()S
					sreturn;
		}

		.method public getProtocol()B 15 {
			.stack 2;
			.locals 0;

				L0:	invokestatic 82;		// com/sun/javacard/impl/NativeMethods.getActiveInterface()B
					invokestatic 83;		// com/sun/javacard/impl/NativeMethods.getCommProtocol(B)B
					sconst_1;
					if_scmpne L2;
				L1:	sconst_1;
					sreturn;
				L2:	invokestatic 82;		// com/sun/javacard/impl/NativeMethods.getActiveInterface()B
					invokestatic 83;		// com/sun/javacard/impl/NativeMethods.getCommProtocol(B)B
					bspush -111;
					if_scmpne L4;
				L3:	bspush -127;
					sreturn;
				L4:	sconst_m1;
					sreturn;
		}

		.method public getNAD()B 16 {
			.stack 1;
			.locals 0;

				L0:	invokestatic 395;		// com/sun/javacard/impl/NativeMethods.t1GetNAD()B
					sreturn;
		}

		.method private receiveBytesAndDiscard()V {
			.stack 4;
			.locals 2;

				L0:	aload_0;
					invokespecial 396;		// javacard/framework/T1APDUImpl.getIncomingFlag()Z
					ifne L2;
				L1:	aload_0;
					invokespecial 397;		// javacard/framework/T1APDUImpl.setIncomingFlag()V
				L2:	aload_0;
					invokespecial 398;		// javacard/framework/T1APDUImpl.getPreReadLength()S
					sstore_1;
				L3:	sload_1;
					ifeq L5;
				L4:	aload_0;
					sconst_0;
					invokespecial 362;		// javacard/framework/T1APDUImpl.setPreReadLength(S)V
					getstatic_a 337;		// reference javacard/framework/T1APDUImpl.ramShortVars
					bspush 7;
					dup2;
					saload;
					sload_1;
					sadd;
					sastore;
				L5:	aload_0;
					invokespecial 399;		// javacard/framework/T1APDUImpl.getIL()S
					getstatic_a 337;		// reference javacard/framework/T1APDUImpl.ramShortVars
					bspush 7;
					saload;
					invokestatic 400;		// com/sun/javacard/impl/NativeMethods.t1RcvAndDiscardData(SS)S
					sstore_2;
				L6:	sload_2;
					bspush -2;
					if_scmpne L8;
				L7:	sspush 26368;
					invokestatic 78;		// javacard/framework/ISOException.throwIt(S)V
					goto L10;
				L8:	sload_2;
					iflt L10;
				L9:	aload_0;
					sload_2;
					invokespecial 363;		// javacard/framework/T1APDUImpl.setLe(S)V
					aload_0;
					invokespecial 372;		// javacard/framework/T1APDUImpl.setDeterminedLEFlag()V
				L10:	return;
		}

		.method public setOutgoing()S 17 {
			.stack 2;
			.locals 0;

				L0:	aload_0;
					invokespecial 374;		// javacard/framework/T1APDUImpl.getOutgoingFlag()Z
					ifeq L2;
				L1:	sconst_1;
					invokestatic 91;		// javacard/framework/APDUException.throwIt(S)V
				L2:	invokestatic 375;		// com/sun/javacard/impl/NativeMethods.t1LastBlockReceived()Z
					ifne L4;
				L3:	aload_0;
					invokespecial 401;		// javacard/framework/T1APDUImpl.receiveBytesAndDiscard()V
				L4:	aload_0;
					invokespecial 402;		// javacard/framework/T1APDUImpl.setOutgoingFlag()V
					aload_0;
					sconst_3;
					invokespecial 389;		// javacard/framework/T1APDUImpl.setCurrState(B)V
					aload_0;
					invokespecial 403;		// javacard/framework/T1APDUImpl.getLe()S
					ifge L6;
				L5:	sspush 26368;
					invokestatic 78;		// javacard/framework/ISOException.throwIt(S)V
				L6:	aload_0;
					invokespecial 403;		// javacard/framework/T1APDUImpl.getLe()S
					sreturn;
		}

		.method public setOutgoingNoChaining()S 18 {
			.stack 2;
			.locals 1;

				L0:	aload_0;
					invokespecial 374;		// javacard/framework/T1APDUImpl.getOutgoingFlag()Z
					ifeq L2;
				L1:	sconst_1;
					invokestatic 91;		// javacard/framework/APDUException.throwIt(S)V
				L2:	invokestatic 375;		// com/sun/javacard/impl/NativeMethods.t1LastBlockReceived()Z
					ifne L6;
				L3:	invokestatic 376;		// com/sun/javacard/impl/NativeMethods.t1Abort()S
					sstore_1;
				L4:	sload_1;
					ifge L6;
				L5:	sconst_4;
					invokestatic 91;		// javacard/framework/APDUException.throwIt(S)V
				L6:	aload_0;
					invokespecial 402;		// javacard/framework/T1APDUImpl.setOutgoingFlag()V
					aload_0;
					invokespecial 404;		// javacard/framework/T1APDUImpl.setNoChainingFlag()V
					aload_0;
					sconst_3;
					invokespecial 389;		// javacard/framework/T1APDUImpl.setCurrState(B)V
					aload_0;
					invokespecial 403;		// javacard/framework/T1APDUImpl.getLe()S
					sreturn;
		}

		.method public setOutgoingLength(S)V 19 {
			.stack 3;
			.locals 0;

				L0:	aload_0;
					invokespecial 374;		// javacard/framework/T1APDUImpl.getOutgoingFlag()Z
					ifne L2;
				L1:	sconst_1;
					invokestatic 91;		// javacard/framework/APDUException.throwIt(S)V
				L2:	aload_0;
					invokespecial 405;		// javacard/framework/T1APDUImpl.getOutgoingLenSetFlag()Z
					ifeq L4;
				L3:	sconst_1;
					invokestatic 91;		// javacard/framework/APDUException.throwIt(S)V
				L4:	sload_1;
					sspush 256;
					if_scmple L7;
				L5:	aload_0;
					invokespecial 391;		// javacard/framework/T1APDUImpl.getExtendedSupportFlag()Z
					ifne L7;
				L6:	sconst_3;
					invokestatic 91;		// javacard/framework/APDUException.throwIt(S)V
				L7:	sload_1;
					ifge L9;
				L8:	sconst_3;
					invokestatic 91;		// javacard/framework/APDUException.throwIt(S)V
				L9:	sload_1;
					invokestatic 394;		// com/sun/javacard/impl/NativeMethods.t1GetIFSD()S
					sconst_2;
					ssub;
					if_scmple L12;
				L10:	aload_0;
					invokevirtual 406;		// getNoChainingFlag()Z
					ifeq L12;
				L11:	sconst_3;
					invokestatic 91;		// javacard/framework/APDUException.throwIt(S)V
				L12:	aload_0;
					invokespecial 407;		// javacard/framework/T1APDUImpl.setOutgoingLenSetFlag()V
					aload_0;
					sconst_4;
					invokespecial 389;		// javacard/framework/T1APDUImpl.setCurrState(B)V
					aload_0;
					sload_1;
					invokespecial 365;		// javacard/framework/T1APDUImpl.setLr(S)V
					aload_0;
					invokespecial 372;		// javacard/framework/T1APDUImpl.setDeterminedLEFlag()V
					sload_1;
					sspush 256;
					if_scmple L14;
				L13:	aload_0;
					invokespecial 373;		// javacard/framework/T1APDUImpl.setExtendedAPDUFlag()V
				L14:	return;
		}

		.method public receiveBytes(S)S 20 {
			.stack 5;
			.locals 5;

				L0:	aload_0;
					invokespecial 399;		// javacard/framework/T1APDUImpl.getIL()S
					ifne L2;
				L1:	sconst_4;
					invokestatic 91;		// javacard/framework/APDUException.throwIt(S)V
				L2:	aload_0;
					invokespecial 396;		// javacard/framework/T1APDUImpl.getIncomingFlag()Z
					ifeq L4;
				L3:	aload_0;
					invokespecial 374;		// javacard/framework/T1APDUImpl.getOutgoingFlag()Z
					ifeq L5;
				L4:	sconst_1;
					invokestatic 91;		// javacard/framework/APDUException.throwIt(S)V
				L5:	aload_0;
					invokespecial 388;		// javacard/framework/T1APDUImpl.getLc()S
					sstore_2;
				L6:	sload_1;
					ifge L8;
				L7:	sconst_2;
					invokestatic 91;		// javacard/framework/APDUException.throwIt(S)V
				L8:	aload_0;
					invokespecial 398;		// javacard/framework/T1APDUImpl.getPreReadLength()S
					sstore_3;
				L9:	sload_3;
					ifeq L14;
				L10:	aload_0;
					sconst_0;
					invokespecial 362;		// javacard/framework/T1APDUImpl.setPreReadLength(S)V
					sload_2;
					ifgt L12;
				L11:	aload_0;
					sconst_2;
					invokespecial 389;		// javacard/framework/T1APDUImpl.setCurrState(B)V
					goto L13;
				L12:	aload_0;
					sconst_1;
					invokespecial 389;		// javacard/framework/T1APDUImpl.setCurrState(B)V
				L13:	getstatic_a 337;		// reference javacard/framework/T1APDUImpl.ramShortVars
					bspush 7;
					dup2;
					saload;
					sload_3;
					sadd;
					sastore;
					sload_3;
					sreturn;
				L14:	sconst_0;
					sstore 4;
				L15:	sload_2;
					ifle_w L34;
				L16:	sconst_0;
					sstore 5;
				L17:	sload_1;
					sstore 6;
				L18:	sload 6;
					sspush 133;
					if_scmpge L23;
				L19:	sload_2;
					ifle L23;
				L20:	sload 6;
					sspush 133;
					invokestatic 384;		// com/sun/javacard/impl/NativeMethods.t1RcvBlock(SS)S
					sstore 5;
					sload 5;
					ifge L22;
				L21:	sconst_4;
					invokestatic 91;		// javacard/framework/APDUException.throwIt(S)V
				L22:	sload_2;
					sload 5;
					ssub;
					sstore_2;
					sload 6;
					sload 5;
					sadd;
					sstore 6;
					sload 4;
					sload 5;
					sadd;
					sstore 4;
					goto L18;
				L23:	sload_2;
					ifge L30;
				L24:	sload_2;
					sconst_m1;
					if_scmpne L29;
				L25:	aload_0;
					invokespecial 339;		// javacard/framework/T1APDUImpl.getExtendedAPDUFlag()Z
					ifeq L27;
				L26:	aload_0;
					getfield_a_this 33;		// reference javacard/framework/T1APDUImpl.buffer
					sload_1;
					sload 4;
					sadd;
					sconst_1;
					ssub;
					baload;
					sspush 255;
					sand;
					bspush 8;
					sshl;
					invokespecial 363;		// javacard/framework/T1APDUImpl.setLe(S)V
					goto L28;
				L27:	aload_0;
					getfield_a_this 33;		// reference javacard/framework/T1APDUImpl.buffer
					sload_1;
					sload 4;
					sadd;
					sconst_1;
					ssub;
					baload;
					sspush 255;
					sand;
					invokespecial 363;		// javacard/framework/T1APDUImpl.setLe(S)V
				L28:	sconst_0;
					sstore_2;
					sinc 4 -1;
					aload_0;
					invokespecial 372;		// javacard/framework/T1APDUImpl.setDeterminedLEFlag()V
					goto L30;
				L29:	aload_0;
					getfield_a_this 33;		// reference javacard/framework/T1APDUImpl.buffer
					sload_1;
					sload 4;
					sadd;
					sconst_2;
					ssub;
					baload;
					sspush 255;
					sand;
					bspush 8;
					sshl;
					getfield_a_this 33;		// reference javacard/framework/T1APDUImpl.buffer
					sload_1;
					sload 4;
					sadd;
					sconst_1;
					ssub;
					baload;
					sspush 255;
					sand;
					sor;
					invokespecial 363;		// javacard/framework/T1APDUImpl.setLe(S)V
					sconst_0;
					sstore_2;
					sinc 4 -2;
					aload_0;
					invokespecial 372;		// javacard/framework/T1APDUImpl.setDeterminedLEFlag()V
				L30:	aload_0;
					sload_2;
					invokespecial 364;		// javacard/framework/T1APDUImpl.setLc(S)V
					sload_2;
					ifne L32;
				L31:	aload_0;
					sconst_2;
					invokespecial 389;		// javacard/framework/T1APDUImpl.setCurrState(B)V
					goto L33;
				L32:	aload_0;
					sconst_1;
					invokespecial 389;		// javacard/framework/T1APDUImpl.setCurrState(B)V
				L33:	getstatic_a 337;		// reference javacard/framework/T1APDUImpl.ramShortVars
					bspush 7;
					dup2;
					saload;
					sload 4;
					sadd;
					sastore;
					sload 4;
					sreturn;
				L34:	invokestatic 375;		// com/sun/javacard/impl/NativeMethods.t1LastBlockReceived()Z
					ifne L43;
				L35:	sload_1;
					sspush 133;
					invokestatic 384;		// com/sun/javacard/impl/NativeMethods.t1RcvBlock(SS)S
					sstore 4;
					sload 4;
					ifge L37;
				L36:	sconst_4;
					invokestatic 91;		// javacard/framework/APDUException.throwIt(S)V
				L37:	aload_0;
					invokespecial 339;		// javacard/framework/T1APDUImpl.getExtendedAPDUFlag()Z
					ifeq L41;
				L38:	aload_0;
					invokespecial 338;		// javacard/framework/T1APDUImpl.getDeterminedLEFlag()Z
					ifeq L40;
				L39:	aload_0;
					aload_0;
					invokespecial 403;		// javacard/framework/T1APDUImpl.getLe()S
					getfield_a_this 33;		// reference javacard/framework/T1APDUImpl.buffer
					sload_1;
					sload 4;
					sadd;
					sconst_1;
					ssub;
					baload;
					sspush 255;
					sand;
					sor;
					invokespecial 363;		// javacard/framework/T1APDUImpl.setLe(S)V
					goto L43;
				L40:	aload_0;
					getfield_a_this 33;		// reference javacard/framework/T1APDUImpl.buffer
					sload_1;
					sload 4;
					sadd;
					sconst_2;
					ssub;
					baload;
					sspush 255;
					sand;
					bspush 8;
					sshl;
					getfield_a_this 33;		// reference javacard/framework/T1APDUImpl.buffer
					sload_1;
					sload 4;
					sadd;
					sconst_1;
					ssub;
					baload;
					sspush 255;
					sand;
					sor;
					invokespecial 363;		// javacard/framework/T1APDUImpl.setLe(S)V
					aload_0;
					invokespecial 372;		// javacard/framework/T1APDUImpl.setDeterminedLEFlag()V
					goto L43;
				L41:	aload_0;
					invokespecial 338;		// javacard/framework/T1APDUImpl.getDeterminedLEFlag()Z
					ifne L43;
				L42:	aload_0;
					getfield_a_this 33;		// reference javacard/framework/T1APDUImpl.buffer
					sload_1;
					sload 4;
					sadd;
					sconst_1;
					ssub;
					baload;
					sspush 255;
					sand;
					invokespecial 363;		// javacard/framework/T1APDUImpl.setLe(S)V
				L43:	aload_0;
					sconst_0;
					invokespecial 364;		// javacard/framework/T1APDUImpl.setLc(S)V
					aload_0;
					sconst_2;
					invokespecial 389;		// javacard/framework/T1APDUImpl.setCurrState(B)V
					sconst_0;
					sreturn;
		}

		.method public sendBytes(SS)V 21 {
			.stack 4;
			.locals 8;

				L0:	sconst_0;
					sstore_3;
				L1:	sload_1;
					iflt L4;
				L2:	sload_2;
					iflt L4;
				L3:	sload_1;
					sload_2;
					sadd;
					sspush 133;
					if_scmple L5;
				L4:	sconst_2;
					invokestatic 91;		// javacard/framework/APDUException.throwIt(S)V
				L5:	aload_0;
					invokespecial 405;		// javacard/framework/T1APDUImpl.getOutgoingLenSetFlag()Z
					ifne L7;
				L6:	sconst_1;
					invokestatic 91;		// javacard/framework/APDUException.throwIt(S)V
				L7:	sload_2;
					ifne L9;
				L8:	return;
				L9:	aload_0;
					invokespecial 408;		// javacard/framework/T1APDUImpl.getLr()S
					sstore 4;
				L10:	sload_2;
					sload 4;
					if_scmple L12;
				L11:	sconst_1;
					invokestatic 91;		// javacard/framework/APDUException.throwIt(S)V
				L12:	aload_0;
					invokespecial 403;		// javacard/framework/T1APDUImpl.getLe()S
					sstore 5;
				L13:	invokestatic 394;		// com/sun/javacard/impl/NativeMethods.t1GetIFSD()S
					sstore 6;
				L14:	sconst_0;
					sstore 7;
				L15:	sload_1;
					sstore 8;
				L16:	aload_0;
					invokevirtual 406;		// getNoChainingFlag()Z
					ifeq L19;
				L17:	sload 4;
					sload 6;
					if_scmple L19;
				L18:	sconst_1;
					invokestatic 91;		// javacard/framework/APDUException.throwIt(S)V
				L19:	sload_2;
					sstore 9;
				L20:	sload 7;
					sload 9;
					if_scmpge L30;
				L21:	sload 6;
					sstore 10;
				L22:	sload_2;
					sload 6;
					if_scmpge L26;
				L23:	sload_2;
					sstore 10;
					sload 4;
					sload_2;
					if_scmpne L26;
				L24:	sload_2;
					sconst_2;
					sadd;
					sload 6;
					if_scmpgt L26;
				L25:	aload_0;
					sload_2;
					invokespecial 409;		// javacard/framework/T1APDUImpl.setLs(S)V
					aload_0;
					sload 8;
					invokespecial 410;		// javacard/framework/T1APDUImpl.setLo(S)V
					aload_0;
					sconst_0;
					invokespecial 365;		// javacard/framework/T1APDUImpl.setLr(S)V
					aload_0;
					sconst_0;
					invokespecial 363;		// javacard/framework/T1APDUImpl.setLe(S)V
					aload_0;
					bspush 6;
					invokespecial 389;		// javacard/framework/T1APDUImpl.setCurrState(B)V
					aload_0;
					invokespecial 411;		// javacard/framework/T1APDUImpl.setSendInProgressFlag()V
					return;
				L26:	sload 8;
					sload 10;
					sconst_0;
					sconst_0;
					invokestatic 380;		// com/sun/javacard/impl/NativeMethods.t1SndBlockRcvAck(SSZZ)S
					sstore_3;
					sload_3;
					ifeq L28;
				L27:	sconst_4;
					invokestatic 91;		// javacard/framework/APDUException.throwIt(S)V
				L28:	sload 8;
					sload 10;
					sadd;
					sstore 8;
					sload 10;
					sload 7;
					sadd;
					sstore 7;
					sload 4;
					sload 10;
					ssub;
					sstore 4;
					sload_2;
					sload 10;
					ssub;
					sstore_2;
				L29:	goto L20;
				L30:	sload 4;
					sstore 5;
					sload 4;
					ifne L32;
				L31:	aload_0;
					bspush 6;
					invokespecial 389;		// javacard/framework/T1APDUImpl.setCurrState(B)V
					goto L33;
				L32:	aload_0;
					sconst_5;
					invokespecial 389;		// javacard/framework/T1APDUImpl.setCurrState(B)V
				L33:	aload_0;
					sload 5;
					invokespecial 363;		// javacard/framework/T1APDUImpl.setLe(S)V
					aload_0;
					sload 4;
					invokespecial 365;		// javacard/framework/T1APDUImpl.setLr(S)V
					return;
		}

		.method public sendBytesLong([BSS)V 22 {
			.stack 5;
			.locals 1;

				L0:	aload_1;
					sload_2;
					sload_3;
					invokestatic 259;		// com/sun/javacard/impl/NativeMethods.checkArrayArgs([BSS)V
					aload_1;
					invokestatic 51;		// com/sun/javacard/impl/NativeMethods.checkPreviousContextAccess(Ljava/lang/Object;)V
					getfield_a_this 33;		// reference javacard/framework/T1APDUImpl.buffer
					arraylength;
					sstore 4;
				L1:	sload_3;
					ifle L5;
				L2:	sload_3;
					sload 4;
					if_scmpge L4;
				L3:	sload_3;
					sstore 4;
				L4:	aload_1;
					sload_2;
					getfield_a_this 33;		// reference javacard/framework/T1APDUImpl.buffer
					sconst_0;
					sload 4;
					invokestatic 52;		// javacard/framework/Util.arrayCopy([BS[BSS)S
					pop;
					aload_0;
					sconst_0;
					sload 4;
					invokevirtual 412;		// sendBytes(SS)V
					sload_3;
					sload 4;
					ssub;
					sstore_3;
					sload_2;
					sload 4;
					sadd;
					sstore_2;
					goto L1;
				L5:	return;
		}

		.method private setIncoming()V {
			.stack 2;
			.locals 0;

				L0:	aload_0;
					invokespecial 398;		// javacard/framework/T1APDUImpl.getPreReadLength()S
					ifeq L2;
				L1:	aload_0;
					invokespecial 397;		// javacard/framework/T1APDUImpl.setIncomingFlag()V
					return;
				L2:	aload_0;
					invokespecial 396;		// javacard/framework/T1APDUImpl.getIncomingFlag()Z
					ifne L4;
				L3:	aload_0;
					invokespecial 374;		// javacard/framework/T1APDUImpl.getOutgoingFlag()Z
					ifeq L5;
				L4:	sconst_1;
					invokestatic 91;		// javacard/framework/APDUException.throwIt(S)V
				L5:	aload_0;
					invokespecial 397;		// javacard/framework/T1APDUImpl.setIncomingFlag()V
					aload_0;
					invokespecial 391;		// javacard/framework/T1APDUImpl.getExtendedSupportFlag()Z
					ifne L8;
				L6:	aload_0;
					invokespecial 388;		// javacard/framework/T1APDUImpl.getLc()S
					sspush 256;
					if_scmple L8;
				L7:	sspush 26368;
					invokestatic 91;		// javacard/framework/APDUException.throwIt(S)V
				L8:	aload_0;
					invokespecial 388;		// javacard/framework/T1APDUImpl.getLc()S
					ifge L10;
				L9:	sspush 26368;
					invokestatic 91;		// javacard/framework/APDUException.throwIt(S)V
				L10:	return;
		}

		.method public setIncomingAndReceive()S 23 {
			.stack 2;
			.locals 0;

				L0:	aload_0;
					invokespecial 413;		// javacard/framework/T1APDUImpl.setIncoming()V
					aload_0;
					invokespecial 339;		// javacard/framework/T1APDUImpl.getExtendedAPDUFlag()Z
					ifeq L2;
				L1:	aload_0;
					bspush 7;
					invokevirtual 414;		// receiveBytes(S)S
					sreturn;
				L2:	aload_0;
					sconst_5;
					invokevirtual 414;		// receiveBytes(S)S
					sreturn;
		}

		.method public setOutgoingAndSend(SS)V 24 {
			.stack 3;
			.locals 0;

				L0:	aload_0;
					invokevirtual 415;		// setOutgoing()S
					pop;
					aload_0;
					sload_2;
					invokevirtual 416;		// setOutgoingLength(S)V
					aload_0;
					sload_1;
					sload_2;
					invokevirtual 412;		// sendBytes(SS)V
					return;
		}

		.method public getCurrentState()B 25 {
			.stack 1;
			.locals 0;

				L0:	aload_0;
					invokespecial 417;		// javacard/framework/T1APDUImpl.getCurrState()B
					sreturn;
		}

		.method public getCurrentAPDUBuffer()[B 26 {
			.stack 1;
			.locals 0;

				L0:	getstatic_a 352;		// reference javacard/framework/T1APDUImpl.theAPDU
					invokeinterface 1 81 7;		// javacard/framework/APDUComm
					areturn;
		}

		.method public markExtendedSupport(Z)V 27 {
			.stack 1;
			.locals 0;

				L0:	sload_1;
					ifne L3;
				L1:	aload_0;
					invokespecial 385;		// javacard/framework/T1APDUImpl.resetExtendedSupportFlag()V
					aload_0;
					invokespecial 339;		// javacard/framework/T1APDUImpl.getExtendedAPDUFlag()Z
					ifeq L4;
				L2:	sspush 26368;
					invokestatic 78;		// javacard/framework/ISOException.throwIt(S)V
					goto L4;
				L3:	aload_0;
					invokespecial 418;		// javacard/framework/T1APDUImpl.setExtendedSupportFlag()V
				L4:	return;
		}

		.method public getIncomingLength()S 28 {
			.stack 1;
			.locals 0;

				L0:	aload_0;
					invokespecial 399;		// javacard/framework/T1APDUImpl.getIL()S
					sreturn;
		}

		.method public getOffsetCdata()S 29 {
			.stack 1;
			.locals 0;

				L0:	aload_0;
					invokespecial 339;		// javacard/framework/T1APDUImpl.getExtendedAPDUFlag()Z
					ifne L2;
				L1:	sconst_5;
					sreturn;
				L2:	bspush 7;
					sreturn;
		}

		.method public verifyLe()V 30 {
			.stack 1;
			.locals 0;

				L0:	aload_0;
					invokespecial 403;		// javacard/framework/T1APDUImpl.getLe()S
					ifge L2;
				L1:	sspush 26368;
					invokestatic 78;		// javacard/framework/ISOException.throwIt(S)V
				L2:	return;
		}

	}

	.class public TransactionException 14 extends CardRuntimeException {

		.fields {
			public static final short IN_PROGRESS = 1;		// S
			public static final short NOT_IN_PROGRESS = 2;		// S
			public static final short BUFFER_FULL = 3;		// S
			public static final short INTERNAL_FAILURE = 4;		// S
			public static final short ILLEGAL_USE = 5;		// S
			private static TransactionException systemInstance;		// Ljavacard/framework/TransactionException;
		}

		.publicMethodTable 3 3 {
			equals(Ljava/lang/Object;)Z 0;
			getReason()S 1;
			setReason(S)V 2;
		}

		.packageMethodTable 0 {
		}

		.method public <init>(S)V 0 {
			.stack 2;
			.locals 0;

				L0:	aload_0;
					sload_1;
					invokespecial 48;		// javacard/framework/CardRuntimeException.<init>(S)V
					getstatic_a 419;		// reference javacard/framework/TransactionException.systemInstance
					ifnonnull L2;
				L1:	aload_0;
					putstatic_a 419;		// reference javacard/framework/TransactionException.systemInstance
				L2:	return;
		}

		.method public static throwIt(S)V 1 {
			.stack 2;
			.locals 0;

				L0:	getstatic_a 419;		// reference javacard/framework/TransactionException.systemInstance
					sload_0;
					invokevirtual 420;		// setReason(S)V
					getstatic_a 419;		// reference javacard/framework/TransactionException.systemInstance
					athrow;
		}

	}

	.class public UserException 15 extends CardException {

		.fields {
			private static UserException systemInstance;		// Ljavacard/framework/UserException;
		}

		.publicMethodTable 3 3 {
			equals(Ljava/lang/Object;)Z 0;
			getReason()S 1;
			setReason(S)V 2;
		}

		.packageMethodTable 0 {
		}

		.method public <init>()V 0 {
			.stack 2;
			.locals 0;

				L0:	aload_0;
					sconst_0;
					invokespecial 193;		// javacard/framework/UserException.<init>(S)V
					return;
		}

		.method public <init>(S)V 1 {
			.stack 2;
			.locals 0;

				L0:	aload_0;
					sload_1;
					invokespecial 186;		// javacard/framework/CardException.<init>(S)V
					getstatic_a 421;		// reference javacard/framework/UserException.systemInstance
					ifnonnull L2;
				L1:	aload_0;
					putstatic_a 421;		// reference javacard/framework/UserException.systemInstance
				L2:	return;
		}

		.method public static throwIt(S)V 2 {
			.stack 2;
			.locals 0;

				L0:	getstatic_a 421;		// reference javacard/framework/UserException.systemInstance
					sload_0;
					invokevirtual 422;		// setReason(S)V
					getstatic_a 421;		// reference javacard/framework/UserException.systemInstance
					athrow;
		}

	}

	.class public Util 16 extends 0.0 {		// extends java/lang/Object

		.publicMethodTable 1 1 {
			equals(Ljava/lang/Object;)Z 0;
		}

		.packageMethodTable 0 {
		}

		.method public static final native arrayCopy([BS[BSS)S 1 {
		}

		.method public static final native arrayCopyNonAtomic([BS[BSS)S 2 {
		}

		.method public static final native arrayFill([BSSB)S 7 {
		}

		.method public static final native arrayFillNonAtomic([BSSB)S 3 {
		}

		.method public static final native arrayCompare([BS[BSS)B 0 {
		}

		.method public static final makeShort(BB)S 5 {
			.stack 3;
			.locals 0;

				L0:	sload_0;
					bspush 8;
					sshl;
					sload_1;
					sspush 255;
					sand;
					sadd;
					sreturn;
		}

		.method public static final getShort([BS)S 4 {
			.stack 4;
			.locals 0;

				L0:	aload_0;
					sload_1;
					baload;
					bspush 8;
					sshl;
					aload_0;
					sload_1;
					sconst_1;
					sadd;
					baload;
					sspush 255;
					sand;
					sadd;
					sreturn;
		}

		.method public static final native setShort([BSS)S 6 {
		}

		.method  <init>()V {
			.stack 1;
			.locals 0;

				L0:	aload_0;
					invokespecial 254;		// java/lang/Object.<init>()V
					return;
		}

	}

}
